Workbook
Name Alabama: 'Rate Tables'!$QX$1:$QX$67
Name Arizona: 'Rate Tables'!$QY$1:$QY$15
Name Arkansas: 'Rate Tables'!$QZ$1:$QZ$75
Name Colorado: 'Rate Tables'!$RA$1:$RA$64
Name Connecticut: 'Rate Tables'!$RB$1:$RB$8
Name Delaware: 'Rate Tables'!$RC$1:$RC$3
Name DV_State: 'Rate Tables'!$QW$2:$QW$39
Name Florida: 'Rate Tables'!$RD$1:$RD$71
Name Georgia: 'Rate Tables'!$RE$1:$RE$159
Name HO6_Alabama: 'Rate Tables'!$SK$1:$SK$8
Name HO6_Connecticut: 'Rate Tables'!$SL$1:$SL$8
Name HO6_Delaware: 'Rate Tables'!$SM$1:$SM$2
Name HO6_DV_State: 'Rate Tables'!$SJ$1:$SJ$19
Name HO6_Florida: 'Rate Tables'!$SN$1:$SN$67
Name HO6_Georgia: 'Rate Tables'!$SO$1:$SO$14
Name HO6_Louisiana: 'Rate Tables'!$SP$1:$SP$23
Name HO6_Maine: 'Rate Tables'!$SQ$1:$SQ$15
Name HO6_Maryland: 'Rate Tables'!$SR$1:$SR$5
Name HO6_Massachusetts: 'Rate Tables'!$SS$1:$SS$10
Name HO6_Mississippi: 'Rate Tables'!$ST$1:$ST$6
Name HO6_New_Hampshire: 'Rate Tables'!$SU$1:$SU$6
Name HO6_New_Jersey: 'Rate Tables'!$SV$1:$SV$12
Name HO6_New_York: 'Rate Tables'!$SW$1:$SW$10
Name HO6_North_Carolina: 'Rate Tables'!$SX$1:$SX$26
Name HO6_Rhode_Island: 'Rate Tables'!$SY$1:$SY$5
Name HO6_South_Carolina: 'Rate Tables'!$SZ$1:$SZ$13
Name HO6_Texas: 'Rate Tables'!$TA$1:$TA$27
Name HO6_Virginia: 'Rate Tables'!$TB$1:$TB$14
Name HO6_Washington_DC: 'Rate Tables'!$TC$1:$TC$1
Name Idaho: 'Rate Tables'!$RF$1:$RF$44
Name Illinois: 'Rate Tables'!$RG$1:$RG$102
Name Indiana: 'Rate Tables'!$RH$1:$RH$92
Name Iowa: 'Rate Tables'!$RI$1:$RI$99
Name Kansas: 'Rate Tables'!$RJ$1:$RJ$105
Name Louisiana: 'Rate Tables'!$RK$1:$RK$74
Name Maine: 'Rate Tables'!$RL$1:$RL$16
Name Maryland: 'Rate Tables'!$RM$1:$RM$24
Name Massachusetts: 'Rate Tables'!$RN$1:$RN$14
Name Michigan: 'Rate Tables'!$RO$1:$RO$83
Name Minnesota: 'Rate Tables'!$RP$1:$RP$87
Name Mississippi: 'Rate Tables'!$RQ$1:$RQ$82
Name Missouri: 'Rate Tables'!$RR$1:$RR$115
Name Nevada: 'Rate Tables'!$RS$1:$RS$17
Name New_Hampshire: 'Rate Tables'!$RT$1:$RT$10
Name New_Jersey: 'Rate Tables'!$RU$1:$RU$21
Name New_Mexico: 'Rate Tables'!$RV$1:$RV$33
Name New_York: 'Rate Tables'!$RW$1:$RW$62
Name North_Carolina: 'Rate Tables'!$RX$1:$RX$100
Name Ohio: 'Rate Tables'!$RY$1:$RY$88
Name Oregon: 'Rate Tables'!$RZ$1:$RZ$36
Name Rhode_Island: 'Rate Tables'!$SA$1:$SA$5
Name South_Carolina: 'Rate Tables'!$SB$1:$SB$46
Name Tennessee: 'Rate Tables'!$SC$1:$SC$95
Name Texas: 'Rate Tables'!$SD$1:$SD$254
Name Utah: 'Rate Tables'!$SE$1:$SE$29
Name Virginia: 'Rate Tables'!$SF$1:$SF$140
Name Washington: 'Rate Tables'!$SG$1:$SG$39
Name Washington_DC: 'Rate Tables'!$SH$1:$SH$1
Name Wisconsin: 'Rate Tables'!$SI$1:$SI$72

Sheet Rater
B1: NEW BUSINESS - INPUT VALUES | D1: PARENT ENTITY NAME | E1: ENTITY NAME | F1: ATTRIBUTE NAME | G1: ATTRIBUTE DATA TYPE | H1: ENTITY DATA TYPE | I1: ENTITY TYPE | J1: OPTIONAL/MANDATORY | K1: FALLBACK VALUE | L1: HAS ADDITIONAL CONDITION ADDED (YES/NO) | M1: Apply Prorata | N1: REFERENCE / NOTES | O1: Iterated | P1: Attribute Display Name
A2: =CELL("address",B2) -> $B$2 | B2: Applicable start date | C2: 06/21/2026 | D2: Root | E2: SolartisInsuredV2 | F2: RateLookupDate | G2: Date | H2: Object | I2: Req/Resp | J2: Mandatory | K2: No | L2: No | O2: No | P2: RateLookupDate
A3: =CELL("address",B3) -> $B$3 | B3: Effective date | C3: 46178 | D3: Root | E3: SolartisInsuredV2 | F3: PolicyEffectiveDate | G3: Date | H3: Object | I3: Req/Resp | J3: Mandatory | K3: No | L3: No | O3: No | P3: PolicyEffectiveDate
A4: =CELL("address",B4) -> $B$4 | B4: Expiration date | C4: 46543 | D4: Root | E4: SolartisInsuredV2 | F4: PolicyExpirationDate | G4: Date | H4: Object | I4: Req/Resp | J4: Mandatory | K4: No | L4: No | O4: No | P4: PolicyExpirationDate
A5: =CELL("address",B5) -> $B$5 | B5: Product Data structure | C5: PersonalLines_Property_V2 | D5: Root | E5: SolartisInsuredV2 | F5: ProductName | G5: Varchar | H5: Object | I5: Req/Resp | J5: Mandatory | K5: No | L5: No | O5: No | P5: ProductName
A6: =CELL("address",B6) -> $B$6 | B6: Product Data Structure Version | C6: PersonalLines_Property_V2_Hierarchy_1.0 | D6: Root | E6: SolartisInsuredV2 | F6: ProductVersionNumber | G6: Varchar | H6: Object | I6: Req/Resp | J6: Mandatory | K6: No | L6: No | O6: No | P6: ProductVersionNumber
A7: =CELL("address",B7) -> $B$7 | B7: State Code | C7: =IF(C106="","",LEFT(C106,2)) -> FL | D7: Root | E7: SolartisInsuredV2 | F7: CarrierName | G7: VarChar | H7: Object | I7: Req/Resp | J7: Mandatory | K7: No | L7: No | O7: No | P7: CarrierName
A8: =CELL("address",B8) -> $B$8 | B8: Carrier Name | C8: Lloyds | D8: Root | E8: SolartisInsuredV2 | F8: SublineName | G8: VarChar | H8: Object | I8: Req/Resp | J8: Mandatory | K8: No | L8: No | O8: No | P8: SublineName
A9: =CELL("address",B9) -> $B$9 | B9: Subline Name/Policy Form | C9: HO3 | D9: Root | E9: SolartisInsuredV2 | F9: Company | G9: Map | H9: Object | I9: Req/Resp | J9: Mandatory | K9: No | L9: No | O9: No | P9: Company
A10: =CELL("address",B10) -> $B$10 | B10: Company Short Name | C10: RTPL | D10: Insured | E10: Location | F10: StateRegionCode | G10: VarChar | H10: List | I10: Req/Resp | J10: Mandatory | K10: No | L10: No | O10: No | P10: StateRegionCode
A11: =CELL("address",F11) -> $F$11 | B11: COVERAGE DETAILS | I11: .
A12: =CELL("address",F12) -> $F$12 | B12: Loss Settlement-Dwelling | C12: RCV | D12: Building | E12: Coverage | F12: DwellingValuation | G12: VarChar | H12: List | I12: Req/Resp | J12: Mandatory | K12: No | L12: No | O12: No | P12: DwellingValuation
A13: =CELL("address",F13) -> $F$13 | B13: Loss Settlement-Contents | C13: RCV | D13: Building | E13: Coverage | F13: PersonalPropertyValuation | G13: VarChar | H13: List | I13: Req/Resp | J13: Mandatory | K13: No | L13: No | O13: No | P13: PersonalPropertyValuation
A14: =CELL("address",F14) -> $F$14 | B14: Transaction Type | C14: New_Business | D14: Root | E14: SolartisInsuredV2 | F14: TransactionType | G14: VarChar | H14: Object | I14: Req/Resp | J14: Mandatory | K14: No | L14: No | O14: No | P14: TransactionType
A15: =CELL("address",F15) -> $F$15 | B15: State | C15: Florida | D15: Insured | E15: Location | F15: State | G15: VarChar | H15: List | I15: Req/Resp | J15: Mandatory | K15: No | L15: No | O15: No | P15: State
A16: =CELL("address",F16) -> $F$16 | B16: County | C16: Brevard | D16: Insured | E16: Location | F16: County | G16: VarChar | H16: List | I16: Req/Resp | J16: Mandatory | K16: No | L16: No | O16: No | P16: County
A17: =CELL("address",F17) -> $F$17 | B17: Zip Code | C17: 31404 | D17: Insured | E17: Location | F17: Zipcode1 | G17: VarChar | H17: List | I17: Req/Resp | J17: Mandatory | K17: No | L17: No | O17: No | P17: Zipcode1
A18: =CELL("address",F18) -> $F$18 | B18: Coverage A/Dwelling Coverage | C18: 274000 | D18: Coverage | E18: DwellingCoverage | F18: Limit | G18: Decimal | H18: Map | I18: Req/Resp | J18: Mandatory | K18: 0 | L18: No | O18: No | P18: Limit
A19: =CELL("address",F19) -> $F$19 | B19: Coverage B/Other Structure Coverage | C19: 27400 | D19: Coverage | E19: OtherStructureCoverage | F19: Limit | G19: Decimal | H19: Map | I19: Req/Resp | J19: Mandatory | K19: 0 | L19: No | O19: No | P19: Limit
A20: =CELL("address",F20) -> $F$20 | B20: Coverage C/Personal Property Coverage | C20: 137000 | D20: Coverage | E20: PersonalPropertyCoverage | F20: Limit | G20: Decimal | H20: Map | I20: Req/Resp | J20: Optional | K20: 0 | L20: No | O20: No | P20: Limit
A21: =CELL("address",F21) -> $F$21 | B21: Coverage D/Loss Of Use Coverage | C21: 54800 | D21: Coverage | E21: LossOfUseCoverage | F21: Limit | G21: Decimal | H21: Map | I21: Req/Resp | J21: Mandatory | K21: 0 | L21: No | O21: No | P21: Limit
A22: =CELL("address",F22) -> $F$22 | B22: Distance To Coast | C22: 5 - 10 Mi. | D22: Location | E22: Building | F22: CoastalWaterDistance | G22: Decimal | H22: List | I22: Req/Resp | J22: Mandatory | K22: 0 | L22: No | O22: No | P22: CoastalWaterDistance
A23: =CELL("address",F23) -> $F$23 | B23: Year Built | C23: 2017 | D23: Location | E23: Building | F23: DateBuilt | G23: Int | H23: List | I23: Req/Resp | J23: Mandatory | K23: 0 | L23: No | O23: No | P23: DateBuilt
A24: =CELL("address",F24) -> $F$24 | B24: RISK FACTORS | I24: .
A25: =CELL("address",F25) -> $F$25 | B25: Construction Type | C25: Frame | D25: Location | E25: Building | F25: ConstructionType | G25: VarChar | H25: List | I25: Req/Resp | J25: Mandatory | K25: No | L25: No | O25: No | P25: ConstructionType
A26: =CELL("address",F26) -> $F$26 | B26: Occupancy Type | C26: Primary | D26: Location | E26: Building | F26: Occupancy | G26: VarChar | H26: List | I26: Req/Resp | J26: Mandatory | K26: No | L26: No | O26: No | P26: Occupancy
A27: =CELL("address",F27) -> $F$27 | B27: Age of Dwelling (In Years)/ AgeofHome | C27: 9 | D27: Location | E27: Building | F27: AgeOfHome | G27: Int | H27: List | I27: Req/Resp | J27: Mandatory | K27: 0 | L27: No | O27: No | P27: AgeOfHome
A28: =CELL("address",F28) -> $F$28 | B28: Age of Roof (In Years) | C28: 6 - 10 Years | D28: Location | E28: Building | F28: AgeOfRoof | G28: Int | H28: List | I28: Req/Resp | J28: Mandatory | K28: 0 | L28: No | O28: No | P28: AgeOfRoof
A29: =CELL("address",F29) -> $F$29 | B29: Number Of Stories | C29: 1.5 | D29: Location | E29: Building | F29: NumberOfStories | G29: Decimal | H29: List | I29: Req/Resp | J29: Mandatory | K29: 0 | L29: No | O29: No | P29: NumberOfStories
A30: =CELL("address",F30) -> $F$30 | B30: Number of claims in the past 5 years | C30: 1 | D30: Location | E30: Building | F30: NumberofLosses | G30: Integer | H30: List | I30: Req/Resp | J30: Mandatory | K30: 0 | L30: No | O30: No | P30: NumberOfLosses
A31: =CELL("address",F31) -> $F$31 | B31: Coverage A Band Credit | C31: $250,000 - $349,999 | D31: Location | E31: Building | F31: CoverageABandCredit | G31: Decimal | H31: List | I31: Req/Resp | J31: Mandatory | K31: 0 | L31: No | O31: No | P31: CoverageABandCredit
A32: =CELL("address",F32) -> $F$32 | B32: Extended Replacement Cost | C32: No | D32: Location | E32: Building | F32: ExtendedReplacementCost | G32: VarChar | H32: List | I32: Req/Resp | J32: Mandatory | K32: No | L32: No | O32: No | P32: ExtendedReplacementCost
A33: =CELL("address",F33) -> $F$33 | B33: Number Of Families | C33: 1 | D33: Location | E33: Building | F33: NumberOfFamilies | G33: VarChar | H33: List | I33: Req/Resp | J33: Mandatory | K33: No | L33: No | O33: No | P33: NumberOfFamilies
A34: =CELL("address",F34) -> $F$34 | B34: Protection Class | C34: 2 | D34: Location | E34: Building | F34: ProtectionClass | G34: VarChar | H34: List | I34: Req/Resp | J34: Mandatory | K34: No | L34: No | O34: No | P34: ProtectionClass
A35: =CELL("address",F35) -> $F$35 | B35: Central Station Alarm | C35: None | D35: Location | E35: Building | F35: Alarm | G35: VarChar | H35: List | I35: Req/Resp | J35: Mandatory | K35: No | L35: No | O35: No | P35: Alarm
A36: =CELL("address",F36) -> $F$36 | B36: Water Damage SubLimit | C36: Full Policy Limits | D36: Coverage | E36: WaterDamageSublimit | F36: Limit | G36: Decimal | H36: Map | I36: Req/Resp | J36: Mandatory | K36: 0 | L36: No | O36: No | P36: Limit
A37: =CELL("address",F37) -> $F$37 | B37: AOP Deductible | C37: 1500 | D37: Coverage | E37: AOPDeductible | F37: Limit | G37: Decimal | H37: Map | I37: Req/Resp | J37: Mandatory | K37: 0 | L37: No | O37: No | P37: Limit
A38: =CELL("address",F38) -> $F$38 | B38: Water Damage Deductible | C38: Equal to AOP | D38: Coverage | E38: WaterDamageDeductible | F38: Limit | G38: Decimal | H38: Map | I38: Req/Resp | J38: Mandatory | K38: 0 | L38: No | O38: No | P38: Limit
A39: =CELL("address",F39) -> $F$39 | B39: INSURANCE SCORE | I39: .
A40: =CELL("address",F40) -> $F$40 | B40: Insurance Score Range | C40: 614-652 | D40: Account | E40: Insured | F40: InsuranceScoreRange | G40: String | H40: List | I40: Req/Resp | J40: Mandatory | K40: No | L40: No | O40: No | P40: InsuranceScoreRange
A41: =CELL("address",F41) -> $F$41 | B41: Insurance Score Last Run Date | C41: 06/21/2026 | D41: Account | E41: Insured | F41: InsuranceScoreFetchedDate | G41: Date | H41: List | I41: Req/Resp | J41: Mandatory | K41: 0 | L41: No | O41: No | P41: InsuranceScoreFetchedDate
A42: =CELL("address",F42) -> $F$42 | B42: WIND COVERAGE | I42: .
A43: =CELL("address",F43) -> $F$43 | B43: Is Wind Coverage Selected? | C43: Yes | D43: Coverage | E43: PLWindCoverage | F43: CoverageSelected | G43: Varchar | H43: Map | I43: Req/Resp | J43: Optional | K43: No | L43: No | O43: No | P43: CoverageSelected
A44: =CELL("address",F44) -> $F$44 | B44: Gross AAL Amount (From Third Party) | C44: 431.56 | D44: Building | E44: Coverage | F44: RMSModeledPremium | G44: Decimal | H44: List | I44: Req/Resp | J44: Mandatory | K44: 0 | L44: No | O44: No | P44: RMSModeledPremium
A45: =CELL("address",F45) -> $F$45 | B45: Wind Deductible | C45: Greater of $5,000 or 2% | D45: Building | E45: Coverage | F45: WindDeductiblePercentage | G45: Decimal | H45: List | I45: Req/Resp | J45: Mandatory | K45: 0 | L45: No | O45: No | P45: WindDeductiblePercentage
A46: =CELL("address",F46) -> $F$46 | B46: UNDERWRITER ADJUSTMENT FACTORS | I46: .
A47: =CELL("address",F47) -> $F$47 | B47: Miscellaneous Surcharge Factor | C47: 0 | D47: Building | E47: Coverage | F47: MiscsurchargeFactor | G47: Decimal | H47: List | I47: Req/Resp | J47: Mandatory | K47: 1 | L47: No | O47: No | P47: MiscsurchargeFactor
A48: =CELL("address",F48) -> $F$48 | B48: Miscellaneous Credit Factor | C48: -0.1 | D48: Location | E48: Building | F48: Creditpercent | G48: Decimal | H48: List | I48: Req/Resp | J48: Mandatory | K48: 1 | L48: No | O48: No | P48: Creditpercent
A49: =CELL("address",F49) -> $F$49 | B49: OPTIONAL COVERAGES | I49: .
A50: =CELL("address",F50) -> $F$50 | B50: Limited Mold | C50: 5000 | D50: Coverage | E50: LimitedMoldCoverage | F50: Limit | G50: Decimal | H50: Map | I50: Req/Resp | J50: Optional | K50: 0 | L50: No | O50: No | P50: Limit
A51: =CELL("address",F51) -> $F$51 | B51: Water Back-Up | C51: 5000 | D51: Coverage | E51: WaterBackupCoverage | F51: Limit | G51: Decimal | H51: Map | I51: Req/Resp | J51: Optional | K51: 0 | L51: No | O51: No | P51: Limit
A52: =CELL("address",F52) -> $F$52 | B52: Identity Fraud | C52: No | D52: Coverage | E52: IdentityFraudCoverage | F52: CoverageSelected | G52: VarChar | H52: Map | I52: Req/Resp | J52: Optional | K52: No | L52: No | O52: No | P52: CoverageSelected
A53: =CELL("address",F53) -> $F$53 | B53: Special Coverage A | C53: No | D53: Coverage | E53: SpecialCoverageA | F53: CoverageSelected | G53: VarChar | H53: Map | I53: Req/Resp | J53: Optional | K53: No | L53: No | O53: No | P53: CoverageSelected
A54: =CELL("address",F54) -> $F$54 | B54: Special Coverage C | C54: No | D54: Coverage | E54: SpecialCoverageC | F54: CoverageSelected | G54: VarChar | H54: Map | I54: Req/Resp | J54: Optional | K54: No | L54: No | O54: No | P54: CoverageSelected
A55: =CELL("address",F55) -> $F$55 | B55: Replacement Cost On Contents | C55: No | D55: Coverage | E55: ReplacementCostOnContentsCoverage | F55: CoverageSelected | G55: VarChar | H55: Map | I55: Req/Resp | J55: Optional | K55: No | L55: No | O55: No | P55: CoverageSelected
A56: =CELL("address",F56) -> $F$56 | B56: Increased Loss Assessment | C56: Not Applicable | D56: Coverage | E56: IncreasedLossAssessment | F56: Limit | G56: Decimal | H56: Map | I56: Req/Resp | J56: Optional | K56: 0 | L56: No | O56: No | P56: Limit
A57: =CELL("address",F57) -> $F$57 | B57: Personal Injury | C57: No | D57: Coverage | E57: PersonalInjuryCoverage | F57: CoverageSelected | G57: VarChar | H57: Map | I57: Req/Resp | J57: Optional | K57: No | L57: No | O57: No | P57: CoverageSelected
A58: =CELL("address",F58) -> $F$58 | B58: South Carolina Earthquake Coverage | C58: No | D58: Coverage | E58: EarthquakeCoverage | F58: CoverageSelected | G58: VarChar | H58: Map | I58: Req/Resp | J58: Optional | K58: No | L58: No | O58: No | P58: CoverageSelected
A59: =CELL("address",F59) -> $F$59 | B59: South Carolina Earthquake (Deductible) | C59: EXCLUDED | D59: Coverage | E59: EarthquakeCoverage | F59: Deductible | G59: Decimal | H59: Map | I59: Req/Resp | J59: Optional | K59: 0 | L59: No | O59: No | P59: EarthquakeDeductiblePercentage
A60: =CELL("address",F60) -> $F$60 | B60: Earthquake Coverage | C60: Excluded | D60: Coverage | E60: EarthquakeCoverage | F60: CoverageSelected | G60: VarChar | H60: Map | I60: Req/Resp | J60: Optional | K60: No | L60: No | O60: No | P60: CoverageSelected
A61: =CELL("address",F61) -> $F$61 | B61: SCHEDULED PERSONAL PROPERTY | I61: .
A62: =CELL("address",F62) -> $F$62 | B62: Scheduled Personal Property – Men's Jewelry (Item Value) | C62: 0 | D62: Building | E62: PersonalProperty | F62: ItemValue | G62: Decimal | H62: List | I62: Req/Resp | J62: Optional | K62: 0 | L62: No | O62: No | P62: ItemValue
A63: =CELL("address",F63) -> $F$63 | B63: Scheduled Personal Property – Women's Jewelry (Item Value) | C63: 0 | D63: Building | E63: PersonalProperty | F63: ItemValue | G63: Decimal | H63: List | I63: Req/Resp | J63: Optional | K63: 0 | L63: No | O63: No | P63: ItemValue
A64: =CELL("address",F64) -> $F$64 | B64: Scheduled Personal Property – Jewelry (Item Value) | C64: 0 | D64: Building | E64: PersonalProperty | F64: ItemValue | G64: Decimal | H64: List | I64: Req/Resp | J64: Optional | K64: 0 | L64: No | O64: No | P64: ItemValue
A65: =CELL("address",F65) -> $F$65 | B65: Scheduled Personal Property – Furs (Item Value) | C65: 0 | D65: Building | E65: PersonalProperty | F65: ItemValue | G65: Decimal | H65: List | I65: Req/Resp | J65: Optional | K65: 0 | L65: No | O65: No | P65: ItemValue
A66: =CELL("address",F66) -> $F$66 | B66: Scheduled Personal Property – Cameras (Item Value) | C66: 0 | D66: Building | E66: PersonalProperty | F66: ItemValue | G66: Decimal | H66: List | I66: Req/Resp | J66: Optional | K66: 0 | L66: No | O66: No | P66: ItemValue
A67: =CELL("address",F67) -> $F$67 | B67: Scheduled Personal Property – Musical Instruments (Item Value) | C67: 0 | D67: Building | E67: PersonalProperty | F67: ItemValue | G67: Decimal | H67: List | I67: Req/Resp | J67: Optional | K67: 0 | L67: No | O67: No | P67: ItemValue
A68: =CELL("address",F68) -> $F$68 | B68: Scheduled Personal Property – Silverware (Item Value) | C68: 0 | D68: Building | E68: PersonalProperty | F68: ItemValue | G68: Decimal | H68: List | I68: Req/Resp | J68: Optional | K68: 0 | L68: No | O68: No | P68: ItemValue
A69: =CELL("address",F69) -> $F$69 | B69: Scheduled Personal Property – Golf Equipment (Item Value) | C69: 0 | D69: Building | E69: PersonalProperty | F69: ItemValue | G69: Decimal | H69: List | I69: Req/Resp | J69: Optional | K69: 0 | L69: No | O69: No | P69: ItemValue
A70: =CELL("address",F70) -> $F$70 | B70: Scheduled Personal Property – Fine Art (Item Value) | C70: 0 | D70: Building | E70: PersonalProperty | F70: ItemValue | G70: Decimal | H70: List | I70: Req/Resp | J70: Optional | K70: 0 | L70: No | O70: No | P70: ItemValue
A71: =CELL("address",F71) -> $F$71 | B71: Scheduled Personal Property – Postage Stamps (Item Value) | C71: 0 | D71: Building | E71: PersonalProperty | F71: ItemValue | G71: Decimal | H71: List | I71: Req/Resp | J71: Optional | K71: 0 | L71: No | O71: No | P71: ItemValue
A72: =CELL("address",F72) -> $F$72 | B72: Scheduled Personal Property – Coins (Item Value) | C72: 0 | D72: Building | E72: PersonalProperty | F72: ItemValue | G72: Decimal | H72: List | I72: Req/Resp | J72: Optional | K72: 0 | L72: No | O72: No | P72: ItemValue
A73: =CELL("address",F73) -> $F$73 | B73: Scheduled Personal Property – Guns & Firearms (Item Value) | C73: 0 | D73: Building | E73: PersonalProperty | F73: ItemValue | G73: Decimal | H73: List | I73: Req/Resp | J73: Optional | K73: 0 | L73: No | O73: No | P73: ItemValue
... A75: =CELL("address",F75) -> $F$75 | B75: Scheduled Personal Property – Miscellaneous Classes (Item Value) | C75: 0 | D75: Building | E75: PersonalProperty | F75: ItemValue | G75: Decimal | H75: List | I75: Req/Resp | J75: Optional | K75: 0 | L75: No | O75: No | P75: ItemValue
A76: =CELL("address",F76) -> $F$76 | B76: DP / BUILDERS RISK OPTIONS | I76: .
A77: =CELL("address",F77) -> $F$77 | B77: Theft Coverage | C77: Excluded | D77: Coverage | E77: TheftCoverage | F77: Limit | G77: Decimal | H77: Map | I77: Req/Resp | J77: Optional | K77: 0 | L77: No | O77: No | P77: Limit
A78: =CELL("address",F78) -> $F$78 | B78: Vandalism & Malicious Mischief Coverage (Applies to DP-1 Only) | C78: Excluded | D78: Coverage | E78: VandalismOrMaliciousMischiefCoverage | F78: CoverageSelected | G78: VarChar | H78: Map | I78: Req/Resp | J78: Optional | K78: No | L78: No | O78: No | P78: CoverageSelected
A79: =CELL("address",F79) -> $F$79 | B79: Extended Coverage (Applies to DP-1 Only) | C79: Excluded | D79: Coverage | E79: ExtendedCoverage | F79: CoverageSelected | G79: VarChar | H79: Map | I79: Req/Resp | J79: Optional | K79: No | L79: No | O79: No | P79: CoverageSelected
A80: =CELL("address",F80) -> $F$80 | B80: LIABILITY COVERAGE | I80: .
A81: =CELL("address",F81) -> $F$81 | B81: Liability Limit | C81: 300000 | D81: Coverage | E81: PersonalLiabilityCoverageL | F81: Limit | G81: Decimal | H81: Map | I81: Req/Resp | J81: Mandatory | K81: 0 | L81: No | O81: No | P81: Limit
A82: =CELL("address",F82) -> $F$82 | B82: Medical Payments | C82: 1000 | D82: Coverage | E82: MedicalPaymentsCoverageM | F82: Limit | G82: Decimal | H82: Map | I82: Req/Resp | J82: Mandatory | K82: 0 | L82: No | O82: No | P82: Limit
D85: Root | E85: SolartisInsuredV2 | F85: QuoteType | G85: VarChar | H85: Object | I85: Req/Resp | J85: Mandatory | K85: No | L85: No | O85: No | P85: QuoteType
D86: Insured | E86: Location | F86: StateRegionCode | G86: VarChar | H86: List | I86: Req/Resp | J86: Mandatory | K86: No | L86: No | O86: No | P86: StateRegionCode
B87: RENEWAL - INPUT VALUES
B88: RENEWAL ADJUSTMENT AND FACTORS
B89: Book Of Business Adjustment | C89: No | D89: Root | E89: Policy | F89: BookOfBusinessAdjustment | G89: Decimal | H89: Object | I89: Resp | J89: Mandatory | K89: 1 | L89: No | O89: No | P89: BookOfBusinessAdjustment
B90: Minimum Renewal Reservation Factor | C90: 0.5 | D90: Root | E90: Policy | F90: MinimumRenewalReserve | G90: Decimal | H90: Object | I90: Resp | J90: Mandatory | K90: 0 | L90: No | O90: No | P90: MinimumRenewalReserve
B91: Maximum Renewal Reservation Factor | C91: 0.7 | D91: Root | E91: Policy | F91: MaximumRenewalReserve | G91: Decimal | H91: Object | I91: Resp | J91: Mandatory | K91: 0 | L91: No | O91: No | P91: MaximumRenewalReserve
B92: Insurance Score Factor Last Run Date | D92: Account | E92: Insured | F92: InsuranceScoreFetchedDate | G92: Date | H92: List | I92: Resp | J92: Mandatory | K92: No | L92: No | O92: No | P92: InsuranceScoreFetchedDate
B93: Insurance Score Range | C93: No Hit | D93: Account | E93: Insured | F93: InsuranceScoreStatus | G93: String | H93: List | I93: Resp | J93: Mandatory | K93: No | L93: No | O93: No | P93: InsuranceScoreStatus
B94: RENEWAL - PREMIUM OVERRIDE METHOD
B95: Adjust By | C95: No Adjustment | D95: Root | E95: Policy | F95: PremiumAdjustBy | G95: VarChar | H95: Object | I95: Resp | J95: Mandatory | K95: 0 | L95: No | O95: No | P95: PremiumAdjustBy
B96: Property Target Premium | C96: 0 | D96: Root | E96: Policy | F96: PropertyTargetPremium | G96: Decimal | H96: Object | I96: Resp | J96: Mandatory | K96: 0 | L96: No | O96: No | P96: PropertyTargetPremium
B97: Liability Target Premium | C97: 0 | D97: Root | E97: Policy | F97: LiabilityTargetPremium | G97: Decimal | H97: Object | I97: Resp | J97: Mandatory | K97: 0 | L97: No | O97: No | P97: LiabilityTargetPremium
B98: Property Target Premium Percentage | C98: 0 | D98: Root | E98: Policy | F98: PropertyTargetPremiumMin | G98: Decimal | H98: Object | I98: Resp | J98: Mandatory | K98: 0 | L98: No | O98: No | P98: PropertyTargetPremiumMin
B99: Liability Target Premium Percentage | C99: 0 | D99: Root | E99: Policy | F99: LiabilityTargetPremiumMin | G99: Decimal | H99: Object | I99: Resp | J99: Mandatory | K99: 0 | L99: No | O99: No | P99: LiabilityTargetPremiumMin
B100: Override Non-Wind Developed Rate | C100: 0 | D100: Root | E100: Policy | F100: OverrideNonWindDevelopment | G100: Decimal | H100: Object | I100: Resp | J100: Mandatory | K100: 1 | L100: No | O100: No | P100: OverrideNonWindDevelopment
I101: .
B102: NEW BUSINESS CALCULATION - OUTPUT VALUE (CALCULATED or DERIVED FROM TABLES) | I102: .
A103: =CELL("address",F103) -> $F$103 | B103: BASIC RISK — DERIVED | I103: .
...

Sheet Rate Tables
A1: Table 1 | G1: Table 2 | N1: Table 3 | X1: Table 4 | AD1: Table 5 | AJ1: Table 6 | AQ1: Table 7 | AX1: Table 8 | BF1: Table 9 | BP1: Table 10 | BZ1: Table 11 | CG1: Table 12 | CO1: Table 13 | CS1: Table 14 | CZ1: Table 15 | DG1: Table 16 | DN1: Table 17 | DX1: Table 18 | EF1: Table 19 | EM1: Table 20 | EV1: Table 21 | FF1: Table 22 | FN1: Table 23 | FU1: Table 24 | GB1: Table 25 | GH1: Table 26 | GN1: Table 27 | GT1: Table 28 | HB1: Table 29 | HJ1: Table 30 | HR1: Table 31 | HY1: Table 32 | IF1: Table 33 | IJ1: Table 34 | IQ1: Table 35 | IW1: Table 36 | JC1: Table 37 | JJ1: Table 38 | JS1: Table 39 | JW1: Table 40 | KA1: Table 41 | KE1: Table 42 | KJ1: Table 43 | NG1: Autauga | NI1: Apache | NK1: Arkansas | NM1: Adams | NO1: Fairfield | NQ1: Kent | NS1: Alachua | NU1: Appling | NW1: Ada | NY1: Adams | OA1: Adams | OC1: Adair | OE1: Allen | OG1: Acadia | OI1: Androscoggin | OK1: Allegany | OM1: Barnstable | OO1: Alcona | OQ1: Aitkin | OS1: Adams | OU1: Adair | OW1: Carson City | OY1: Belknap | PA1: Atlantic | PC1: Bernalillo | PE1: Albany | PG1: Alamance | PI1: Adams | PK1: Baker | PM1: Bristol | PO1: Abbeville | PQ1: Anderson | PS1: Anderson | PU1: Beaver | PW1: Alexandria (City) | PY1: Adams | QA1: Adams | QF1: Washington D.C. | QH1: POLICY_FEE_RATE_TABLE State | QI1: State Code | QJ1: Fee 0-999999 | QK1: Fee 1000000+ | QM1: $0 - $99,999 | QR1: DV_Occupancy_Std (non-HO6) | QS1: DV_Occupancy_HO6 | QU1: RTPL_HO6_TCQ_FACTOR (from One London) | QV1: TCQ_FACTOR | QW1: STATE_LIST | QX1: Autauga | QY1: Apache | QZ1: Arkansas | RA1: Adams | RB1: Fairfield | RC1: Kent | RD1: Alachua | RE1: Appling | RF1: Ada | RG1: Adams | RH1: Adams | RI1: Adair | RJ1: Allen | RK1: Acadia | RL1: Androscoggin | RM1: Allegany | RN1: Barnstable | RO1: Alcona | RP1: Aitkin | RQ1: Adams | RR1: Adair | RS1: Carson City | RT1: Belknap | RU1: Atlantic | RV1: Bernalillo | RW1: Albany | RX1: Alamance | RY1: Adams | RZ1: Baker | SA1: Bristol | SB1: Abbeville | SC1: Anderson | SD1: Anderson | SE1: Beaver | SF1: Accomack | SG1: Adams | SH1: Washington D.C. | SI1: Adams | SJ1: Alabama | SK1: BALDWIN | SL1: FAIRFIELD | SM1: KENT | SN1: ALACHUA | SO1: BRANTLEY | SP1: ACADIA | SQ1: ANDROSCOGGIN | SR1: CAROLINE | SS1: BARNSTABLE | ST1: GEORGE | SU1: BELKNAP | SV1: ATLANTIC | SW1: BRONX | SX1: BEAUFORT | SY1: BRISTOL | SZ1: BAMBERG | TA1: ARANSAS | TB1: ACCOMACK | TC1: DISTRICT OF COLUMBIA
A2: Rate Table Name | B2: RTPL_POLICY_FORM_FACTOR | G2: Rate TableName | H2: RTPL_BASE_RATE | N2: Rate Table Name | O2: RTPL_TIV_RATE_RELATIVITY_FACTOR | X2: Rate TableName | Y2: RTPL_MINIMUM_NONWIND_RATE | AD2: Rate TableName | AE2: RTPL_RATINGTERRITORY | AJ2: Rate TableName | AK2: RTPL_CONSTRUCTION_TYPE_FACTOR | AQ2: Rate TableName | AR2: RTPL_OCCUPANCY_FACTOR | AX2: Rate TableName | AY2: RTPL_DWELLING_AGE_FACTOR | BF2: Rate TableName | BG2: RTPL_ROOF_AGE_FACTOR | BP2: Rate TableName | BQ2: RTPL_NUMBER_OF_STORIES_FACTOR | BZ2: Rate TableName | CA2: RTPL_LOSS_SURCHARGE_FACTOR | CG2: Rate TableName | CH2: RTPL_COVEAGE_A_BAND_FACTOR | CO2: Rate TableName | CP2: RTPL_EXTENDED_REPLACEMENT_COST | CS2: Rate TableName | CT2: RTPL_FAMILY_FACTOR | CZ2: Rate TableName | DA2: RTPL_PROTECTION_CLASS_FACTOR | DG2: Rate TableName | DH2: RTPL_CENTRAL_STATION_ALARM_FACTOR | DN2: Rate TableName | DO2: RTPL_WATER_DAMAGE_SUBLIMIT_FACTOR | DX2: Rate TableName | DY2: RTPL_AOP_DEDUCTIBLE_FACTOR | EF2: Rate TableName | EG2: RTPL_WATER_DAMAGE_DEDUCTIBLE_FACTOR | EM2: Rate TableName | EN2: RTPL_INSURANCESCORE_FACTOR | EV2: Rate TableName | EW2: RTPL_AAL_FACTOR | FF2: Rate TableName | FG2: RTPL_MINIMUM_PROPERTY_RATE | FN2: Rate TableName | FO2: RTPL_MOLD_COVERAGE_FACTOR | FU2: Rate TableName | FV2: RTPL_WATERBACKUP_COVERAGE_FACTOR | GB2: Rate TableName | GC2: RTPL_IDENTITYFRAUD_COVERAGE_FACTOR | GH2: Rate TableName | GI2: RTPL_LOSS_ASSESSMENT_COVERAGE_FACTOR | GN2: Rate TableName | GO2: RTPL_PERSONAL_INJURY_LIABILITY_FACTOR | GT2: Rate TableName | GU2: RTPL_EARTHQUAKE_COVERAGE_FACTOR | HB2: Rate TableName | HC2: RTPL_EARTHQUAKE_DEDUCTIBLE_COVERAGE_FACTOR | HJ2: Rate TableName | HK2: RTPL_EARTHQUAKE_COVERAGE_FACTOR_CONDO | HR2: Rate TableName | HS2: RTPL_THEFT_COVERAGEFACTOR | HY2: Rate TableName | HZ2: RTPL_VANDALISM_MISCHIEF_COVERAGE_FACTOR | IF2: Rate TableName | IG2: RTPL_EXTENDED_COVERAGE | IJ2: Rate TableName | IK2: RTPL_LIABILITY_LIMIT_FACTOR | IQ2: Rate TableName | IR2: RTPL_MEDICAL_PAYMENT_FACTOR | IW2: Rate TableName | IX2: RTPL_MINIMUM_PREMIUM_CONDO | JC2: Rate TableName | JD2: RTPL_BOB_ADJUSTMENT_FACTOR | JJ2: Rate TableName | JK2: RTPL_RISK_ADJUSTMENT_FACTOR | JS2: Rate TableName | JT2: RTPL_WIND_HAIL_DEDUCTIBLE_FACTOR_RENEWAL | JW2: Rate TableName | JX2: STATE_AND_COUNTY | KA2: Rate TableName | KB2: RTPL_TERRITORYFACTOR | KE2: Rate TableName | KF2: RSUM_POLICY_FEE_RATE_TABLE | KJ2: Rate Table Name | KK2: RTPL_SCHEDULED_PERSONAL_PROPERTY_COVERAGE_FACTOR | NG2: Barbour | NI2: Coconino | NK2: Baxter | NM2: Arapahoe | NO2: Litchfield | NQ2: New Castle | NS2: Bay | NU2: Atkinson | NW2: Bannock | NY2: Bond | OA2: Bartholomew | OC2: Allamakee | OE2: Atchison | OG2: Allen | OI2: Aroostook | OK2: Anne Arundel | OM2: Berkshire | OO2: Allegan | OQ2: Becker | OS2: Alcorn | OU2: Atchison | OW2: Clark | OY2: Carroll | PA2: Bergen | PC2: Catron | PE2: Allegany | PG2: Alexander | PI2: Ashland | PK2: Clackamas | PM2: Newport | PO2: Aiken | PQ2: Benton | PS2: Andrews | PU2: Cache | PW2: Bristol (City) | PY2: Benton | QA2: Barron | QH2: Alabama | QI2: AL | QJ2: 100 | QK2: 200 | QM2: $100,000 - $149,999 | QN2: HO6 Base Premium (from Reference TIV Rate Relativity H3) | QO2: 500 | QR2: Primary | QS2: Owner - Primary Residence | QU2: AL1 | QV2: 4 | QW2: Alabama | QX2: Baldwin | QY2: Cochise | QZ2: Ashley | RA2: Alamosa | RB2: Hartford | RC2: New Castle | RD2: Baker | RE2: Atkinson | RF2: Adams | RG2: Alexander | RH2: Allen | RI2: Adams | RJ2: Anderson | RK2: Allen | RL2: Aroostook | RM2: Anne Arundel | RN2: Berkshire | RO2: Alger | RP2: Anoka | RQ2: Alcorn | RR2: Andrew | RS2: Churchill | RT2: Carroll | RU2: Bergen | RV2: Catron | RW2: Allegany | RX2: Alexander | RY2: Allen | RZ2: Benton | SA2: Kent | SB2: Aiken | SC2: Bedford | SD2: Andrews | SE2: Box Elder | SF2: Albemarle | SG2: Asotin | SI2: Ashland | SJ2: Connecticut | SK2: CLARKE | SL2: HARTFORD | SM2: SUSSEX | SN2: BAKER | SO2: BRYAN | SP2: ASSUMPTION | SQ2: AROOSTOOK | SR2: DORCHESTER | SS2: BRISTOL | ST2: HANCOCK | SU2: CARROLL | SV2: BURLINGTON | SW2: DUTCHESS | SX2: BERTIE | SY2: KENT | SZ2: BEAUFORT | TA2: BEE | TB2: CHESAPEAKE CITY
A3: Column Name | B3: POLICY_FORM | C3: DWELLING_VALUATION | D3: CONTENT_VALUATION | E3: POLICY_FORM_FACTOR | G3: Column Name | H3: POLICY_FORM | I3: STATE_CODE | J3: TERRITORY | K3: RATING_TERM | L3: RATE | N3: Column Name | O3: POLICY_FORM | P3: STATE_CODE | Q3: DWELLING_MIN | R3: DWELLING_MAX | S3: MINIMUMTIV | T3: TIV_RATE_RELATIVITY_FACTOR | U3: MAXIMUMTIV | V3: MAXTIVRATERELATIVITYFACTOR | X3: Column Name | Y3: POLICY_FORM | Z3: STATE_CODE | AA3: TERRITORY | AB3: RATE | AD3: Column Name | AE3: ZIPCODE | AF3: COUNTY | AG3: STATE | AH3: RATINGTERRITORY | AJ3: Column Name | AK3: POLICY_FORM | AL3: STATE_CODE | AM3: CONSTRUCTION_TYPE | AN3: RATING_TERM | AO3: FACTOR | AQ3: Column Name | AR3: POLICY_FORM | AS3: STATE_CODE | AT3: OCCUPANCY_TYPE | AU3: RATING_TERM | AV3: FACTOR | AX3: Column Name | AY3: POLICY_FORM | AZ3: STATE_CODE | BA3: MINIMUM_DWELLING_AGE | BB3: MAXIMUM_DWELLING_AGE | BC3: RATING_TERM | BD3: DWELLING_AGE_FACTOR | BF3: Column Name | BG3: POLICY_FORM | BH3: STATE_CODE | BI3: MINIMUM_DWELLING_AGE | BJ3: MAXIMUM_DWELLING_AGE | BK3: MINIMUM_ROOF_AGE | BL3: MAXIMUM_ROOF_AGE | BM3: RATING_TERM | BN3: FACTOR | BP3: Column Name | BQ3: POLICY_FORM | BR3: STATE_CODE | BS3: WIND_COVERAGE | BT3: CONSTRUCTION_TYPE | BU3: MINIMUM_STORIES | BV3: MAXIMUM_STORIES | BW3: RATING_TERM | BX3: NUMBER_OF_STORIES_FACTOR | BZ3: Column Name | CA3: POLICY_FORM | CB3: STATE_CODE | CC3: NUMBER_OF_LOSSES | CD3: RATING_TERM | CE3: LOSS_SURCHARGE_FACTOR | CG3: Column Name | CH3: POLICY_FORM | CI3: STATE_CODE | CJ3: DWELLING_COVERAGE_MIN | CK3: DWELLING_COVERAGE_MAX | CL3: RATING_TERM | CM3: COVEAGE_A_BAND_FACTOR | CO3: Column Name | CP3: EXTENDEDREPLACEMENTCOST | CQ3: EXTENDEDREPLACEMENTCOSTFACTOR | CS3: Column Name | CT3: POLICY_FORM | CU3: STATE_CODE | CV3: NUMBER_OF_FAMILIES | CW3: RATING_TERM | CX3: FACTOR | CZ3: Column Name | DA3: POLICY_FORM | DB3: STATE_CODE | DC3: PROTECTION_CLASS | DD3: RATING_TERM | DE3: FACTOR | DG3: Column Name | DH3: POLICY_FORM | DI3: STATE_CODE | DJ3: ALARM | DK3: RATING_TERM | DL3: FACTOR | DN3: Column Name | DO3: POLICY_FORM | DP3: QUOTE_TYPE | DQ3: STATE_CODE | DR3: COUNTY | DS3: ZIPCODE | DT3: WATER_DAMAGE_SUBLIMIT | DU3: RATING_TERM | DV3: FACTOR | DX3: Column Name | DY3: POLICY_FORM | DZ3: STATE_CODE | EA3: AOP_DEDUCTIBLE | EB3: DEDUCTIBLE_TYPE | EC3: RATING_TERM | ED3: FACTOR | EF3: Column Name | EG3: POLICY_FORM | EH3: STATE_CODE | EI3: AOP_DEDUCTIBLE | EJ3: WATER_DAMAGE_DEDUCTIBLE | EK3: FACTOR | EM3: Column Name | EN3: POLICY_FORM | EO3: STATE_CODE | EP3: SCORE_STATUS | EQ3: MIN_SCORE | ER3: MAX_SCORE | ES3: RATING_TERM | ET3: FACTOR | EV3: Column Name | EW3: POLICY_FORM | EX3: STATE_CODE | EY3: TERRITORY | EZ3: MINIMUM_YEAR_BUILT | FA3: MAXIMUM_YEAR_BUILT | FB3: TIGER_CQ_APPLICABLE | FC3: RATING_TERM | FD3: AAL_FACTOR | FF3: Column Name | FG3: POLICY_FORM | FH3: STATE_CODE | FI3: TERRITORY | FJ3: DISTANCE_TO_COASTAL | FK3: RATING_TERM | FL3: FACTOR | FN3: Column Name | FO3: POLICY_FORM | FP3: STATE_CODE | FQ3: MOLD_LIMIT | FR3: RATING_TERM | FS3: FACTOR | FU3: Column Name | FV3: POLICY_FORM | FW3: STATE_CODE | FX3: WATER_BACKUP_LIMIT | FY3: RATING_TERM | FZ3: WATERBACKUP_COVERAGE_FACTOR | GB3: Column Name | GC3: POLICY_FORM | GD3: STATE_CODE | GE3: ID_FRAUD_LIMIT | GF3: FACTOR | GH3: Column Name | GI3: POLICY_FORM | GJ3: STATE_CODE | GK3: LOSS_ASSESSMENT_LIMIT | GL3: LOSS_ASSESSMENT_COVERAGE_FACTOR | GN3: Column Name | GO3: POLICY_FORM | GP3: STATE_CODE | GQ3: PERSONAL_INJURY_LIABILITY | GR3: PERSONAL_INJURY_LIABILITY_FACTOR | GT3: Column Name | GU3: POLICY_FORM | GV3: STATE_CODE | GW3: EARTHQUAKE_SELECTED | GX3: CONSTRUCTION_TYPE | GY3: RATING_TERM | GZ3: EARTHQUAKE_COVERAGE_FACTOR | HB3: Column Name | HC3: POLICY_FORM | HD3: STATE_CODE | HE3: EARTHQUAKE_EXCLUDED | HF3: DEDUCTIBLE_PERCENT | HG3: RATING_TERM | HH3: EARTHQUAKE_DEDUCTIBLE_COVERAGE_FACTOR | HJ3: Column Name | HK3: POLICY_FORM | HL3: STATE_CODE | HM3: EARTHQUAKE_DEDUCTIBLE | HN3: EARTHQUAKE_SELECTED | HO3: CONSTRUCTION_TYPE | HP3: EARTHQUAKE_COVERAGE_FACTOR | HR3: Column Name | HS3: POLICY_FORM | HT3: STATE_CODE | HU3: THEFT_LIMIT | HV3: RATING_TERM | HW3: FACTOR | HY3: Column Name | HZ3: POLICY_FORM | IA3: STATE_CODE | IB3: VANDALISM_COVERAGE | IC3: RATING_TERM | ID3: FACTOR | IF3: Column Name | IG3: EXTENDED_COVERAGE | IH3: FACTOR | IJ3: Column Name | IK3: POLICY_FORM | IL3: STATE_CODE | IM3: LIABILITY_LIMIT | IN3: RATING_TERM | IO3: LIABILITY_LIMIT_FACTOR | IQ3: Column Name | IR3: POLICY_FORM | IS3: STATE_CODE | IT3: MEDICAL_LIMIT | IU3: MEDICAL_PAYMENT_FACTOR | IW3: Column Name | IX3: POLICY_FORM | IY3: STATE_CODE | IZ3: TERRITORY | JA3: MINIMUM_PREMIUM | JC3: Column Name | JD3: STATE | JE3: ZIPCODE | JF3: COUNTY | JG3: CITY | JH3: BOBAPPLICABLEFACTOR | JJ3: Column Name | JK3: STATE | JL3: ZIPCODE | JM3: COUNTY | JN3: CITY | JO3: AGEOFHOMERISKFACTOR | JP3: CONSTRUCTIONTYPERISKFACTOR | JQ3: ROOFAGERISKFACTOR | JS3: Column Name | JT3: WINDDEDUCTIBLE | JU3: WINDHAILDEDUCTIBLEFACTOR | JW3: Column Name | JX3: State | JY3: County | KA3: Column Name | KB3: TERRITORY | KC3: TERRITORYFACTOR | KE3: Column Name | KF3: SUBLINE_NAME | KG3: STATE | KH3: POLICY_FEE | KJ3: Column Name | KK3: POLICY_FORM | KL3: PERSONAL_PROPERTY_TYPE | KM3: SCHEDULED_PERSONAL_PROPERTY_ COVERAGE_FACTOR | NG3: Baldwin | NI3: Cochise | NK3: Ashley | NM3: Alamosa | NO3: Hartford | NQ3: Sussex | NS3: Baker | NU3: Bacon | NW3: Adams | NY3: Alexander | OA3: Allen | OC3: Adams | OE3: Anderson | OG3: Ascension | OI3: Cumberland | OK3: Baltimore | OM3: Bristol | OO3: Alger | OQ3: Anoka | OS3: Amite | OU3: Andrew | OW3: Churchill | OY3: Cheshire | PA3: Burlington | PC3: Chaves | PE3: Bronx | PG3: Alleghany | PI3: Allen | PK3: Benton | PM3: Kent | PO3: Allendale | PQ3: Bedford | PS3: Angelina | PU3: Box Elder | PW3: Buena Vista (City) | PY3: Asotin | QA3: Ashland | QH3: Alaska | QI3: AK | QJ3: 100 | QK3: 200 | QM3: $150,000-$249,999 | QR3: Secondary/Seasonal | QS3: Owner - Secondary Residence | QU3: AL2 | QV3: 4 | QW3: Arizona | QX3: Barbour | QY3: Coconino | QZ3: Baxter | RA3: Arapahoe | RB3: Litchfield | RC3: Sussex | RD3: Bay | RE3: Bacon | RF3: Bannock | RG3: Bond | RH3: Bartholomew | RI3: Allamakee | RJ3: Atchison | RK3: Ascension | RL3: Cumberland | RM3: Baltimore | RN3: Bristol | RO3: Allegan | RP3: Becker | RQ3: Amite | RR3: Atchison | RS3: Clark | RT3: Cheshire | RU3: Burlington | RV3: Chaves | RW3: Bronx | RX3: Alleghany | RY3: Ashland | RZ3: Clackamas | SA3: Newport | SB3: Allendale | SC3: Benton | SD3: Angelina | SE3: Cache | SF3: Alexandria (City) | SG3: Benton | SI3: Barron | SJ3: Delaware | SK3: COVINGTON | SL3: LITCHFIELD | SN3: BAY | SO3: BULLOCH | SP3: CALCASIEU | SQ3: CUMBERLAND | SR3: SOMERSET | SS3: DUKES | ST3: HARRISON | SU3: HILLSBOROUGH | SV3: CAMDEN | SW3: KINGS | SX3: BLADEN | SY3: NEWPORT | SZ3: BERKELEY | TA3: BRAZORIA | TB3: GLOUCESTER
A4: Column Category (Input/Output) | B4: Input | C4: Input | D4: Input | E4: Output | G4: Column Category (Input/Output) | H4: Input | I4: Input | J4: Input | K4: Input | L4: Output | N4: Column Category (Input/Output) | O4: Input | P4: Input | Q4: Input | R4: Input | S4: Output | T4: Output | U4: Output | V4: Output | X4: Column Category (Input/Output) | Y4: Input | Z4: Input | AA4: Input | AB4: Output | AD4: Column Category (Input/Output) | AE4: Input | AF4: Input | AG4: Input | AH4: Output | AJ4: Column Category (Input/Output) | AK4: Input | AL4: Input | AM4: Input | AN4: Input | AO4: Output | AQ4: Column Category (Input/Output) | AR4: Input | AS4: Input | AT4: Input | AU4: Input | AV4: Output | AX4: Column Category (Input/Output) | AY4: Input | AZ4: Input | BA4: Input | BB4: Input | BC4: Input | BD4: Output | BF4: Column Category (Input/Output) | BG4: Input | BH4: Input | BI4: Input | BJ4: Input | BK4: Input | BL4: Input | BM4: Input | BN4: Output | BP4: Column Category (Input/Output) | BQ4: Input | BR4: Input | BS4: Input | BT4: Input | BU4: Input | BV4: Input | BW4: Input | BX4: Output | BZ4: Column Category (Input/Output) | CA4: Input | CB4: Input | CC4: Input | CD4: Input | CE4: Output | CG4: Column Category (Input/Output) | CH4: Input | CI4: Input | CJ4: Input | CK4: Input | CL4: Input | CM4: Output | CO4: Column Category (Input/Output) | CP4: Input | CQ4: Output | CS4: Column Category (Input/Output) | CT4: Input | CU4: Input | CV4: Input | CW4: Input | CX4: Output | CZ4: Column Category (Input/Output) | DA4: Input | DB4: Input | DC4: Input | DD4: Input | DE4: Output | DG4: Column Category (Input/Output) | DH4: Input | DI4: Input | DJ4: Input | DK4: Input | DL4: Output | DN4: Column Category (Input/Output) | DO4: Input | DP4: Input | DQ4: Input | DR4: Input | DS4: Input | DT4: Input | DU4: Input | DV4: Output | DX4: Column Category (Input/Output) | DY4: Input | DZ4: Input | EA4: Input | EB4: Input | EC4: Input | ED4: Output | EF4: Column Category (Input/Output) | EG4: Input | EH4: Input | EI4: Input | EJ4: Input | EK4: Output | EM4: Column Category (Input/Output) | EN4: Input | EO4: Input | EP4: Input | EQ4: Input | ER4: Input | ES4: Input | ET4: Output | EV4: Column Category (Input/Output) | EW4: Input | EX4: Input | EY4: Input | EZ4: Input | FA4: Input | FB4: Input | FC4: Input | FD4: Output | FF4: Column Category (Input/Output) | FG4: Input | FH4: Input | FI4: Input | FJ4: Input | FK4: Input | FL4: Output | FN4: Column Category (Input/Output) | FO4: Input | FP4: Input | FQ4: Input | FR4: Input | FS4: Output | FU4: Column Category (Input/Output) | FV4: Input | FW4: Input | FX4: Input | FY4: Input | FZ4: Output | GB4: Column Category (Input/Output) | GC4: Input | GD4: Input | GE4: Input | GF4: Output | GH4: Column Category (Input/Output) | GI4: Input | GJ4: Input | GK4: Input | GL4: Output | GN4: Column Category (Input/Output) | GO4: Input | GP4: Input | GQ4: Input | GR4: Output | GT4: Column Category (Input/Output) | GU4: Input | GV4: Input | GW4: Input | GX4: Input | GY4: Input | GZ4: Output | HB4: Column Category (Input/Output) | HC4: Input | HD4: Input | HE4: Input | HF4: Input | HG4: Input | HH4: Output | HJ4: Column Category (Input/Output) | HK4: Input | HL4: Input | HM4: Input | HN4: Input | HO4: Input | HP4: Output | HR4: Column Category (Input/Output) | HS4: Input | HT4: Input | HU4: Input | HV4: Input | HW4: Output | HY4: Column Category (Input/Output) | HZ4: Input | IA4: Input | IB4: Input | IC4: Input | ID4: Output | IF4: Column Category (Input/Output) | IG4: Input | IH4: Output | IJ4: Column Category (Input/Output) | IK4: Input | IL4: Input | IM4: Input | IN4: Input | IO4: Output | IQ4: Column Category (Input/Output) | IR4: Input | IS4: Input | IT4: Input | IU4: Output | IW4: Column Category (Input/Output) | IX4: Input | IY4: Input | IZ4: Input | JA4: Output | JC4: Column Category (Input/Output) | JD4: Input | JE4: Input | JF4: Input | JG4: Input | JH4: Output | JJ4: Column Category (Input/Output) | JK4: Input | JL4: Input | JM4: Input | JN4: Input | JO4: Output | JP4: Output | JQ4: Output | JS4: Column Category (Input/Output) | JT4: Input | JU4: Output | JW4: Column Category (Input/Output) | JX4: Input | JY4: Input | KA4: Column Category (Input/Output) | KB4: Input | KC4: Output | KE4: Column Category (Input/Output) | KF4: Input | KG4: Input | KH4: Output | KJ4: Column Category (Input/Output) | KK4: Input | KL4: Input | KM4: Output | NG4: Bibb | NI4: Gila | NK4: Benton | NM4: Archuleta | NO4: Middlesex | NS4: Bradford | NU4: Baker | NW4: Bear Lake | NY4: Boone | OA4: Benton | OC4: Appanoose | OE4: Barber | OG4: Assumption | OI4: Franklin | OK4: Baltimore City | OM4: Dukes | OO4: Alpena | OQ4: Beltrami | OS4: Attala | OU4: Audrain | OW4: Douglas | OY4: Coos | PA4: Camden | PC4: Cibola | PE4: Broome | PG4: Anson | PI4: Ashtabula | PK4: Clatsop | PM4: Providence | PO4: Anderson | PQ4: Bledsoe | PS4: Aransas | PU4: Carbon | PW4: Charlottesville (City) | PY4: Chelan | QA4: Bayfield | QH4: Arizona | QI4: AZ | QJ4: 100 | QK4: 200 | QM4: $250,000 - $349,999 | QR4: Long-Term Rental | QS4: Rental - Annual | QU4: AL3 | QV4: 4 | QW4: Arkansas | QX4: Bibb | QY4: Gila | QZ4: Benton | RA4: Archuleta | RB4: Middlesex | RD4: Bradford | RE4: Baker | RF4: Bear Lake | RG4: Boone | RH4: Benton | RI4: Appanoose | RJ4: Barber | RK4: Assumption | RL4: Franklin | RM4: Baltimore City | RN4: Dukes | RO4: Alpena | RP4: Beltrami | RQ4: Attala | RR4: Audrain | RS4: Douglas | RT4: Coos | RU4: Camden | RV4: Cibola | RW4: Broome | RX4: Anson | RY4: Ashtabula | RZ4: Clatsop | SA4: Providence | SB4: Anderson | SC4: Bledsoe | SD4: Aransas | SE4: Carbon | SF4: Alleghany | SG4: Chelan | SI4: Bayfield | SJ4: Florida | SK4: ESCAMBIA | SL4: MIDDLESEX | SN4: BRADFORD | SO4: CAMDEN | SP4: CAMERON | SQ4: FRANKLIN | SR4: WICOMICO | SS4: ESSEX | ST4: JACKSON | SU4: MERRIMACK | SV4: CAPE MAY | SW4: NASSAU | SX4: BRUNSWICK | SY4: PROVIDENCE | SZ4: CHARLESTON | TA4: BROOKS | TB4: HAMPTON CITY
A5: Operator | B5: Exact Match | C5: Exact Match | D5: Exact Match | E5: Exact Match | G5: Operator | H5: Exact Match | I5: Exact Match | J5: Exact Match | K5: Exact Match | L5: Exact Match | N5: Operator | O5: Exact Match | P5: Exact Match | Q5: Exact Match | R5: Exact Match | S5: Exact Match | T5: Exact Match | U5: Exact Match | V5: Exact Match | X5: Operator | Y5: Exact Match | Z5: Exact Match | AA5: Exact Match | AB5: Exact Match | AD5: Operator | AE5: Exact Match | AF5: Exact Match | AG5: Exact Match | AH5: Exact Match | AJ5: Operator | AK5: Exact Match | AL5: Exact Match | AM5: Exact Match | AN5: Exact Match | AO5: Exact Match | AQ5: Operator | AR5: Exact Match | AS5: Exact Match | AT5: Exact Match | AU5: Exact Match | AV5: Exact Match | AX5: Operator | AY5: Exact Match | AZ5: Exact Match | BA5: Greater than or equal | BB5: Less than or equal | BC5: Exact Match | BD5: Exact Match | BF5: Operator | BG5: Exact Match | BH5: Exact Match | BI5: Greater than or equal | BJ5: Less than or equal | BK5: Greater than or equal | BL5: Less than or equal | BM5: Exact Match | BN5: Exact Match | BP5: Operator | BQ5: Exact Match | BR5: Exact Match | BS5: Exact Match | BT5: Exact Match | BU5: Greater than or equal | BV5: Less than or equal | BW5: Exact Match | BX5: Exact Match | BZ5: Operator | CA5: Exact Match | CB5: Exact Match | CC5: Exact Match | CD5: Exact Match | CE5: Exact Match | CG5: Operator | CH5: Exact Match | CI5: Exact Match | CJ5: Greater than or equal | CK5: Less than or equal | CL5: Exact Match | CM5: Exact Match | CO5: Operator | CP5: Exact Match | CQ5: Exact Match | CS5: Operator | CT5: Exact Match | CU5: Exact Match | CV5: Exact Match | CW5: Exact Match | CX5: Exact Match | CZ5: Operator | DA5: Exact Match | DB5: Exact Match | DC5: Exact Match | DD5: Exact Match | DE5: Exact Match | DG5: Operator | DH5: Exact Match | DI5: Exact Match | DJ5: Exact Match | DK5: Exact Match | DL5: Exact Match | DN5: Operator | DO5: Exact Match | DP5: Exact Match | DQ5: Exact Match | DR5: Exact Match | DS5: Exact Match | DT5: Exact Match | DU5: Exact Match | DV5: Exact Match | DX5: Operator | DY5: Exact Match | DZ5: Exact Match | EA5: Exact Match | EB5: Exact Match | EC5: Exact Match | ED5: Exact Match | EF5: Operator | EG5: Exact Match | EH5: Exact Match | EI5: Exact Match | EJ5: Exact Match | EK5: Exact Match | EM5: Operator | EN5: Exact Match | EO5: Exact Match | EP5: Exact Match | EQ5: Greater than or equal | ER5: Less than or equal | ES5: Exact Match | ET5: Exact Match | EV5: Operator | EW5: Exact Match | EX5: Exact Match | EY5: Exact Match | EZ5: Greater than or equal | FA5: Less than or equal | FB5: Exact Match | FC5: Exact Match | FD5: Exact Match | FF5: Operator | FG5: Exact Match | FH5: Exact Match | FI5: Exact Match | FJ5: Exact Match | FK5: Exact Match | FL5: Exact Match | FN5: Operator | FO5: Exact Match | FP5: Exact Match | FQ5: Exact Match | FR5: Exact Match | FS5: Exact Match | FU5: Operator | FV5: Exact Match | FW5: Exact Match | FX5: Exact Match | FY5: Exact Match | FZ5: Exact Match | GB5: Operator | GC5: Exact Match | GD5: Exact Match | GE5: Exact Match | GF5: Exact Match | GH5: Operator | GI5: Exact Match | GJ5: Exact Match | GK5: Exact Match | GL5: Exact Match | GN5: Operator | GO5: Exact Match | GP5: Exact Match | GQ5: Exact Match | GR5: Exact Match | GT5: Operator | GU5: Exact Match | GV5: Exact Match | GW5: Exact Match | GX5: Exact Match | GY5: Exact Match | GZ5: Exact Match | HB5: Operator | HC5: Exact Match | HD5: Exact Match | HE5: Exact Match | HF5: Exact Match | HG5: Exact Match | HH5: Exact Match | HJ5: Operator | HK5: Exact Match | HL5: Exact Match | HM5: Exact Match | HN5: Exact Match | HO5: Exact Match | HP5: Exact Match | HR5: Operator | HS5: Exact Match | HT5: Exact Match | HU5: Exact Match | HV5: Exact Match | HW5: Exact Match | HY5: Operator | HZ5: Exact Match | IA5: Exact Match | IB5: Exact Match | IC5: Exact Match | ID5: Exact Match | IF5: Operator | IG5: Exact Match | IH5: Exact Match | IJ5: Operator | IK5: Exact Match | IL5: Exact Match | IM5: Exact Match | IN5: Exact Match | IO5: Exact Match | IQ5: Operator | IR5: Exact Match | IS5: Exact Match | IT5: Exact Match | IU5: Exact Match | IW5: Operator | IX5: Exact Match | IY5: Exact Match | IZ5: Exact Match | JA5: Exact Match | JC5: Operator | JD5: Exact Match | JE5: Exact Match | JF5: Exact Match | JG5: Exact Match | JH5: Exact Match | JJ5: Operator | JK5: Exact Match | JL5: Exact Match | JM5: Exact Match | JN5: Exact Match | JO5: Exact Match | JP5: Exact Match | JQ5: Exact Match | JS5: Operator | JT5: Exact Match | JU5: Exact Match | JW5: Operator | JX5: Exact Match | JY5: Exact Match | KA5: Operator | KB5: Exact Match | KC5: Exact Match | KE5: Operator | KF5: Exact Match | KG5: Exact Match | KH5: Exact Match | KJ5: Operator | KK5: Exact Match | KL5: Exact Match | KM5: Exact Match | NG5: Blount | NI5: Graham | NK5: Boone | NM5: Baca | NO5: New Haven | NS5: Brevard | NU5: Baldwin | NW5: Benewah | NY5: Brown | OA5: Blackford | OC5: Audubon | OE5: Barton | OG5: Avoyelles | OI5: Hancock | OK5: Calvert | OM5: Essex | OO5: Antrim | OQ5: Benton | OS5: Benton | OU5: Barry | OW5: Elko | OY5: Grafton | PA5: Cape May | PC5: Colfax | PE5: Cattaraugus | PG5: Ashe | PI5: Athens | PK5: Columbia | PM5: Washington | PO5: Bamberg | PQ5: Blount | PS5: Archer | PU5: Daggett | PW5: Chesapeake (City) | PY5: Clallam | QA5: Brown | QH5: Arkansas | QI5: AR | QJ5: 100 | QK5: 200 | QM5: $350,000 - $499,999 | QN5: HO6_STORIES_MIN (Reference) | QO5: MAX | QP5: FACTOR | QR5: Short-Term Rental | QS5: Rental - Short Term/Seasonal | QU5: AL4 | QV5: 4 | QW5: Colorado | QX5: Blount | QY5: Graham | QZ5: Boone | RA5: Baca | RB5: New Haven | RD5: Brevard | RE5: Baldwin | RF5: Benewah | RG5: Brown | RH5: Blackford | RI5: Audubon | RJ5: Barton | RK5: Avoyelles | RL5: Hancock | RM5: Calvert | RN5: Essex | RO5: Antrim | RP5: Benton | RQ5: Benton | RR5: Barry | RS5: Elko | RT5: Grafton | RU5: Cape May | RV5: Colfax | RW5: Cattaraugus | RX5: Ashe | RY5: Athens | RZ5: Columbia | SA5: Washington | SB5: Bamberg | SC5: Blount | SD5: Archer | SE5: Daggett | SF5: Amelia | SG5: Clallam | SI5: Brown | SJ5: Georgia | SK5: GENEVA | SL5: NEW HAVEN | SN5: BREVARD | SO5: CHARLTON | SP5: IBERIA | SQ5: HANCOCK | SR5: WORCESTER | SS5: MIDDLESEX | ST5: PEARL RIVER | SU5: ROCKINGHAM | SV5: CUMBERLAND | SW5: NEW YORK | SX5: CAMDEN | SY5: WASHINGTON | SZ5: COLLETON | TA5: CALHOUN | TB5: LANCASTER
A6: DS Attribute Name | B6: SublineName | C6: DwellingValuation | D6: PersonalPropertyValuation | E6: PolicyformFactor | G6: DS Attribute Name | H6: SublineName | I6: StateRegionCode | J6: RatingTerritory | L6: BaseRate | N6: DS Attribute Name | O6: SublineName | P6: StateRegionCode | Q6: TIV | R6: TIV | S6: MinimumTiv | T6: TIVRateRelativityFactor | U6: MaximumTiv | V6: MaxTIVRateRelativityFactor | X6: DS Attribute Name | Y6: SublineName | Z6: StateRegionCode | AA6: RatingTerritory | AB6: MinimumNonWindRate | AD6: DS Attribute Name | AE6: Zipcode1 | AF6: County | AG6: State | AH6: RatingTerritory | AJ6: DS Attribute Name | AK6: SublineName | AL6: StateRegionCode | AM6: ConstructionType | AO6: ConstructionTypeFactor | AQ6: DS Attribute Name | AR6: SublineName | AS6: StateRegionCode | AT6: Occupancy | AV6: OccupancyFactor | AX6: DS Attribute Name | AY6: SublineName | AZ6: StateRegionCode | BA6: AgeOfHome | BB6: AgeOfHome | BD6: AllOtherAgeofHomeFactor | BF6: DS Attribute Name | BG6: SublineName | BH6: StateRegionCode | BI6: AgeOfHome | BJ6: AgeOfHome | BK6: AgeOfRoof | BL6: AgeOfRoof | BN6: AgeOfRoofFactor | BP6: DS Attribute Name | BQ6: SublineName | BR6: StateRegionCode | BS6: CoverageSelected | BT6: ConstructionType | BU6: NumberOfStories | BV6: NumberOfStories | BX6: NumberOfStoriesFactor | BZ6: DS Attribute Name | CA6: SublineName | CB6: StateRegionCode | CC6: NumberofLosses | CE6: LossSurchargeFactor | CG6: DS Attribute Name | CH6: SublineName | CI6: StateRegionCode | CJ6: LimitChosen | CK6: LimitChosen | CM6: CoverageABandFactor | CO6: DS Attribute Name | CP6: ExtendedReplacementCost | CQ6: ExtendedReplacementCostFactor | CS6: DS Attribute Name | CT6: SublineName | CU6: StateRegionCode | CV6: NumberOfFamilies | CX6: FamilyFactor | CZ6: DS Attribute Name | DA6: SublineName | DB6: StateRegionCode | DC6: ProtectionClass | DE6: ProtectionFactor | DG6: DS Attribute Name | DH6: SublineName | DI6: StateRegionCode | DJ6: Alarm | DL6: AlarmFactor | DN6: DS Attribute Name | DO6: SublineName | DP6: QuoteType | DQ6: StateRegionCode | DR6: County | DS6: Zipcode1 | DT6: WaterDamageSublimit | DV6: WaterDamageSublimitFactor | DX6: DS Attribute Name | DY6: SublineName | DZ6: StateRegionCode | EA6: DeductibleAmount | EB6: DeductibleType | ED6: DeductibleFactor | EF6: DS Attribute Name | EG6: SublineName | EH6: StateRegionCode | EI6: DeductibleAmount | EJ6: DeductibleAmount | EK6: DeductibleFactor | EM6: DS Attribute Name | EN6: SublineName | EO6: StateRegionCode | EP6: InsuranceScoreStatus | EQ6: InsuranceScore | ER6: InsuranceScore | ET6: NonWindBaseRate | EV6: DS Attribute Name | EW6: SublineName | EX6: StateRegionCode | EY6: RatingTerritory | EZ6: DateBuilt | FA6: DateBuilt | FB6: TigerCQApplicable | FD6: WindAalFactor | FF6: DS Attribute Name | FG6: SublineName | FH6: StateRegionCode | FI6: RatingTerritory | FJ6: CoastalWaterDistance | FL6: MinimumPropertyRateFactor | FN6: DS Attribute Name | FO6: SublineName | FP6: StateRegionCode | FQ6: LimitChosen | FS6: Premium | FU6: DS Attribute Name | FV6: SublineName | FW6: StateRegionCode | FX6: LimitChosen | FZ6: Premium | GB6: DS Attribute Name | GC6: SublineName | GD6: StateRegionCode | GE6: LimitChosen | GF6: Premium | GH6: DS Attribute Name | GI6: SublineName | GJ6: StateRegionCode | GK6: LimitChosen | GL6: Premium | GN6: DS Attribute Name | GO6: SublineName | GP6: StateRegionCode | GQ6: CoverageSelected | GR6: Premium | GT6: DS Attribute Name | GU6: SublineName | GV6: StateRegionCode | GW6: CoverageSelected | GX6: ConstructionType | GZ6: Factor | HB6: DS Attribute Name | HC6: SublineName | HD6: StateRegionCode | HE6: CoverageSelected | HF6: Deductible | HH6: DeductibleFactor | HJ6: DS Attribute Name | HK6: SublineName | HL6: StateRegionCode | HM6: Deductible | HN6: CoverageSelected | HO6: CoverageSelected | HP6: DeductibleFactor | HR6: DS Attribute Name | HS6: SublineName | HT6: StateRegionCode | HU6: LimitChosen | HW6: Premium | HY6: DS Attribute Name | HZ6: SublineName | IA6: StateRegionCode | IB6: CoverageSelected | ID6: Factor | IF6: DS Attribute Name | IG6: CoverageSelected | IH6: Factor | IJ6: DS Attribute Name | IK6: SublineName | IL6: StateRegionCode | IM6: LimitChosen | IO6: Premium | IQ6: DS Attribute Name | IR6: SublineName | IS6: StateRegionCode | IT6: MedicalLimit | IU6: Premium | IW6: DS Attribute Name | IX6: SublineName | IY6: StateRegionCode | IZ6: RatingTerritory | JA6: MinimumPremium | JC6: DS Attribute Name | JD6: State | JE6: Zipcode1 | JF6: County | JG6: City | JH6: BoBApplicableFactor | JJ6: DS Attribute Name | JK6: State | JL6: Zipcode1 | JM6: County | JN6: City | JO6: AgeOfHomeRiskFactor | JP6: ConstructionTypeRiskFactor | JQ6: RoofAgeRiskFactor | JS6: DS Attribute Name | JT6: WindDeductiblePercentage | JU6: WindHailDeductibleFactorRenewal | JW6: DS Attribute Name | JX6: - | JY6: - | KA6: DS Attribute Name | KB6: RatingTerritory | KC6: TerritoryRelativityFactor | KE6: DS Attribute Name | KF6: SublineName | KG6: StateRegionCode | KH6: PolicyFee | KJ6: DS Attribute Name | KK6: SublineName | KL6: PersonalPropertyType | KM6: ScheduledPersonalPropertyFactor | NG6: Bullock | NI6: Greenlee | NK6: Bradley | NM6: Bent | NO6: New London | NS6: Broward | NU6: Banks | NW6: Bingham | NY6: Bureau | OA6: Boone | OC6: Benton | OE6: Bourbon | OG6: Beauregard | OI6: Kennebec | OK6: Caroline | OM6: Franklin | OO6: Arenac | OQ6: Big Stone | OS6: Bolivar | OU6: Barton | OW6: Esmeralda | OY6: Hillsborough | PA6: Cumberland | PC6: Curry | PE6: Cayuga | PG6: Avery | PI6: Auglaize | PK6: Coos | PO6: Barnwell | PQ6: Bradley | PS6: Armstrong | PU6: Davis | PW6: Colonial Heights (City) | PY6: Clark | QA6: Buffalo | QH6: California | QI6: CA | QJ6: 100 | QK6: 200 | QM6: $500,000 - $1,000,000 | QN6: 1 | QO6: 3 | QP6: 1.1 | QR6: Vacant | QS6: Vacant | QU6: AL5 | QV6: 4 | QW6: Connecticut | QX6: Bullock | QY6: Greenlee | QZ6: Bradley | RA6: Bent | RB6: New London | RD6: Broward | RE6: Banks | RF6: Bingham | RG6: Bureau | RH6: Boone | RI6: Benton | RJ6: Bourbon | RK6: Beauregard | RL6: Kennebec | RM6: Caroline | RN6: Franklin | RO6: Arenac | RP6: Big Stone | RQ6: Bolivar | RR6: Barton | RS6: Esmeralda | RT6: Hillsborough | RU6: Cumberland | RV6: Curry | RW6: Cayuga | RX6: Avery | RY6: Auglaize | RZ6: Coos | SB6: Barnwell | SC6: Bradley | SD6: Armstrong | SE6: Davis | SF6: Amherst | SG6: Clark | SI6: Buffalo | SJ6: Louisiana | SK6: MOBILE | SL6: NEW LONDON | SN6: BROWARD | SO6: CHATHAM | SP6: IBERVILLE | SQ6: KENNEBEC | SS6: NANTUCKET | ST6: STONE | SU6: STRAFFORD | SV6: GLOUCESTER | SW6: PUTNAM | SX6: CARTERET | SZ6: DILLON | TA6: CAMERON | TB6: MATHEWS
A7: Fully Qualified DS Attribute Name | B7: Root/SolartisInsuredV1/SublineName | C7: Location/Building/DwellingValuation | D7: Location/Building/PersonalPropertyValuation | E7: Location/Building/PolicyformFactor | G7: Fully Qualified DS Attribute Name | H7: Root/SolartisInsuredV1/SublineName | I7: Insured/Location/StateRegionCode | J7: Insured/Location/RatingTerritory | L7: Location/Building/BaseRate | N7: Fully Qualified DS Attribute Name | O7: Root/SolartisInsuredV1/SublineName | P7: Insured/Location/StateRegionCode | Q7: Location/Building/TIV | R7: Location/Building/TIV | S7: Location/Building/MinimumTiv | T7: Location/Building/TIVRateRelativityFactor | U7: Location/Building/MaximumTiv | V7: Location/Building/MaxTIVRateRelativityFactor | X7: Fully Qualified DS Attribute Name | Y7: Root/SolartisInsuredV1/SublineName | Z7: Insured/Location/StateRegionCode | AA7: Insured/Location/RatingTerritory | AB7: Location/Building/MinimumNonWindRate | AD7: Fully Qualified DS Attribute Name | AE7: Insured/Location/Zipcode1 | AF7: Insured/Location/County | AG7: Root/SolartisInsuredV1/State | AH7: Insured/Location/RatingTerritory | AJ7: Fully Qualified DS Attribute Name | AK7: Root/SolartisInsuredV1/SublineName | AL7: Insured/Location/StateRegionCode | AM7: Location/Building/ConstructionType | AO7: Location/Building/ConstructionTypeFactor | AQ7: Fully Qualified DS Attribute Name | AR7: Root/SolartisInsuredV1/SublineName | AS7: Insured/Location/StateRegionCode | AT7: Location/Building/Occupancy | AV7: Location/Building/OccupancyFactor | AX7: Fully Qualified DS Attribute Name | AY7: Root/SolartisInsuredV1/SublineName | AZ7: Insured/Location/StateRegionCode | BA7: Location/Building/AgeOfHome | BB7: Location/Building/AgeOfHome | BD7: Location/Building/AllOtherAgeofHomeFactor | BF7: Fully Qualified DS Attribute Name | BG7: Root/SolartisInsuredV1/SublineName | BH7: Insured/Location/StateRegionCode | BI7: Location/Building/AgeOfHome | BJ7: Location/Building/AgeOfHome | BK7: Location/Building/AgeOfRoof | BL7: Location/Building/AgeOfRoof | BN7: Location/Building/AgeOfRoofFactor | BP7: Fully Qualified DS Attribute Name | BQ7: Root/SolartisInsuredV1/SublineName | BR7: Insured/Location/StateRegionCode | BS7: Building/PLWindCoverage/CoverageSelected | BT7: Location/Building/ConstructionType | BU7: Location/Building/NumberOfStories | BV7: Location/Building/NumberOfStories | BX7: Location/Building/NumberOfStoriesFactor | BZ7: Fully Qualified DS Attribute Name | CA7: Root/SolartisInsuredV1/SublineName | CB7: Insured/Location/StateRegionCode | CC7: Location/Building/NumberOfLosses | CE7: Location/Building/LossSurchargeFactor | CG7: Fully Qualified DS Attribute Name | CH7: Root/SolartisInsuredV1/SublineName | CI7: Insured/Location/StateRegionCode | CJ7: Building/DwellingCoverage/LimitChosen | CK7: Building/DwellingCoverage/LimitChosen | CM7: Location/Building/CoverageABandFactor | CO7: Fully Qualified DS Attribute Name | CP7: Location/Building/ExtendedReplacementCost | CQ7: Location/Building/ExtendedReplacementCostFactor | CS7: Fully Qualified DS Attribute Name | CT7: Root/SolartisInsuredV1/SublineName | CU7: Insured/Location/StateRegionCode | CV7: Location/Building/NumberOfFamilies | CX7: Location/Building/FamilyFactor | CZ7: Fully Qualified DS Attribute Name | DA7: Root/SolartisInsuredV1/SublineName | DB7: Insured/Location/StateRegionCode | DC7: Location/Building/ProtectionClass | DE7: Location/Building/ProtectionFactor | DG7: Fully Qualified DS Attribute Name | DH7: Root/SolartisInsuredV1/SublineName | DI7: Insured/Location/StateRegionCode | DJ7: Location/Building/Alarm | DL7: Location/Building/AlarmFactor | DN7: Fully Qualified DS Attribute Name | DO7: Root/SolartisInsuredV1/SublineName | DP7: Root/SolartisInsuredV1/QuoteType | DQ7: Insured/Location/StateRegionCode | DR7: Insured/Location/County | DS7: Insured/Location/Zipcode1 | DT7: Location/Building/WaterDamageSublimit | DV7: Location/Building/WaterDamageSublimitFactor | DX7: Fully Qualified DS Attribute Name | DY7: Root/SolartisInsuredV1/SublineName | DZ7: Insured/Location/StateRegionCode | EA7: Building/AllOtherPerils/DeductibleAmount | EB7: Building/AllOtherPerils/DeductibleType | ED7: Building/AllOtherPerils/DeductibleFactor | EF7: Fully Qualified DS Attribute Name | EG7: Root/SolartisInsuredV1/SublineName | EH7: Insured/Location/StateRegionCode | EI7: Building/AllOtherPerils/DeductibleAmount | EJ7: Building/WaterDamage/DeductibleAmount | EK7: Building/WaterDamage/DeductibleFactor | EM7: Fully Qualified DS Attribute Name | EN7: Root/SolartisInsuredV1/SublineName | EO7: Insured/Location/StateRegionCode | EP7: Account/Insured/InsuranceScoreStatus | EQ7: Account/Insured/InsuranceScore | ER7: Account/Insured/InsuranceScore | ET7: Location/Building/NonWindBaseRate | EV7: Fully Qualified DS Attribute Name | EW7: Root/SolartisInsuredV1/SublineName | EX7: Insured/Location/StateRegionCode | EY7: Insured/Location/RatingTerritory | EZ7: Location/Building/DateBuilt | FA7: Location/Building/DateBuilt | FB7: Location/Building/TigerCQApplicable | FD7: Location/Building/WindAalFactor | FF7: Fully Qualified DS Attribute Name | FG7: Root/SolartisInsuredV1/SublineName | FH7: Insured/Location/StateRegionCode | FI7: Insured/Location/RatingTerritory | FJ7: Location/Building/CoastalWaterDistance | FL7: Location/Building/MinimumPropertyRateFactor | FN7: Fully Qualified DS Attribute Name | FO7: Root/SolartisInsuredV1/SublineName | FP7: Insured/Location/StateRegionCode | FQ7: Building/MoldCoverage/LimitChosen | FS7: Building/MoldCoverage/Premium | FU7: Fully Qualified DS Attribute Name | FV7: Root/SolartisInsuredV1/SublineName | FW7: Insured/Location/StateRegionCode | FX7: Building/WaterBackup/LimitChosen | FZ7: Building/WaterBackup/Premium | GB7: Fully Qualified DS Attribute Name | GC7: Root/SolartisInsuredV1/SublineName | GD7: Insured/Location/StateRegionCode | GE7: Building/IFCoverage/LimitChosen | GF7: Building/IFCoverage/Premium | GH7: Fully Qualified DS Attribute Name | GI7: Root/SolartisInsuredV1/SublineName | GJ7: Insured/Location/StateRegionCode | GK7: Building/LossAssessment/LimitChosen | GL7: Building/LossAssessment/Premium | GN7: Fully Qualified DS Attribute Name | GO7: Root/SolartisInsuredV1/SublineName | GP7: Insured/Location/StateRegionCode | GQ7: Building/PersonalInjuryCoverage/CoverageSelected | GR7: Building/PersonalInjuryCoverage/Premium | GT7: Fully Qualified DS Attribute Name | GU7: Root/SolartisInsuredV1/SublineName | GV7: Insured/Location/StateRegionCode | GW7: Building/EQCoverage/CoverageSelected | GX7: Location/Building/ConstructionType | GZ7: Building/EQCoverage/Factor | HB7: Fully Qualified DS Attribute Name | HC7: Root/SolartisInsuredV1/SublineName | HD7: Insured/Location/StateRegionCode | HE7: Building/EQCoverage/CoverageSelected | HF7: Building/EQCoverage/Deductible | HH7: Building/EQCoverage/DeductibleFactor | HJ7: Fully Qualified DS Attribute Name | HK7: Root/SolartisInsuredV1/SublineName | HL7: Insured/Location/StateRegionCode | HM7: Building/EQCoverage/Deductible | HN7: Building/EQCoverage/CoverageSelected | HO7: Building/EQCoverage/CoverageSelected | HP7: Building/EQCoverage/DeductibleFactor | HR7: Fully Qualified DS Attribute Name | HS7: Root/SolartisInsuredV1/SublineName | HT7: Insured/Location/StateRegionCode | HU7: Building/TheftCoverage/LimitChosen | HW7: Building/TheftCoverage/Premium | HY7: Fully Qualified DS Attribute Name | HZ7: Root/SolartisInsuredV1/SublineName | IA7: Insured/Location/StateRegionCode | IB7: Building/VandalismOrMaliciousMischiefCoverage/CoverageSelected | ID7: Building/VandalismOrMaliciousMischiefCoverage/Factor | IF7: Fully Qualified DS Attribute Name | IG7: Building/ExtendedCoverage/CoverageSelected | IH7: Building/ExtendedCoverage/Factor | IJ7: Fully Qualified DS Attribute Name | IK7: Root/SolartisInsuredV1/SublineName | IL7: Insured/Location/StateRegionCode | IM7: Building/PersonalLiabilityCoverage/LimitChosen | IO7: Building/PersonalLiabilityCoverage/Premium | IQ7: Fully Qualified DS Attribute Name | IR7: Root/SolartisInsuredV1/SublineName | IS7: Insured/Location/StateRegionCode | IT7: Building/MedicalPaymentsCoverage/MedicalLimit | IU7: Building/MedicalPaymentsCoverage/Premium | IW7: Fully Qualified DS Attribute Name | IX7: Root/SolartisInsuredV1/SublineName | IY7: Insured/Location/StateRegionCode | IZ7: Insured/Location/RatingTerritory | JA7: Root/SolartisInsuredV1/MinimumPremium | JC7: Fully Qualified DS Attribute Name | JD7: Root/SolartisInsuredV1/State | JE7: Insured/Location/Zipcode1 | JF7: Insured/Location/County | JG7: Insured/Location/City | JH7: Insured/Location/BoBApplicableFactor | JJ7: Fully Qualified DS Attribute Name | JK7: Root/SolartisInsuredV1/State | JL7: Insured/Location/Zipcode1 | JM7: Insured/Location/County | JN7: Insured/Location/City | JO7: Location/Building/AgeOfHomeRiskFactor | JP7: Location/Building/ConstructionTypeRiskFactor | JQ7: Location/Building/RoofAgeRiskFactor | JS7: Fully Qualified DS Attribute Name | JT7: Location/Building/WindDeductiblePercentage | JU7: Building/Coverage/WindHailDeductibleFactorRenewal | JW7: Fully Qualified DS Attribute Name | JX7: - | JY7: - | KA7: Fully Qualified DS Attribute Name | KB7: Insured/Location/RatingTerritory | KC7: Location/Building/TerritoryRelativityFactor | KE7: Fully Qualified DS Attribute Name | KF7: Root/SolartisInsuredV1/SublineName | KG7: Insured/Location/StateRegionCode | KH7: Root/SolartisInsuredV1/PolicyFee | KJ7: Fully Qualified DS Attribute Name | KK7: Root/SolartisInsuredV1/SublineName | KL7: Location/Building/PersonalPropertyType | KM7: Location/Building/ScheduledPersonalPropertyFactor | NG7: Butler | NI7: La Paz | NK7: Calhoun | NM7: Boulder | NO7: Tolland | NS7: Calhoun | NU7: Barrow | NW7: Blaine | NY7: Calhoun | OA7: Brown | OC7: Black Hawk | OE7: Brown | OG7: Bienville | OI7: Knox | OK7: Carroll | OM7: Hampden | OO7: Baraga | OQ7: Blue Earth | OS7: Calhoun | OU7: Bates | OW7: Eureka | OY7: Merrimack | PA7: Essex | PC7: De Baca | PE7: Chautauqua | PG7: Beaufort | PI7: Belmont | PK7: Crook | PO7: Beaufort | PQ7: Campbell | PS7: Atascosa | PU7: Duchesne | PW7: Covington (City) | PY7: Columbia | QA7: Burnett | QH7: Colorado | QI7: CO | QJ7: 100 | QK7: 200 | QM7: $1,000,000+ | QN7: 4 | QO7: 7 | QP7: 1 | QR7: Builders Risk | QU7: AL6 | QV7: 4 | QW7: Delaware | QX7: Butler | QY7: La Paz | QZ7: Calhoun | RA7: Boulder | RB7: Tolland | RD7: Calhoun | RE7: Barrow | RF7: Blaine | RG7: Calhoun | RH7: Brown | RI7: Black Hawk | RJ7: Brown | RK7: Bienville | RL7: Knox | RM7: Carroll | RN7: Hampden | RO7: Baraga | RP7: Blue Earth | RQ7: Calhoun | RR7: Bates | RS7: Eureka | RT7: Merrimack | RU7: Essex | RV7: De Baca | RW7: Chautauqua | RX7: Beaufort | RY7: Belmont | RZ7: Crook | SB7: Beaufort | SC7: Campbell | SD7: Atascosa | SE7: Duchesne | SF7: Appomattox | SG7: Columbia | SI7: Burnett | SJ7: Maine | SK7: MONROE | SL7: TOLLAND | SN7: CALHOUN | SO7: EFFINGHAM | SP7: JEFFERSON | SQ7: KNOX | SS7: NORFOLK | SV7: HUDSON | SW7: QUEENS | SX7: CHOWAN | SZ7: DORCHESTER | TA7: CHAMBERS | TB7: MIDDLESEX
A8: 1 | B8: DP1 | C8: Actual Cash Value | D8: Actual Cash Value | E8: 0.9 | G8: 1 | H8: HO3 | I8: AK | J8: AK1 | K8: Annual | L8: 0.3675 | N8: 1 | O8: HO6 | P8: CW | Q8: 0 | R8: 4999 | S8: 0 | T8: 0.955 | U8: 5000 | V8: 0.955 | X8: 1 | Y8: HO6 | Z8: CT | AA8: 1 | AB8: 0.2 | AD8: 1 | AE8: 28428 | AF8: New Hanover | AG8: North Carolina | AH8: NC6 | AJ8: 1 | AK8: HO3 | AL8: CW | AM8: Frame | AN8: Annual | AO8: 1 | AQ8: 1 | AR8: HO3 | AS8: CW | AT8: Builders Risk | AU8: Annual | AV8: 1 | AX8: 1 | AY8: HO6 | AZ8: CW | BA8: 0 | BB8: 0 | BC8: Annual | BD8: 0.8 | BF8: 1 | BG8: HO3 | BH8: CW | BI8: -1 | BJ8: 10 | BK8: -1 | BL8: 10 | BM8: Annual | BN8: 1 | BP8: 1 | BQ8: HO6 | BR8: CW | BS8: NO | BT8: Frame | BU8: 0 | BV8: 1 | BW8: Annual | BX8: 1 | BZ8: 1 | CA8: HO3 | CB8: CW | CC8: 0 | CD8: Annual | CE8: 0.98 | CG8: 1 | CH8: Builders Risk | CI8: CW | CJ8: 0 | CK8: 99999 | CL8: Monthly | CM8: 2 | CO8: 1 | CP8: Yes | CQ8: 1.1 | CS8: 1 | CT8: HO3 | CU8: CW | CV8: 1 | CW8: Annual | CX8: 1 | CZ8: 1 | DA8: HO3 | DB8: CW | DC8: 1 | DD8: Annual | DE8: 1 | DG8: 1 | DH8: HO3 | DI8: CW | DJ8: None | DK8: Annual | DL8: 1 | DN8: 1 | DO8: HO3 | DP8: NEW_BUSINESS | DQ8: FL | DR8: ALL | DS8: 33002 | DT8: 10000 | DU8: Annual | DV8: 1 | DX8: 1 | DY8: HO3 | DZ8: CW | EA8: 1000 | EC8: Annual | ED8: 1 | EF8: 1 | EG8: HO6 | EH8: CW | EI8: 500 | EJ8: 10000 | EK8: 0.95 | EM8: 1 | EN8: HO3 | EO8: CW | EP8: 1 | EQ8: 835 | ER8: 997 | ES8: Annual | ET8: 0.75 | EV8: 1 | EW8: HO3 | EX8: AK | EY8: 1 | EZ8: 0 | FA8: 1994 | FB8: N | FC8: Annual | FD8: 0 | FF8: 1 | FG8: HO3 | FH8: AK | FI8: 1 | FJ8: 0 | FK8: Annual | FL8: 0.3 | FN8: 1 | FO8: HO3 | FP8: CW | FQ8: 5000 | FR8: Annual | FS8: 0 | FU8: 1 | FV8: HO3 | FW8: CW | FX8: 0 | FY8: Annual | FZ8: 0 | GB8: 1 | GC8: HO3 | GD8: CW | GE8: 15000 | GF8: 25 | GH8: 1 | GI8: HO6 | GJ8: CW | GK8: 10000 | GL8: 25 | GN8: 1 | GO8: HO6 | GP8: CW | GQ8: No | GR8: 0 | GT8: 1 | GU8: HO3 | GV8: SC | GW8: Yes | GX8: Frame | GY8: Annual | GZ8: 0.1 | HB8: 1 | HC8: HO3 | HD8: SC | HE8: Yes | HF8: 0 | HG8: Annual | HH8: 0 | HJ8: 1 | HK8: HO6 | HL8: SC | HM8: 0 | HN8: Yes | HO8: Fire Resistive | HP8: 0 | HR8: 1 | HS8: HO3 | HT8: CW | HU8: 0 | HV8: Annual | HW8: 0 | HY8: 1 | HZ8: HO3 | IA8: CW | IB8: No | IC8: Annual | ID8: 1 | IF8: 1 | IG8: Included | IH8: 1 | IJ8: 1 | IK8: HO3 | IL8: CW | IM8: 0 | IN8: Annual | IO8: 0 | IQ8: 1 | IR8: HO3 | IS8: CW | IT8: 0 | IU8: 0 | IW8: 1 | IX8: HO6 | IY8: CT | IZ8: 1 | JA8: 350 | JC8: 1 | JD8: Alabama | JE8: ALL | JF8: ALL | JG8: ALL | JH8: -0.05 | JJ8: 1 | JK8: Alabama | JL8: ALL | JM8: ALL | JN8: ALL | JO8: 0.04 | JP8: -0.025 | JQ8: 0.1 | JS8: 1 | JT8: 1000 | JU8: 1 | JW8: 1 | JX8: Alabama | JY8: Autauga | KA8: 1 | KB8: AL8 | KC8: 0.8 | KE8: 1 | KF8: ALL | KG8: MI | KH8: 59 | KJ8: 1 | KK8: HO3 | KL8: Mens Jewelry | KM8: 0.0275 | NG8: Calhoun | NI8: Maricopa | NK8: Carroll | NM8: City & of Broomfield | NO8: Windham | NS8: Charlotte | NU8: Bartow | NW8: Boise | NY8: Carroll | OA8: Carroll | OC8: Boone | OE8: Butler | OG8: Bossier | OI8: Lincoln | OK8: Cecil | OM8: Hampshire | OO8: Barry | OQ8: Brown | OS8: Carroll | OU8: Benton | OW8: Humboldt | OY8: Rockingham | PA8: Gloucester | PC8: Dona Ana | PE8: Chemung | PG8: Bertie | PI8: Brown | PK8: Curry | PO8: Berkeley | PQ8: Cannon | PS8: Austin | PU8: Emery | PW8: Danville (City) | PY8: Cowlitz | QA8: Calumet | QH8: Connecticut | QI8: CT | QJ8: 0 | QK8: 0 | QN8: 8 | QO8: 10 | QP8: 0.95 | QU8: AL7 | QV8: 4 | QW8: Florida | QX8: Calhoun | QY8: Maricopa | QZ8: Carroll | RA8: Chaffee | RB8: Windham | RD8: Charlotte | RE8: Bartow | RF8: Boise | RG8: Carroll | RH8: Carroll | RI8: Boone | RJ8: Butler | RK8: Bossier | RL8: Lincoln | RM8: Cecil | RN8: Hampshire | RO8: Barry | RP8: Brown | RQ8: Carroll | RR8: Benton | RS8: Humboldt | RT8: Rockingham | RU8: Gloucester | RV8: Dona Ana | RW8: Chemung | RX8: Bertie | RY8: Brown | RZ8: Curry | SB8: Berkeley | SC8: Cannon | SD8: Austin | SE8: Emery | SF8: Arlington | SG8: Cowlitz | SI8: Calumet | SJ8: Maryland | SK8: WASHINGTON | SL8: WINDHAM | SN8: CHARLOTTE | SO8: EVANS | SP8: JEFFERSON DAVIS | SQ8: LINCOLN | SS8: PLYMOUTH | SV8: MERCER | SW8: RICHMOND | SX8: COLUMBUS | SZ8: GEORGETOWN | TA8: FORT BEND | TB8: NORFOLK CITY
A9: 2 | B9: DP3 | C9: Replacement Cost | D9: Actual Cash Value | E9: 1 | G9: 2 | H9: HO3 | I9: AL | J9: AL1 | K9: Annual | L9: 0.31 | N9: 2 | O9: HO6 | P9: CW | Q9: 5000 | R9: 9999 | S9: 5000 | T9: 0.955 | U9: 10000 | V9: 0.96 | X9: 2 | Y9: HO6 | Z9: CT | AA9: 2 | AB9: 0.2 | AD9: 2 | AE9: 28402 | AF9: New Hanover | AG9: North Carolina | AH9: NC7 | AJ9: 2 | AK9: HO5 | AL9: CW | AM9: Frame | AN9: Annual | AO9: 1 | AQ9: 2 | AR9: HO5 | AS9: CW | AT9: Builders Risk | AU9: Annual | AV9: 1 | AX9: 2 | AY9: HO6 | AZ9: CW | BA9: 1 | BB9: 1 | BC9: Annual | BD9: 0.81 | BF9: 2 | BG9: HO5 | BH9: CW | BI9: -1 | BJ9: 10 | BK9: -1 | BL9: 10 | BM9: Annual | BN9: 1 | BP9: 2 | BQ9: HO6 | BR9: CW | BS9: NO | BT9: Frame | BU9: 2 | BV9: 100 | BW9: Annual | BX9: 1.05 | BZ9: 2 | CA9: HO3 | CB9: CW | CC9: 1 | CD9: Annual | CE9: 1 | CG9: 2 | CH9: Builders Risk | CI9: CW | CJ9: 100000 | CK9: 149999 | CL9: Monthly | CM9: 1.35 | CO9: 2 | CP9: No | CQ9: 1 | CS9: 2 | CT9: HO5 | CU9: CW | CV9: 1 | CW9: Annual | CX9: 1 | CZ9: 2 | DA9: HO5 | DB9: CW | DC9: 1 | DD9: Annual | DE9: 1 | DG9: 2 | DH9: HO5 | DI9: CW | DJ9: None | DK9: Annual | DL9: 1 | DN9: 2 | DO9: HO3 | DP9: NEW_BUSINESS | DQ9: FL | DR9: ALL | DS9: 33004 | DT9: 10000 | DU9: Annual | DV9: 1 | DX9: 2 | DY9: HO5 | DZ9: CW | EA9: 1000 | EC9: Annual | ED9: 1 | EF9: 2 | EG9: HO6 | EH9: CW | EI9: 1000 | EJ9: 10000 | EK9: 0.95 | EM9: 2 | EN9: HO3 | EO9: CW | EP9: 1 | EQ9: 799 | ER9: 834 | ES9: Annual | ET9: 0.8 | EV9: 2 | EW9: HO3 | EX9: AK | EY9: 1 | EZ9: 1995 | FA9: 2999 | FB9: N | FC9: Annual | FD9: 0 | FF9: 2 | FG9: HO3 | FH9: AK | FI9: 1 | FJ9: 540000 | FK9: Annual | FL9: 0.3 | FN9: 2 | FO9: HO5 | FP9: CW | FQ9: 5000 | FR9: Annual | FS9: 0 | FU9: 2 | FV9: HO5 | FW9: CW | FX9: 0 | FY9: Annual | FZ9: 0 | GB9: 2 | GC9: HO5 | GD9: CW | GE9: 15000 | GF9: 25 | GH9: 2 | GI9: HO6 | GJ9: CW | GK9: 11000 | GL9: 30 | GN9: 2 | GO9: HO6 | GP9: CW | GQ9: Yes | GR9: 15 | GT9: 2 | GU9: HO5 | GV9: SC | GW9: Yes | GX9: Frame | GY9: Annual | GZ9: 0.1 | HB9: 2 | HC9: HO5 | HD9: SC | HE9: Yes | HF9: 0 | HG9: Annual | HH9: 0 | HJ9: 2 | HK9: HO6 | HL9: SC | HM9: 5 | HN9: Yes | HO9: Fire Resistive | HP9: 0.05 | HR9: 2 | HS9: HO5 | HT9: CW | HU9: 0 | HV9: Annual | HW9: 0 | HY9: 2 | HZ9: HO5 | IA9: CW | IB9: No | IC9: Annual | ID9: 1 | IJ9: 2 | IK9: HO5 | IL9: CW | IM9: 0 | IN9: Annual | IO9: 0 | IQ9: 2 | IR9: HO3 | IS9: CW | IT9: 1000 | IU9: 0 | IW9: 2 | IX9: HO6 | IY9: CT | IZ9: 2 | JA9: 350 | JC9: 2 | JD9: Arizona | JE9: ALL | JF9: ALL | JG9: ALL | JH9: -0.05 | JJ9: 2 | JK9: Arizona | JL9: ALL | JM9: ALL | JN9: ALL | JO9: 0.025 | JP9: -0.02 | JQ9: 0.075 | JS9: 2 | JT9: Greater of $2,500 or 1% | JU9: 0.9 | JW9: 2 | JX9: Alabama | JY9: Barbour | KA9: 2 | KB9: CT8 | KC9: 0.7 | KE9: 2 | KF9: ALL | KG9: CT | KH9: 0 | KJ9: 2 | KK9: HO5 | KL9: Mens Jewelry | KM9: 0.0275 | NG9: Chambers | NI9: Mohave | NK9: Chicot | NM9: Chaffee | NS9: Citrus | NU9: Ben Hill | NW9: Bonner | NY9: Cass | OA9: Cass | OC9: Bremer | OE9: Chase | OG9: Caddo | OI9: Oxford | OK9: Charles | OM9: Middlesex | OO9: Bay | OQ9: Carlton | OS9: Chickasaw | OU9: Bollinger | OW9: Lander | OY9: Strafford | PA9: Hudson | PC9: Eddy | PE9: Chenango | PG9: Bladen | PI9: Butler | PK9: Deschutes | PO9: Calhoun | PQ9: Carroll | PS9: Bailey | PU9: Garfield | PW9: Emporia (City) | PY9: Douglas | QA9: Chippewa | QH9: Delaware | QI9: DE | QJ9: 100 | QK9: 200 | QN9: 11 | QO9: 9999 | QP9: 0.9 | QU9: AL8 | QV9: 4.5 | QW9: Georgia | QX9: Chambers | QY9: Mohave | QZ9: Chicot | RA9: Cheyenne | RD9: Citrus | RE9: Ben Hill | RF9: Bonner | RG9: Cass | RH9: Cass | RI9: Bremer | RJ9: Chase | RK9: Caddo | RL9: Oxford | RM9: Charles | RN9: Middlesex | RO9: Bay | RP9: Carlton | RQ9: Chickasaw | RR9: Bollinger | RS9: Lander | RT9: Strafford | RU9: Hudson | RV9: Eddy | RW9: Chenango | RX9: Bladen | RY9: Butler | RZ9: Deschutes | SB9: Calhoun | SC9: Carroll | SD9: Bailey | SE9: Garfield | SF9: Augusta | SG9: Douglas | SI9: Chippewa | SJ9: Massachusetts | SN9: CITRUS | SO9: GLYNN | SP9: LAFAYETTE | SQ9: OXFORD | SS9: SUFFOLK | SV9: MIDDLESEX | SW9: SUFFOLK | SX9: CRAVEN | SZ9: HAMPTON | TA9: GALVESTON | TB9: NORTHAMPTON
A10: 3 | B10: HO3 | C10: Actual Cash Value | D10: Actual Cash Value | E10: 0.92 | G10: 3 | H10: HO3 | I10: AL | J10: AL2 | K10: Annual | L10: 0.31 | N10: 3 | O10: HO6 | P10: CW | Q10: 10000 | R10: 19999 | S10: 10000 | T10: 0.96 | U10: 20000 | V10: 0.965 | X10: 3 | Y10: HO6 | Z10: CT | AA10: 3 | AB10: 0.2 | AD10: 3 | AE10: 28461 | AF10: Brunswick | AG10: North Carolina | AH10: NC8 | AJ10: 3 | AK10: HO8 | AL10: CW | AM10: Frame | AN10: Annual | AO10: 1 | AQ10: 3 | AR10: HO8 | AS10: CW | AT10: Builders Risk | AU10: Annual | AV10: 1 | AX10: 3 | AY10: HO6 | AZ10: CW | BA10: 10 | BB10: 10 | BC10: Annual | BD10: 0.92 | BF10: 3 | BG10: HO8 | BH10: CW | BI10: -1 | BJ10: 10 | BK10: -1 | BL10: 10 | BM10: Annual | BN10: 1 | BP10: 3 | BQ10: HO6 | BR10: CW | BS10: NO | BT10: Masonry | BU10: 0 | BV10: 1 | BW10: Annual | BX10: 1 | BZ10: 3 | CA10: HO3 | CB10: CW | CC10: 2 | CD10: Annual | CE10: 1.1 | CG10: 3 | CH10: Builders Risk | CI10: CW | CJ10: 150000 | CK10: 249999 | CL10: Monthly | CM10: 1.2 | CS10: 3 | CT10: HO8 | CU10: CW | CV10: 1 | CW10: Annual | CX10: 1 | CZ10: 3 | DA10: HO8 | DB10: CW | DC10: 1 | DD10: Annual | DE10: 1 | DG10: 3 | DH10: HO8 | DI10: CW | DJ10: None | DK10: Annual | DL10: 1 | DN10: 3 | DO10: HO3 | DP10: NEW_BUSINESS | DQ10: FL | DR10: ALL | DS10: 33013 | DT10: 10000 | DU10: Annual | DV10: 1 | DX10: 3 | DY10: HO8 | DZ10: CW | EA10: 1000 | EC10: Annual | ED10: 1 | EF10: 3 | EG10: HO6 | EH10: CW | EI10: 2500 | EJ10: 10000 | EK10: 0.9 | EM10: 3 | EN10: HO3 | EO10: CW | EP10: 1 | EQ10: 769 | ER10: 798 | ES10: Annual | ET10: 0.85 | EV10: 3 | EW10: HO3 | EX10: AL | EY10: 1 | EZ10: 0 | FA10: 1994 | FB10: Y | FC10: Annual | FD10: 10 | FF10: 3 | FG10: HO3 | FH10: AK | FI10: 1 | FJ10: 530000 | FK10: Annual | FL10: 0.3 | FN10: 3 | FO10: HO8 | FP10: CW | FQ10: 5000 | FR10: Annual | FS10: 0 | FU10: 3 | FV10: HO8 | FW10: CW | FX10: 0 | FY10: Annual | FZ10: 0 | GB10: 3 | GC10: HO8 | GD10: CW | GE10: 15000 | GF10: 25 | GH10: 3 | GI10: HO6 | GJ10: CW | GK10: 12000 | GL10: 35 | GT10: 3 | GU10: HO8 | GV10: SC | GW10: Yes | GX10: Frame | GY10: Annual | GZ10: 0.1 | HB10: 3 | HC10: HO8 | HD10: SC | HE10: Yes | HF10: 0 | HG10: Annual | HH10: 0 | HJ10: 3 | HK10: HO6 | HL10: SC | HM10: 10 | HN10: Yes | HO10: Fire Resistive | HP10: 0.04 | HR10: 3 | HS10: HO8 | HT10: CW | HU10: 0 | HV10: Annual | HW10: 0 | HY10: 3 | HZ10: HO8 | IA10: CW | IB10: No | IC10: Annual | ID10: 1 | IJ10: 3 | IK10: HO8 | IL10: CW | IM10: 0 | IN10: Annual | IO10: 0 | IQ10: 3 | IR10: HO3 | IS10: CW | IT10: 10000 | IU10: 40 | IW10: 3 | IX10: HO6 | IY10: CT | IZ10: 3 | JA10: 350 | JC10: 3 | JD10: Arkansas | JE10: ALL | JF10: ALL | JG10: ALL | JH10: -0.05 | JJ10: 3 | JK10: Arkansas | JL10: ALL | JM10: ALL | JN10: ALL | JO10: 0.02 | JP10: -0.03 | JQ10: 0.06 | JS10: 3 | JT10: Greater of $5,000 or 2% | JU10: 0.8 | JW10: 3 | JX10: Alabama | JY10: Baldwin | KA10: 3 | KB10: FL5 | KC10: 1.45 | KE10: 3 | KF10: ALL | KG10: OR | KH10: 100 | KJ10: 3 | KK10: HO8 | KL10: Mens Jewelry | KM10: 0.0275 | NG10: Cherokee | NI10: Navajo | NK10: Clark | NM10: Cheyenne | NS10: Clay | NU10: Berrien | NW10: Bonneville | NY10: Champaign | OA10: Clark | OC10: Buchanan | OE10: Chautauqua | OG10: Calcasieu | OI10: Penobscot | OK10: Dorchester | OM10: Nantucket | OO10: Benzie | OQ10: Carver | OS10: Choctaw | OU10: Boone | OW10: Lincoln | OY10: Sullivan | PA10: Hunterdon | PC10: Grant | PE10: Clinton | PG10: Brunswick | PI10: Carroll | PK10: Douglas | PO10: Charleston | PQ10: Carter | PS10: Bandera | PU10: Grand | PW10: Fairfax (City) | PY10: Ferry | QA10: Clark | QH10: Washington_DC | QI10: DC | QJ10: 100 | QK10: 200 | QU10: CT1 | QV10: 2.5 | QW10: Idaho | QX10: Cherokee | QY10: Navajo | QZ10: Clark | RA10: City & of Broomfield | RD10: Clay | RE10: Berrien | RF10: Bonneville | RG10: Champaign | RH10: Clark | RI10: Buchanan | RJ10: Chautauqua | RK10: Calcasieu | RL10: Penobscot | RM10: Dorchester | RN10: Nantucket | RO10: Benzie | RP10: Carver | RQ10: Choctaw | RR10: Boone | RS10: Lincoln | RT10: Sullivan | RU10: Hunterdon | RV10: Grant | RW10: Clinton | RX10: Brunswick | RY10: Carroll | RZ10: Douglas | SB10: Charleston | SC10: Carter | SD10: Bandera | SE10: Grand | SF10: Bath | SG10: Ferry | SI10: Clark | SJ10: Mississippi | SN10: CLAY | SO10: LIBERTY | SP10: LAFOURCHE | SQ10: PENOBSCOT | SS10: WORCESTER | SV10: MONMOUTH | SW10: WESTCHESTER | SX10: CURRITUCK | SZ10: HORRY | TA10: HARDIN | TB10: NORTHUMBERLAND
A11: 4 | B11: HO3 | C11: Replacement Cost | D11: Actual Cash Value | E11: 0.95 | G11: 4 | H11: HO3 | I11: AL | J11: AL3 | K11: Annual | L11: 0.31 | N11: 4 | O11: HO6 | P11: CW | Q11: 20000 | R11: 29999 | S11: 20000 | T11: 0.965 | U11: 30000 | V11: 0.97 | X11: 4 | Y11: HO6 | Z11: CT | AA11: 4 | AB11: 0.2 | AD11: 4 | AE11: ALL | AF11: Chowan | AG11: North Carolina | AH11: NC10 | AJ11: 4 | AK11: DP1 | AL11: CW | AM11: Frame | AN11: Annual | AO11: 1 | AQ11: 4 | AR11: DP1 | AS11: CW | AT11: Builders Risk | AU11: Annual | AV11: 1 | AX11: 4 | AY11: HO6 | AZ11: CW | BA11: 11 | BB11: 11 | BC11: Annual | BD11: 0.94 | BF11: 4 | BG11: DP1 | BH11: CW | BI11: -1 | BJ11: 10 | BK11: -1 | BL11: 10 | BM11: Annual | BN11: 1 | BP11: 4 | BQ11: HO6 | BR11: CW | BS11: NO | BT11: Masonry | BU11: 2 | BV11: 3 | BW11: Annual | BX11: 1.05 | BZ11: 4 | CA11: HO3 | CB11: CW | CC11: 3 | CD11: Annual | CE11: 1.5 | CG11: 4 | CH11: Builders Risk | CI11: CW | CJ11: 250000 | CK11: 349999 | CL11: Monthly | CM11: 1 | CS11: 4 | CT11: DP1 | CU11: CW | CV11: 1 | CW11: Annual | CX11: 1 | CZ11: 4 | DA11: DP1 | DB11: CW | DC11: 1 | DD11: Annual | DE11: 1 | DG11: 4 | DH11: DP1 | DI11: CW | DJ11: None | DK11: Annual | DL11: 1 | DN11: 4 | DO11: HO3 | DP11: NEW_BUSINESS | DQ11: FL | DR11: ALL | DS11: 33014 | DT11: 10000 | DU11: Annual | DV11: 1 | DX11: 4 | DY11: DP1 | DZ11: CW | EA11: 1000 | EC11: Annual | ED11: 1 | EF11: 4 | EG11: HO6 | EH11: CW | EI11: 5000 | EJ11: 10000 | EK11: 0.9 | EM11: 4 | EN11: HO3 | EO11: CW | EP11: 1 | EQ11: 741 | ER11: 768 | ES11: Annual | ET11: 0.9 | EV11: 4 | EW11: HO3 | EX11: AL | EY11: 1 | EZ11: 1995 | FA11: 2999 | FB11: Y | FC11: Annual | FD11: 10 | FF11: 4 | FG11: HO3 | FH11: AK | FI11: 1 | FJ11: 400000 | FK11: Annual | FL11: 0.3 | FN11: 4 | FO11: DP1 | FP11: CW | FQ11: 5000 | FR11: Annual | FS11: 0 | FU11: 4 | FV11: DP1 | FW11: CW | FX11: 0 | FY11: Annual | FZ11: 0 | GB11: 4 | GC11: DP1 | GD11: CW | GE11: 15000 | GF11: 25 | GH11: 4 | GI11: HO6 | GJ11: CW | GK11: 13000 | GL11: 40 | GT11: 4 | GU11: DP1 | GV11: SC | GW11: Yes | GX11: Frame | GY11: Annual | GZ11: 0.1 | HB11: 4 | HC11: DP1 | HD11: SC | HE11: Yes | HF11: 0 | HG11: Annual | HH11: 0 | HJ11: 4 | HK11: HO6 | HL11: SC | HM11: 15 | HN11: Yes | HO11: Fire Resistive | HP11: 0.03 | HR11: 4 | HS11: DP1 | HT11: CW | HU11: 0 | HV11: Annual | HW11: 0 | HY11: 4 | HZ11: DP1 | IA11: CW | IB11: No | IC11: Annual | ID11: 1 | IJ11: 4 | IK11: DP1 | IL11: CW | IM11: 0 | IN11: Annual | IO11: 0 | IQ11: 4 | IR11: HO3 | IS11: CW | IT11: 2000 | IU11: 5 | IW11: 4 | IX11: HO6 | IY11: CT | IZ11: 4 | JA11: 350 | JC11: 4 | JD11: Colorado | JE11: ALL | JF11: ALL | JG11: ALL | JH11: -0.05 | JJ11: 4 | JK11: Colorado | JL11: ALL | JM11: ALL | JN11: ALL | JO11: 0.025 | JP11: -0.025 | JQ11: 0.07 | JS11: 4 | JT11: Greater of $10,000 or 4% | JU11: 0.7 | JW11: 4 | JX11: Alabama | JY11: Bibb | KA11: 4 | KB11: FL13 | KC11: 0.8 | KE11: 4 | KF11: ALL | KG11: MA | KH11: 100 | KJ11: 4 | KK11: DP1 | KL11: Mens Jewelry | KM11: 0.0275 | NG11: Chilton | NI11: Pima | NK11: Clay | NM11: Clear Creek | NS11: Collier | NU11: Bibb | NW11: Boundary | NY11: Christian | OA11: Clay | OC11: Buena Vista | OE11: Cherokee | OG11: Caldwell | OI11: Piscataquis | OK11: Frederick | OM11: Norfolk | OO11: Berrien | OQ11: Cass | OS11: Claiborne | OU11: Buchanan | OW11: Lyon | PA11: Mercer | PC11: Guadalupe | PE11: Columbia | PG11: Buncombe | PI11: Champaign | PK11: Gilliam | PO11: Cherokee | PQ11: Cheatham | PS11: Bastrop | PU11: Iron | PW11: Falls Church (City) | PY11: Franklin | QA11: Columbia | QH11: Florida | QI11: FL | QJ11: 35 | QK11: 35 | QU11: CT2 | QV11: 2.5 | QW11: Illinois | QX11: Chilton | QY11: Pima | QZ11: Clay | RA11: City and of Denver | RD11: Collier | RE11: Bibb | RF11: Boundary | RG11: Christian | RH11: Clay | RI11: Buena Vista | RJ11: Cherokee | RK11: Caldwell | RL11: Piscataquis | RM11: Frederick | RN11: Norfolk | RO11: Berrien | RP11: Cass | RQ11: Claiborne | RR11: Buchanan | RS11: Lyon | RU11: Mercer | RV11: Guadalupe | RW11: Columbia | RX11: Buncombe | RY11: Champaign | RZ11: Gilliam | SB11: Cherokee | SC11: Cheatham | SD11: Bastrop | SE11: Iron | SF11: Bedford | SG11: Franklin | SI11: Columbia | SJ11: New_Hampshire | SN11: COLLIER | SO11: LONG | SP11: ORLEANS | SQ11: SAGADAHOC | SV11: OCEAN | SX11: DARE | SZ11: JASPER | TA11: HARRIS | TB11: POQUOSON CITY
A12: 5 | B12: HO3 | C12: Replacement Cost | D12: Replacement Cost | E12: 1 | G12: 5 | H12: HO3 | I12: AL | J12: AL4 | K12: Annual | L12: 0.31 | N12: 5 | O12: HO6 | P12: CW | Q12: 30000 | R12: 39999 | S12: 30000 | T12: 0.97 | U12: 40000 | V12: 0.975 | X12: 5 | Y12: HO6 | Z12: CT | AA12: 5 | AB12: 0.2 | AD12: 5 | AE12: 27941 | AF12: Currituck | AG12: North Carolina | AH12: NC10 | AJ12: 5 | AK12: DP3 | AL12: CW | AM12: Frame | AN12: Annual | AO12: 1 | AQ12: 5 | AR12: DP3 | AS12: CW | AT12: Builders Risk | AU12: Annual | AV12: 1 | AX12: 5 | AY12: HO6 | AZ12: CW | BA12: 12 | BB12: 12 | BC12: Annual | BD12: 0.96 | BF12: 5 | BG12: DP3 | BH12: CW | BI12: -1 | BJ12: 10 | BK12: -1 | BL12: 10 | BM12: Annual | BN12: 1 | BP12: 5 | BQ12: HO6 | BR12: CW | BS12: NO | BT12: Masonry | BU12: 4 | BV12: 100 | BW12: Annual | BX12: 1.1 | BZ12: 5 | CA12: HO3 | CB12: CW | CC12: 4 | CD12: Annual | CE12: 2 | CG12: 5 | CH12: Builders Risk | CI12: CW | CJ12: 350000 | CK12: 499999 | CL12: Monthly | CM12: 0.95 | CS12: 5 | CT12: DP3 | CU12: CW | CV12: 1 | CW12: Annual | CX12: 1 | CZ12: 5 | DA12: DP3 | DB12: CW | DC12: 1 | DD12: Annual | DE12: 1 | DG12: 5 | DH12: DP3 | DI12: CW | DJ12: None | DK12: Annual | DL12: 1 | DN12: 5 | DO12: HO3 | DP12: NEW_BUSINESS | DQ12: FL | DR12: ALL | DS12: 33015 | DT12: 10000 | DU12: Annual | DV12: 1 | DX12: 5 | DY12: DP3 | DZ12: CW | EA12: 1000 | EC12: Annual | ED12: 1 | EF12: 5 | EG12: HO6 | EH12: CW | EI12: 10000 | EJ12: 10000 | EK12: 0.9 | EM12: 5 | EN12: HO3 | EO12: CW | EP12: 1 | EQ12: 0 | ER12: 548 | ES12: Annual | ET12: 4 | EV12: 5 | EW12: HO3 | EX12: AL | EY12: 2 | EZ12: 0 | FA12: 1994 | FB12: Y | FC12: Annual | FD12: 10 | FF12: 5 | FG12: HO3 | FH12: AK | FI12: 1 | FJ12: 260000 | FK12: Annual | FL12: 0.3 | FN12: 5 | FO12: DP3 | FP12: CW | FQ12: 5000 | FR12: Annual | FS12: 0 | FU12: 5 | FV12: DP3 | FW12: CW | FX12: 0 | FY12: Annual | FZ12: 0 | GB12: 5 | GC12: DP3 | GD12: CW | GE12: 15000 | GF12: 25 | GH12: 5 | GI12: HO6 | GJ12: CW | GK12: 14000 | GL12: 45 | GT12: 5 | GU12: DP3 | GV12: SC | GW12: Yes | GX12: Frame | GY12: Annual | GZ12: 0.1 | HB12: 5 | HC12: DP3 | HD12: SC | HE12: Yes | HF12: 0 | HG12: Annual | HH12: 0 | HJ12: 5 | HK12: HO6 | HL12: SC | HM12: 25 | HN12: Yes | HO12: Fire Resistive | HP12: 0.02 | HR12: 5 | HS12: DP3 | HT12: CW | HU12: 0 | HV12: Annual | HW12: 0 | HY12: 5 | HZ12: DP3 | IA12: CW | IB12: No | IC12: Annual | ID12: 1 | IJ12: 5 | IK12: DP3 | IL12: CW | IM12: 0 | IN12: Annual | IO12: 0 | IQ12: 5 | IR12: HO3 | IS12: CW | IT12: 3000 | IU12: 10 | IW12: 5 | IX12: HO6 | IY12: CT | IZ12: 5 | JA12: 350 | JC12: 5 | JD12: Connecticut | JE12: ALL | JF12: ALL | JG12: ALL | JH12: -0.05 | JJ12: 5 | JK12: Connecticut | JL12: ALL | JM12: ALL | JN12: ALL | JO12: 0.075 | JP12: 0.05 | JQ12: 0.15 | JS12: 5 | JT12: Greater of $15,000 or 5% | JU12: 0.6 | JW12: 5 | JX12: Alabama | JY12: Blount | KA12: 5 | KB12: FL21 | KC12: 0.6 | KE12: 5 | KF12: ALL | KG12: SC | KH12: 100 | KJ12: 5 | KK12: DP3 | KL12: Mens Jewelry | KM12: 0.0275 | NG12: Choctaw | NI12: Pinal | NK12: Cleburne | NM12: Conejos | NS12: Columbia | NU12: Bleckley | NW12: Butte | NY12: Clark | OA12: Clinton | OC12: Butler | OE12: Cheyenne | OG12: Cameron | OI12: Sagadahoc | OK12: Garrett | OM12: Plymouth | OO12: Branch | OQ12: Chippewa | OS12: Clarke | OU12: Butler | OW12: Mineral | PA12: Middlesex | PC12: Harding | PE12: Cortland | PG12: Burke | PI12: Clark | PK12: Grant | PO12: Chester | PQ12: Chester | PS12: Baylor | PU12: Juab | PW12: Franklin (City) | PY12: Garfield | QA12: Crawford | QH12: Georgia | QI12: GA | QJ12: 100 | QK12: 200 | QU12: CT3 | QV12: 2.5 | QW12: Indiana | QX12: Choctaw | QY12: Pinal | QZ12: Cleburne | RA12: Clear Creek | RD12: Columbia | RE12: Bleckley | RF12: Butte | RG12: Clark | RH12: Clinton | RI12: Butler | RJ12: Cheyenne | RK12: Cameron | RL12: Sagadahoc | RM12: Garrett | RN12: Plymouth | RO12: Branch | RP12: Chippewa | RQ12: Clarke | RR12: Butler | RS12: Mineral | RU12: Middlesex | RV12: Harding | RW12: Cortland | RX12: Burke | RY12: Clark | RZ12: Grant | SB12: Chester | SC12: Chester | SD12: Baylor | SE12: Juab | SF12: Bland | SG12: Garfield | SI12: Crawford | SJ12: New_Jersey | SN12: COLUMBIA | SO12: MCINTOSH | SP12: PLAQUEMINES | SQ12: SOMERSET | SV12: UNION | SX12: DUPLIN | SZ12: MARION | TA12: HIDALGO | TB12: PORTSMOUTH CITY
A13: 6 | B13: HO5 | C13: Replacement Cost | D13: Replacement Cost | E13: 1.05 | G13: 6 | H13: HO3 | I13: AL | J13: AL5 | K13: Annual | L13: 0.31 | N13: 6 | O13: HO6 | P13: CW | Q13: 40000 | R13: 49999 | S13: 40000 | T13: 0.975 | U13: 50000 | V13: 0.98 | X13: 6 | Y13: HO6 | Z13: CT | AA13: 6 | AB13: 0.2 | AD13: 6 | AE13: 27953 | AF13: Dare | AG13: North Carolina | AH13: NC10 | AJ13: 6 | AK13: HO3 | AL13: CW | AM13: Masonry | AN13: Annual | AO13: 0.9 | AQ13: 6 | AR13: HO3 | AS13: CW | AT13: Long-Term Rental | AU13: Annual | AV13: 1 | AX13: 6 | AY13: HO6 | AZ13: CW | BA13: 13 | BB13: 13 | BC13: Annual | BD13: 0.98 | BF13: 6 | BG13: HO3 | BH13: CW | BI13: 11 | BJ13: 999 | BK13: -1 | BL13: 5 | BM13: Annual | BN13: 0.95 | BP13: 6 | BQ13: HO6 | BR13: CW | BS13: NO | BT13: Steel | BU13: 1 | BV13: 3 | BW13: Annual | BX13: 1 | BZ13: 6 | CA13: HO5 | CB13: CW | CC13: 0 | CD13: Annual | CE13: 0.98 | CG13: 6 | CH13: Builders Risk | CI13: CW | CJ13: 500000 | CK13: 1000000 | CL13: Monthly | CM13: 0.9 | CS13: 6 | CT13: HO3 | CU13: CW | CV13: 2 | CW13: Annual | CX13: 1.1 | CZ13: 6 | DA13: HO3 | DB13: CW | DC13: 10 | DD13: Annual | DE13: 2 | DG13: 6 | DH13: HO3 | DI13: CW | DJ13: CentralStationBurglarAlarm | DK13: Annual | DL13: 0.95 | DN13: 6 | DO13: HO5 | DP13: NEW_BUSINESS | DQ13: FL | DR13: ALL | DS13: 33002 | DT13: 10000 | DU13: Annual | DV13: 1 | DX13: 6 | DY13: HO3 | DZ13: CW | EA13: 10000 | EC13: Annual | ED13: 0.875 | EF13: 6 | EG13: HO6 | EH13: CW | EI13: 500 | EJ13: 2500 | EK13: 1.1 | EM13: 6 | EN13: HO3 | EO13: CW | EP13: 1 | EQ13: 713 | ER13: 740 | ES13: Annual | ET13: 1 | EV13: 6 | EW13: HO3 | EX13: AL | EY13: 2 | EZ13: 1995 | FA13: 2999 | FB13: Y | FC13: Annual | FD13: 10 | FF13: 6 | FG13: HO3 | FH13: AK | FI13: 1 | FJ13: 130000 | FK13: Annual | FL13: 0.3 | FN13: 6 | FO13: HO3 | FP13: CW | FQ13: 10000 | FR13: Annual | FS13: 25 | FU13: 6 | FV13: HO3 | FW13: CW | FX13: 10000 | FY13: Annual | FZ13: 50 | GB13: 6 | GC13: HO3 | GD13: CW | GE13: 0 | GF13: 0 | GH13: 6 | GI13: HO6 | GJ13: CW | GK13: 15000 | GL13: 50 | GT13: 6 | GU13: HO3 | GV13: SC | GW13: Yes | GX13: Masonry | GY13: Annual | GZ13: 0.15 | HB13: 6 | HC13: HO3 | HD13: SC | HE13: Yes | HF13: 10 | HG13: Annual | HH13: 0.9 | HJ13: 6 | HK13: HO6 | HL13: SC | HM13: 0 | HN13: Yes | HO13: Frame | HP13: 0 | HR13: 6 | HS13: HO3 | HT13: CW | HU13: 5000 | HV13: Annual | HW13: 75 | HY13: 6 | HZ13: HO3 | IA13: CW | IB13: Yes | IC13: Annual | ID13: 1.1 | IJ13: 6 | IK13: HO3 | IL13: CW | IM13: 100000 | IN13: Annual | IO13: 25 | IQ13: 6 | IR13: HO3 | IS13: CW | IT13: 4000 | IU13: 15 | IW13: 6 | IX13: HO6 | IY13: CT | IZ13: 6 | JA13: 350 | JC13: 6 | JD13: Delaware | JE13: ALL | JF13: ALL | JG13: ALL | JH13: -0.05 | JJ13: 6 | JK13: Delaware | JL13: ALL | JM13: ALL | JN13: ALL | JO13: 0.04 | JP13: -0.02 | JQ13: 0.1 | JS13: 6 | JT13: Greater of $25,000 or 10% | JU13: 0.5 | JW13: 6 | JX13: Alabama | JY13: Bullock | KA13: 6 | KB13: FL29 | KC13: 0.92 | KE13: 6 | KF13: ALL | KG13: NY | KH13: 100 | KJ13: 6 | KK13: HO3 | KL13: Womens Jewelry | KM13: 0.0175 | NG13: Clarke | NI13: Santa Cruz | NK13: Cleveland | NM13: Costilla | NS13: Desoto | NU13: Brantley | NW13: Camas | NY13: Clay | OA13: Crawford | OC13: Calhoun | OE13: Clark | OG13: Catahoula | OI13: Somerset | OK13: Harford | OM13: Suffolk | OO13: Calhoun | OQ13: Chisago | OS13: Clay | OU13: Caldwell | OW13: Nye | PA13: Monmouth | PC13: Hidalgo | PE13: Delaware | PG13: Cabarrus | PI13: Clermont | PK13: Harney | PO13: Chesterfield | PQ13: Claiborne | PS13: Bee | PU13: Kane | PW13: Fredericksburg (City) | PY13: Grant | QA13: Dane | QH13: Hawaii | QI13: HI | QJ13: 100 | QK13: 200 | QU13: CT4 | QV13: 2.5 | QW13: Iowa | QX13: Clarke | QY13: Santa Cruz | QZ13: Cleveland | RA13: Conejos | RD13: DE SOTO | RE13: Brantley | RF13: Camas | RG13: Clay | RH13: Crawford | RI13: Calhoun | RJ13: Clark | RK13: Catahoula | RL13: Somerset | RM13: Harford | RN13: Suffolk | RO13: Calhoun | RP13: Chisago | RQ13: Clay | RR13: Caldwell | RS13: Nye | RU13: Monmouth | RV13: Hidalgo | RW13: Delaware | RX13: Cabarrus | RY13: Clermont | RZ13: Harney | SB13: Chesterfield | SC13: Claiborne | SD13: Bee | SE13: Kane | SF13: Botetourt | SG13: Grant | SI13: Dane | SJ13: New_York | SN13: DE SOTO | SO13: TATTNALL | SP13: ST. BERNARD | SQ13: WALDO | SX13: GATES | SZ13: WILLIAMSBURG | TA13: JACKSON | TB13: VIRGINIA BEACH CITY
A14: 7 | B14: HO8 | C14: Actual Cash Value | D14: Actual Cash Value | E14: 0.85 | G14: 7 | H14: HO3 | I14: AL | J14: AL6 | K14: Annual | L14: 0.567 | N14: 7 | O14: HO6 | P14: CW | Q14: 50000 | R14: 59999 | S14: 50000 | T14: 0.98 | U14: 60000 | V14: 0.99 | X14: 7 | Y14: HO6 | Z14: CT | AA14: 7 | AB14: 0.2 | AD14: 7 | AE14: 28451 | AF14: Brunswick | AG14: North Carolina | AH14: NC11 | AJ14: 7 | AK14: HO5 | AL14: CW | AM14: Masonry | AN14: Annual | AO14: 0.9 | AQ14: 7 | AR14: HO5 | AS14: CW | AT14: Long-Term Rental | AU14: Annual | AV14: 1 | AX14: 7 | AY14: HO6 | AZ14: CW | BA14: 14 | BB14: 14 | BC14: Annual | BD14: 0.99 | BF14: 7 | BG14: HO5 | BH14: CW | BI14: 11 | BJ14: 999 | BK14: -1 | BL14: 5 | BM14: Annual | BN14: 0.95 | BP14: 7 | BQ14: HO6 | BR14: CW | BS14: NO | BT14: Steel | BU14: 4 | BV14: 7 | BW14: Annual | BX14: 1 | BZ14: 7 | CA14: HO5 | CB14: CW | CC14: 1 | CD14: Annual | CE14: 1 | CG14: 7 | CH14: Builders Risk | CI14: CW | CJ14: 1000001 | CK14: 9999999999 | CL14: Monthly | CM14: 0.85 | CS14: 7 | CT14: HO5 | CU14: CW | CV14: 2 | CW14: Annual | CX14: 1.1 | CZ14: 7 | DA14: HO5 | DB14: CW | DC14: 10 | DD14: Annual | DE14: 2 | DG14: 7 | DH14: HO5 | DI14: CW | DJ14: CentralStationBurglarAlarm | DK14: Annual | DL14: 0.95 | DN14: 7 | DO14: HO5 | DP14: NEW_BUSINESS | DQ14: FL | DR14: ALL | DS14: 33004 | DT14: 10000 | DU14: Annual | DV14: 1 | DX14: 7 | DY14: HO5 | DZ14: CW | EA14: 10000 | EC14: Annual | ED14: 0.875 | EF14: 7 | EG14: HO6 | EH14: CW | EI14: 1000 | EJ14: 2500 | EK14: 1.1 | EM14: 7 | EN14: HO3 | EO14: CW | EP14: 1 | EQ14: 686 | ER14: 712 | ES14: Annual | ET14: 1.05 | EV14: 7 | EW14: HO3 | EX14: AL | EY14: 3 | EZ14: 0 | FA14: 1994 | FB14: Y | FC14: Annual | FD14: 10 | FF14: 7 | FG14: HO3 | FH14: AK | FI14: 1 | FJ14: 80000 | FK14: Annual | FL14: 0.3 | FN14: 7 | FO14: HO5 | FP14: CW | FQ14: 10000 | FR14: Annual | FS14: 25 | FU14: 7 | FV14: HO5 | FW14: CW | FX14: 10000 | FY14: Annual | FZ14: 50 | GB14: 7 | GC14: HO5 | GD14: CW | GE14: 0 | GF14: 0 | GH14: 7 | GI14: HO6 | GJ14: CW | GK14: 16000 | GL14: 55 | GT14: 7 | GU14: HO5 | GV14: SC | GW14: Yes | GX14: Masonry | GY14: Annual | GZ14: 0.15 | HB14: 7 | HC14: HO5 | HD14: SC | HE14: Yes | HF14: 10 | HG14: Annual | HH14: 0.9 | HJ14: 7 | HK14: HO6 | HL14: SC | HM14: 5 | HN14: Yes | HO14: Frame | HP14: 0.05 | HR14: 7 | HS14: HO5 | HT14: CW | HU14: 5000 | HV14: Annual | HW14: 75 | HY14: 7 | HZ14: HO5 | IA14: CW | IB14: Yes | IC14: Annual | ID14: 1.1 | IJ14: 7 | IK14: HO5 | IL14: CW | IM14: 100000 | IN14: Annual | IO14: 25 | IQ14: 7 | IR14: HO3 | IS14: CW | IT14: 5000 | IU14: 20 | IW14: 7 | IX14: HO6 | IY14: CT | IZ14: 7 | JA14: 350 | JC14: 7 | JD14: Florida | JE14: ALL | JF14: ALL | JG14: ALL | JH14: -0.05 | JJ14: 7 | JK14: Florida | JL14: ALL | JM14: ALL | JN14: ALL | JO14: 0.02 | JP14: -0.025 | JQ14: 0.06 | JW14: 7 | JX14: Alabama | JY14: Butler | KA14: 7 | KB14: FL37 | KC14: 0.92 | KE14: 7 | KF14: ALL | KG14: IN | KH14: 100 | KJ14: 7 | KK14: HO5 | KL14: Womens Jewelry | KM14: 0.0175 | NG14: Clay | NI14: Yavapai | NK14: Columbia | NM14: Crowley | NS14: Dixie | NU14: Brooks | NW14: Canyon | NY14: Clinton | OA14: Daviess | OC14: Carroll | OE14: Clay | OG14: Claiborne | OI14: Waldo | OK14: Howard | OM14: Worcester | OO14: Cass | OQ14: Clay | OS14: Coahoma | OU14: Callaway | OW14: Pershing | PA14: Morris | PC14: Lea | PE14: Dutchess | PG14: Caldwell | PI14: Clinton | PK14: Hood River | PO14: Clarendon | PQ14: Clay | PS14: Bell | PU14: Millard | PW14: Galax (City) | PY14: Grays Harbor | QA14: Dodge | QH14: Idaho | QI14: ID | QJ14: 100 | QK14: 200 | QU14: CT5 | QV14: 2.5 | QW14: Kansas | QX14: Clay | QY14: Yavapai | QZ14: Columbia | RA14: Costilla | RD14: Desoto | RE14: Brooks | RF14: Canyon | RG14: Clinton | RH14: Daviess | RI14: Carroll | RJ14: Clay | RK14: Claiborne | RL14: Waldo | RM14: Howard | RN14: Worcester | RO14: Cass | RP14: Clay | RQ14: Coahoma | RR14: Callaway | RS14: Pershing | RU14: Morris | RV14: Lea | RW14: Dutchess | RX14: Caldwell | RY14: Clinton | RZ14: Hood River | SB14: Clarendon | SC14: Clay | SD14: Bell | SE14: Millard | SF14: Bristol (City) | SG14: Grays Harbor | SI14: Dodge | SJ14: North_Carolina | SN14: DIXIE | SO14: WAYNE | SP14: ST. CHARLES | SQ14: WASHINGTON | SX14: HERTFORD | TA14: JEFFERSON | TB14: YORK
A15: 8 | B15: HO8 | C15: Functional Replacement Cost | D15: Actual Cash Value | E15: 0.9 | G15: 8 | H15: HO3 | I15: AR | J15: AR1 | K15: Annual | L15: 0.525 | N15: 8 | O15: HO6 | P15: CW | Q15: 60000 | R15: 69999 | S15: 60000 | T15: 0.99 | U15: 70000 | V15: 1 | X15: 8 | Y15: HO6 | Z15: CT | AA15: 8 | AB15: 0.2 | AD15: 8 | AE15: 28470 | AF15: Brunswick | AG15: North Carolina | AH15: NC11 | AJ15: 8 | AK15: HO8 | AL15: CW | AM15: Masonry | AN15: Annual | AO15: 0.9 | AQ15: 8 | AR15: HO8 | AS15: CW | AT15: Long-Term Rental | AU15: Annual | AV15: 1 | AX15: 8 | AY15: HO6 | AZ15: CW | BA15: 15 | BB15: 15 | BC15: Annual | BD15: 1 | BF15: 8 | BG15: HO8 | BH15: CW | BI15: 11 | BJ15: 999 | BK15: -1 | BL15: 5 | BM15: Annual | BN15: 0.95 | BP15: 8 | BQ15: HO6 | BR15: CW | BS15: NO | BT15: Steel | BU15: 8 | BV15: 14 | BW15: Annual | BX15: 0.85 | BZ15: 8 | CA15: HO5 | CB15: CW | CC15: 2 | CD15: Annual | CE15: 1.1 | CG15: 8 | CH15: Builders Risk DP3 | CI15: CW | CJ15: 0 | CK15: 99999 | CL15: Monthly | CM15: 2 | CS15: 8 | CT15: HO8 | CU15: CW | CV15: 2 | CW15: Annual | CX15: 1.1 | CZ15: 8 | DA15: HO8 | DB15: CW | DC15: 10 | DD15: Annual | DE15: 2 | DG15: 8 | DH15: HO8 | DI15: CW | DJ15: CentralStationBurglarAlarm | DK15: Annual | DL15: 0.95 | DN15: 8 | DO15: HO5 | DP15: NEW_BUSINESS | DQ15: FL | DR15: ALL | DS15: 33013 | DT15: 10000 | DU15: Annual | DV15: 1 | DX15: 8 | DY15: HO8 | DZ15: CW | EA15: 10000 | EC15: Annual | ED15: 0.875 | EF15: 8 | EG15: HO6 | EH15: CW | EI15: 2500 | EJ15: 2500 | EK15: 1 | EM15: 8 | EN15: HO3 | EO15: CW | EP15: 1 | EQ15: 653 | ER15: 685 | ES15: Annual | ET15: 1.2 | EV15: 8 | EW15: HO3 | EX15: AL | EY15: 3 | EZ15: 1995 | FA15: 2999 | FB15: Y | FC15: Annual | FD15: 10 | FF15: 8 | FG15: HO3 | FH15: AK | FI15: 1 | FJ15: 50000 | FK15: Annual | FL15: 0.3 | FN15: 8 | FO15: HO8 | FP15: CW | FQ15: 10000 | FR15: Annual | FS15: 25 | FU15: 8 | FV15: HO8 | FW15: CW | FX15: 10000 | FY15: Annual | FZ15: 50 | GB15: 8 | GC15: HO8 | GD15: CW | GE15: 0 | GF15: 0 | GH15: 8 | GI15: HO6 | GJ15: CW | GK15: 17000 | GL15: 60 | GT15: 8 | GU15: HO8 | GV15: SC | GW15: Yes | GX15: Masonry | GY15: Annual | GZ15: 0.15 | HB15: 8 | HC15: HO8 | HD15: SC | HE15: Yes | HF15: 10 | HG15: Annual | HH15: 0.9 | HJ15: 8 | HK15: HO6 | HL15: SC | HM15: 10 | HN15: Yes | HO15: Frame | HP15: 0.04 | HR15: 8 | HS15: HO8 | HT15: CW | HU15: 5000 | HV15: Annual | HW15: 75 | HY15: 8 | HZ15: HO8 | IA15: CW | IB15: Yes | IC15: Annual | ID15: 1.1 | IJ15: 8 | IK15: HO8 | IL15: CW | IM15: 100000 | IN15: Annual | IO15: 25 | IQ15: 8 | IR15: HO5 | IS15: CW | IT15: 0 | IU15: 0 | IW15: 8 | IX15: HO6 | IY15: CT | IZ15: 8 | JA15: 350 | JC15: 8 | JD15: Georgia | JE15: ALL | JF15: ALL | JG15: ALL | JH15: -0.05 | JJ15: 8 | JK15: Georgia | JL15: ALL | JM15: ALL | JN15: ALL | JO15: 0.025 | JP15: -0.025 | JQ15: 0.07 | JW15: 8 | JX15: Alabama | JY15: Calhoun | KA15: 8 | KB15: FL45 | KC15: 0.92 | KE15: 8 | KF15: ALL | KG15: VT | KH15: 100 | KJ15: 8 | KK15: HO8 | KL15: Womens Jewelry | KM15: 0.0175 | NG15: Cleburne | NI15: Yuma | NK15: Conway | NM15: Custer | NS15: Duval | NU15: Bryan | NW15: Caribou | NY15: Coles | OA15: Dearborn | OC15: Cass | OE15: Cloud | OG15: Concordia | OI15: Washington | OK15: Kent | OO15: Charlevoix | OQ15: Clearwater | OS15: Copiah | OU15: Camden | OW15: Storey | PA15: Ocean | PC15: Lincoln | PE15: Erie | PG15: Camden | PI15: Columbiana | PK15: Jackson | PO15: Colleton | PQ15: Cocke | PS15: Bexar | PU15: Morgan | PW15: Hampton (City) | PY15: Island | QA15: Door | QH15: Illinois | QI15: IL | QJ15: 100 | QK15: 200 | QU15: CT6 | QV15: 2.5 | QW15: Louisiana | QX15: Cleburne | QY15: Yuma | QZ15: Conway | RA15: Crowley | RD15: Dixie | RE15: Bryan | RF15: Caribou | RG15: Coles | RH15: DeKalb | RI15: Cass | RJ15: Cloud | RK15: Concordia | RL15: Washington | RM15: Kent | RO15: Charlevoix | RP15: Clearwater | RQ15: Copiah | RR15: Camden | RS15: Storey | RU15: Ocean | RV15: Lincoln | RW15: Erie | RX15: Camden | RY15: Columbiana | RZ15: Jackson | SB15: Colleton | SC15: Cocke | SD15: Bexar | SE15: Morgan | SF15: Brunswick | SG15: Island | SI15: Door | SJ15: Rhode_Island | SN15: DUVAL | SP15: ST. JAMES | SQ15: YORK | SX15: HYDE | TA15: JIM WELLS
A16: 9 | B16: HO8 | C16: Functional Replacement Cost | D16: Replacement Cost | E16: 0.95 | G16: 9 | H16: HO3 | I16: AZ | J16: AZ1 | K16: Annual | L16: 0.3675 | N16: 9 | O16: HO6 | P16: CW | Q16: 70000 | R16: 79999 | S16: 70000 | T16: 1 | U16: 80000 | V16: 1.05 | X16: 9 | Y16: HO6 | Z16: DE | AA16: 1 | AB16: 0.12 | AD16: 9 | AE16: 27968 | AF16: Dare | AG16: North Carolina | AH16: NC12 | AJ16: 9 | AK16: DP1 | AL16: CW | AM16: Masonry | AN16: Annual | AO16: 0.9 | AQ16: 9 | AR16: DP1 | AS16: CW | AT16: Long-Term Rental | AU16: Annual | AV16: 1 | AX16: 9 | AY16: HO6 | AZ16: CW | BA16: 16 | BB16: 16 | BC16: Annual | BD16: 1.01 | BF16: 9 | BG16: DP1 | BH16: CW | BI16: 11 | BJ16: 999 | BK16: -1 | BL16: 5 | BM16: Annual | BN16: 0.95 | BP16: 9 | BQ16: HO6 | BR16: CW | BS16: NO | BT16: Steel | BU16: 15 | BV16: 100 | BW16: Annual | BX16: 0.75 | BZ16: 9 | CA16: HO5 | CB16: CW | CC16: 3 | CD16: Annual | CE16: 1.5 | CG16: 9 | CH16: Builders Risk DP3 | CI16: CW | CJ16: 100000 | CK16: 149999 | CL16: Monthly | CM16: 1.35 | CS16: 9 | CT16: DP1 | CU16: CW | CV16: 2 | CW16: Annual | CX16: 1.1 | CZ16: 9 | DA16: DP1 | DB16: CW | DC16: 10 | DD16: Annual | DE16: 2 | DG16: 9 | DH16: DP1 | DI16: CW | DJ16: CentralStationBurglarAlarm | DK16: Annual | DL16: 0.95 | DN16: 9 | DO16: HO5 | DP16: NEW_BUSINESS | DQ16: FL | DR16: ALL | DS16: 33014 | DT16: 10000 | DU16: Annual | DV16: 1 | DX16: 9 | DY16: DP1 | DZ16: CW | EA16: 10000 | EC16: Annual | ED16: 0.875 | EF16: 9 | EG16: HO6 | EH16: CW | EI16: 500 | EJ16: 5000 | EK16: 1 | EM16: 9 | EN16: HO3 | EO16: CW | EP16: 1 | EQ16: 614 | ER16: 652 | ES16: Annual | ET16: 1.4 | EV16: 9 | EW16: HO3 | EX16: AL | EY16: 4 | EZ16: 0 | FA16: 1994 | FB16: Y | FC16: Annual | FD16: 10 | FF16: 9 | FG16: HO3 | FH16: AK | FI16: 1 | FJ16: 25000 | FK16: Annual | FL16: 0.3 | FN16: 9 | FO16: DP1 | FP16: CW | FQ16: 10000 | FR16: Annual | FS16: 25 | FU16: 9 | FV16: DP1 | FW16: CW | FX16: 10000 | FY16: Annual | FZ16: 50 | GB16: 9 | GC16: DP1 | GD16: CW | GE16: 0 | GF16: 0 | GH16: 9 | GI16: HO6 | GJ16: CW | GK16: 18000 | GL16: 65 | GT16: 9 | GU16: DP1 | GV16: SC | GW16: Yes | GX16: Masonry | GY16: Annual | GZ16: 0.15 | HB16: 9 | HC16: DP1 | HD16: SC | HE16: Yes | HF16: 10 | HG16: Annual | HH16: 0.9 | HJ16: 9 | HK16: HO6 | HL16: SC | HM16: 15 | HN16: Yes | HO16: Frame | HP16: 0.03 | HR16: 9 | HS16: DP1 | HT16: CW | HU16: 5000 | HV16: Annual | HW16: 75 | HY16: 9 | HZ16: DP1 | IA16: CW | IB16: Yes | IC16: Annual | ID16: 1.1 | IJ16: 9 | IK16: DP1 | IL16: CW | IM16: 100000 | IN16: Annual | IO16: 25 | IQ16: 9 | IR16: HO5 | IS16: CW | IT16: 1000 | IU16: 0 | IW16: 9 | IX16: HO6 | IY16: DC | IZ16: 1 | JA16: 350 | JC16: 9 | JD16: Idaho | JE16: ALL | JF16: ALL | JG16: ALL | JH16: -0.05 | JJ16: 9 | JK16: Idaho | JL16: ALL | JM16: ALL | JN16: ALL | JO16: 0.02 | JP16: -0.03 | JQ16: 0.055 | JW16: 9 | JX16: Alabama | JY16: Chambers | KA16: 9 | KB16: FL53 | KC16: 1.15 | KE16: 9 | KF16: ALL | KG16: NH | KH16: 100 | KJ16: 9 | KK16: DP1 | KL16: Womens Jewelry | KM16: 0.0175 | NG16: Coffee | NK16: Craighead | NM16: Delta | NS16: Escambia | NU16: Bulloch | NW16: Cassia | NY16: Cook | OA16: Decatur | OC16: Cedar | OE16: Coffey | OG16: De Soto | OI16: York | OK16: Montgomery | OO16: Cheboygan | OQ16: Cook | OS16: Covington | OU16: Cape Girardeau | OW16: Washoe | PA16: Passaic | PC16: Los Alamos | PE16: Essex | PG16: Carteret | PI16: Coshocton | PK16: Jefferson | PO16: Darlington | PQ16: Coffee | PS16: Blanco | PU16: Piute | PW16: Harrisonburg (City) | PY16: Jefferson | QA16: Douglas | QH16: Indiana | QI16: IN | QJ16: 100 | QK16: 200 | QU16: CT7 | QV16: 2.5 | QW16: Maine | QX16: Coffee | QZ16: Craighead | RA16: Custer | RD16: Duval | RE16: Bulloch | RF16: Cassia | RG16: Cook | RH16: Dearborn | RI16: Cedar | RJ16: Coffey | RK16: De Soto | RL16: York | RM16: Montgomery | RO16: Cheboygan | RP16: Cook | RQ16: Covington | RR16: Cape Girardeau | RS16: Washoe | RU16: Passaic | RV16: Los Alamos | RW16: Essex | RX16: Carteret | RY16: Coshocton | RZ16: Jefferson | SB16: Darlington | SC16: Coffee | SD16: Blanco | SE16: Piute | SF16: Buchanan | SG16: Jefferson | SI16: Douglas | SJ16: South_Carolina | SN16: ESCAMBIA | SP16: ST. JOHN THE BAPTIST | SX16: JONES | TA16: KENEDY
A17: 10 | B17: Builders Risk DP1 | C17: ALL | D17: ALL | E17: 1 | G17: 10 | H17: HO3 | I17: CA | J17: CA1 | K17: Annual | L17: 0.3675 | N17: 10 | O17: HO6 | P17: CW | Q17: 80000 | R17: 89999 | S17: 80000 | T17: 1.05 | U17: 90000 | V17: 1.1 | X17: 10 | Y17: HO6 | Z17: DE | AA17: 2 | AB17: 0.12 | AD17: 10 | AE17: 28520 | AF17: Carteret | AG17: North Carolina | AH17: NC13 | AJ17: 10 | AK17: DP3 | AL17: CW | AM17: Masonry | AN17: Annual | AO17: 0.9 | AQ17: 10 | AR17: DP3 | AS17: CW | AT17: Long-Term Rental | AU17: Annual | AV17: 1 | AX17: 10 | AY17: HO6 | AZ17: CW | BA17: 17 | BB17: 17 | BC17: Annual | BD17: 1.02 | BF17: 10 | BG17: DP3 | BH17: CW | BI17: 11 | BJ17: 999 | BK17: -1 | BL17: 5 | BM17: Annual | BN17: 0.95 | BP17: 10 | BQ17: HO6 | BR17: CW | BS17: NO | BT17: Reinforced Concrete | BU17: 1 | BV17: 3 | BW17: Annual | BX17: 1 | BZ17: 10 | CA17: HO5 | CB17: CW | CC17: 4 | CD17: Annual | CE17: 2 | CG17: 10 | CH17: Builders Risk DP3 | CI17: CW | CJ17: 150000 | CK17: 249999 | CL17: Monthly | CM17: 1.2 | CS17: 10 | CT17: DP3 | CU17: CW | CV17: 2 | CW17: Annual | CX17: 1.1 | CZ17: 10 | DA17: DP3 | DB17: CW | DC17: 10 | DD17: Annual | DE17: 2 | DG17: 10 | DH17: DP3 | DI17: CW | DJ17: CentralStationBurglarAlarm | DK17: Annual | DL17: 0.95 | DN17: 10 | DO17: HO5 | DP17: NEW_BUSINESS | DQ17: FL | DR17: ALL | DS17: 33015 | DT17: 10000 | DU17: Annual | DV17: 1 | DX17: 10 | DY17: DP3 | DZ17: CW | EA17: 10000 | EC17: Annual | ED17: 0.875 | EF17: 10 | EG17: HO6 | EH17: CW | EI17: 1000 | EJ17: 5000 | EK17: 1 | EM17: 10 | EN17: HO3 | EO17: CW | EP17: 1 | EQ17: 549 | ER17: 613 | ES17: Annual | ET17: 1.7 | EV17: 10 | EW17: HO3 | EX17: AL | EY17: 4 | EZ17: 1995 | FA17: 2999 | FB17: Y | FC17: Annual | FD17: 10 | FF17: 10 | FG17: HO3 | FH17: AK | FI17: 1 | FJ17: 10000 | FK17: Annual | FL17: 0.3 | FN17: 10 | FO17: DP3 | FP17: CW | FQ17: 10000 | FR17: Annual | FS17: 25 | FU17: 10 | FV17: DP3 | FW17: CW | FX17: 10000 | FY17: Annual | FZ17: 50 | GB17: 10 | GC17: DP3 | GD17: CW | GE17: 0 | GF17: 0 | GH17: 10 | GI17: HO6 | GJ17: CW | GK17: 19000 | GL17: 70 | GT17: 10 | GU17: DP3 | GV17: SC | GW17: Yes | GX17: Masonry | GY17: Annual | GZ17: 0.15 | HB17: 10 | HC17: DP3 | HD17: SC | HE17: Yes | HF17: 10 | HG17: Annual | HH17: 0.9 | HJ17: 10 | HK17: HO6 | HL17: SC | HM17: 25 | HN17: Yes | HO17: Frame | HP17: 0.02 | HR17: 10 | HS17: DP3 | HT17: CW | HU17: 5000 | HV17: Annual | HW17: 75 | HY17: 10 | HZ17: DP3 | IA17: CW | IB17: Yes | IC17: Annual | ID17: 1 | IJ17: 10 | IK17: DP3 | IL17: CW | IM17: 100000 | IN17: Annual | IO17: 25 | IQ17: 10 | IR17: HO5 | IS17: CW | IT17: 10000 | IU17: 40 | IW17: 10 | IX17: HO6 | IY17: ME | IZ17: 1 | JA17: 300 | JC17: 10 | JD17: Illinois | JE17: ALL | JF17: ALL | JG17: ALL | JH17: -0.05 | JJ17: 10 | JK17: Illinois | JL17: ALL | JM17: ALL | JN17: ALL | JO17: 0.035 | JP17: -0.025 | JQ17: 0.11 | JW17: 10 | JX17: Alabama | JY17: Cherokee | KA17: 10 | KB17: FL61 | KC17: 0.8 | KE17: 10 | KF17: ALL | KG17: WY | KH17: 100 | KJ17: 10 | KK17: DP3 | KL17: Womens Jewelry | KM17: 0.0175 | NG17: Colbert | NK17: Crawford | NM17: City and of Denver | NS17: Flagler | NU17: Burke | NW17: Clark | NY17: Crawford | OA17: DeKalb | OC17: Cerro Gordo | OE17: Comanche | OG17: East Baton Rouge | OK17: Prince George's | OO17: Chippewa | OQ17: Cottonwood | OS17: DeSoto | OU17: Carroll | OW17: White Pine | PA17: Salem | PC17: Luna | PE17: Franklin | PG17: Caswell | PI17: Crawford | PK17: Josephine | PO17: Dillon | PQ17: Crockett | PS17: Borden | PU17: Rich | PW17: Hopewell (City) | PY17: King | QA17: Dunn | QH17: Iowa | QI17: IA | QJ17: 100 | QK17: 200 | QU17: CT8 | QV17: 2.5 | QW17: Maryland | QX17: Colbert | QZ17: Crawford | RA17: Delta | RD17: Escambia | RE17: Burke | RF17: Clark | RG17: Crawford | RH17: Decatur | RI17: Cerro Gordo | RJ17: Comanche | RK17: East Baton Rouge | RM17: Prince George's | RO17: Chippewa | RP17: Cottonwood | RQ17: DeSoto | RR17: Carroll | RS17: White Pine | RU17: Salem | RV17: Luna | RW17: Franklin | RX17: Caswell | RY17: Crawford | RZ17: Josephine | SB17: Dillon | SC17: Crockett | SD17: Borden | SE17: Rich | SF17: Buckingham | SG17: King | SI17: Dunn | SJ17: Texas | SN17: FLAGLER | SP17: ST. MARTIN | SX17: MARTIN | TA17: KLEBERG
A18: 11 | B18: Builders Risk DP3 | C18: ALL | D18: ALL | E18: 1.1 | G18: 11 | H18: HO3 | I18: CO | J18: CO1 | K18: Annual | L18: 0.55 | N18: 11 | O18: HO6 | P18: CW | Q18: 90000 | R18: 99999 | S18: 90000 | T18: 1.1 | U18: 100000 | V18: 1.15 | X18: 11 | Y18: HO6 | Z18: DC | AA18: 1 | AB18: 0.3 | AD18: 11 | AE18: ALL | AF18: Allen | AG18: Ohio | AH18: OH1 | AJ18: 11 | AK18: HO3 | AL18: CW | AM18: Reinforced Concrete | AN18: Annual | AO18: 0.8 | AQ18: 11 | AR18: HO3 | AS18: CW | AT18: Primary | AU18: Annual | AV18: 1 | AX18: 11 | AY18: HO6 | AZ18: CW | BA18: 18 | BB18: 18 | BC18: Annual | BD18: 1.03 | BF18: 11 | BG18: HO3 | BH18: CW | BI18: 0 | BJ18: 10 | BK18: 0 | BL18: 10 | BM18: Annual | BN18: 1 | BP18: 11 | BQ18: HO6 | BR18: CW | BS18: NO | BT18: Reinforced Concrete | BU18: 4 | BV18: 7 | BW18: Annual | BX18: 1 | BZ18: 11 | CA18: HO8 | CB18: CW | CC18: 0 | CD18: Annual | CE18: 0.98 | CG18: 11 | CH18: Builders Risk DP3 | CI18: CW | CJ18: 250000 | CK18: 349999 | CL18: Monthly | CM18: 1 | CS18: 11 | CT18: HO3 | CU18: CW | CV18: 3 | CW18: Annual | CX18: 1.3 | CZ18: 11 | DA18: HO3 | DB18: CW | DC18: 2 | DD18: Annual | DE18: 1 | DG18: 11 | DH18: HO3 | DI18: CW | DJ18: CentralStationFireAlarm | DK18: Annual | DL18: 0.95 | DN18: 11 | DO18: DP3 | DP18: NEW_BUSINESS | DQ18: FL | DR18: ALL | DS18: 33002 | DT18: 10000 | DU18: Annual | DV18: 1 | DX18: 11 | DY18: HO3 | DZ18: CW | EA18: 2500 | EB18: 0 | EC18: Annual | ED18: 0.925 | EF18: 11 | EG18: HO6 | EH18: CW | EI18: 2500 | EJ18: 5000 | EK18: 0.95 | EM18: 11 | EN18: HO3 | EO18: CW | EP18: 2 | EQ18: -1 | ER18: -1 | ES18: Annual | ET18: 1.42 | EV18: 11 | EW18: HO3 | EX18: AL | EY18: 5 | EZ18: 0 | FA18: 1994 | FB18: Y | FC18: Annual | FD18: 10 | FF18: 11 | FG18: HO3 | FH18: AK | FI18: 1 | FJ18: 5000 | FK18: Annual | FL18: 0.3 | FN18: 11 | FO18: HO3 | FP18: CW | FQ18: 15000 | FR18: Annual | FS18: 50 | FU18: 11 | FV18: HO3 | FW18: CW | FX18: 25000 | FY18: Annual | FZ18: 100 | GH18: 11 | GI18: HO6 | GJ18: CW | GK18: 20000 | GL18: 75 | GT18: 11 | GU18: HO3 | GV18: SC | GW18: Yes | GX18: Reinforced Concrete | GY18: Annual | GZ18: 0.15 | HB18: 11 | HC18: HO3 | HD18: SC | HE18: Yes | HF18: 15 | HG18: Annual | HH18: 0.8 | HJ18: 11 | HK18: HO6 | HL18: SC | HM18: 0 | HN18: Yes | HO18: Masonry | HP18: 0 | HR18: 11 | HS18: Builders Risk | HT18: CW | HU18: 0 | HV18: Monthly | HW18: 0 | HY18: 11 | HZ18: VDP1 | IA18: CW | IB18: Yes | IC18: Monthly | ID18: 1.1 | IJ18: 11 | IK18: HO3 | IL18: CW | IM18: 1000000 | IN18: Annual | IO18: 200 | IQ18: 11 | IR18: HO5 | IS18: CW | IT18: 2000 | IU18: 5 | IW18: 11 | IX18: HO6 | IY18: ME | IZ18: 2 | JA18: 300 | JC18: 11 | JD18: Indiana | JE18: ALL | JF18: ALL | JG18: ALL | JH18: -0.05 | JJ18: 11 | JK18: Indiana | JL18: ALL | JM18: ALL | JN18: ALL | JO18: 0.06 | JP18: 0.03 | JQ18: 0.13 | JW18: 11 | JX18: Alabama | JY18: Chilton | KA18: 11 | KB18: FL69 | KC18: 0.92 | KE18: 11 | KF18: ALL | KG18: AZ | KH18: 100 | KJ18: 11 | KK18: HO3 | KL18: Bank Vault Jewelry | KM18: 0.01 | NG18: Conecuh | NK18: Crittenden | NM18: Dolores | NS18: Franklin | NU18: Butts | NW18: Clearwater | NY18: Cumberland | OA18: Delaware | OC18: Cherokee | OE18: Cowley | OG18: East Carroll | OK18: Queen Anne's | OO18: Clare | OQ18: Crow Wing | OS18: Forrest | OU18: Carter | PA18: Somerset | PC18: McKinley | PE18: Fulton | PG18: Catawba | PI18: Cuyahoga | PK18: Klamath | PO18: Dorchester | PQ18: Cumberland | PS18: Bosque | PU18: Salt Lake | PW18: Lexington (City) | PY18: Kitsap | QA18: Eau Claire | QH18: Kansas | QI18: KS | QJ18: 100 | QK18: 200 | QU18: DE1 | QV18: 2.5 | QW18: Massachusetts | QX18: Conecuh | QZ18: Crittenden | RA18: Dolores | RD18: Flagler | RE18: Butts | RF18: Clearwater | RG18: Cumberland | RH18: Delaware | RI18: Cherokee | RJ18: Cowley | RK18: East Carroll | RM18: Queen Anne's | RO18: Clare | RP18: Crow Wing | RQ18: Forrest | RR18: Carter | RU18: Somerset | RV18: McKinley | RW18: Fulton | RX18: Catawba | RY18: Cuyahoga | RZ18: Klamath | SB18: Dorchester | SC18: Cumberland | SD18: Bosque | SE18: Salt Lake | SF18: Buena Vista (City) | SG18: Kitsap | SI18: Eau Claire | SJ18: Virginia | SN18: FRANKLIN | SP18: ST. MARY | SX18: NEW HANOVER | TA18: LIBERTY
A19: 12 | B19: VDP1 | C19: ALL | D19: ALL | E19: 1.48 | G19: 12 | H19: HO3 | I19: CT | J19: CT1 | K19: Annual | L19: 0.21 | N19: 12 | O19: HO6 | P19: CW | Q19: 100000 | R19: 109999 | S19: 100000 | T19: 1.15 | U19: 110000 | V19: 1.19 | X19: 12 | Y19: HO6 | Z19: FL | AA19: 1 | AB19: 0.3 | AD19: 12 | AE19: ALL | AF19: Champaign | AG19: Ohio | AH19: OH1 | AJ19: 12 | AK19: HO5 | AL19: CW | AM19: Reinforced Concrete | AN19: Annual | AO19: 0.8 | AQ19: 12 | AR19: HO5 | AS19: CW | AT19: Primary | AU19: Annual | AV19: 1 | AX19: 12 | AY19: HO6 | AZ19: CW | BA19: 19 | BB19: 19 | BC19: Annual | BD19: 1.04 | BF19: 12 | BG19: HO5 | BH19: CW | BI19: 0 | BJ19: 10 | BK19: 0 | BL19: 10 | BM19: Annual | BN19: 1 | BP19: 12 | BQ19: HO6 | BR19: CW | BS19: NO | BT19: Reinforced Concrete | BU19: 8 | BV19: 14 | BW19: Annual | BX19: 0.85 | BZ19: 12 | CA19: HO8 | CB19: CW | CC19: 1 | CD19: Annual | CE19: 1 | CG19: 12 | CH19: Builders Risk DP3 | CI19: CW | CJ19: 350000 | CK19: 499999 | CL19: Monthly | CM19: 0.95 | CS19: 12 | CT19: HO5 | CU19: CW | CV19: 3 | CW19: Annual | CX19: 1.3 | CZ19: 12 | DA19: HO5 | DB19: CW | DC19: 2 | DD19: Annual | DE19: 1 | DG19: 12 | DH19: HO5 | DI19: CW | DJ19: CentralStationFireAlarm | DK19: Annual | DL19: 0.95 | DN19: 12 | DO19: DP3 | DP19: NEW_BUSINESS | DQ19: FL | DR19: ALL | DS19: 33004 | DT19: 10000 | DU19: Annual | DV19: 1 | DX19: 12 | DY19: HO5 | DZ19: CW | EA19: 2500 | EB19: 0 | EC19: Annual | ED19: 0.925 | EF19: 12 | EG19: HO6 | EH19: CW | EI19: 5000 | EJ19: 5000 | EK19: 0.95 | EM19: 12 | EN19: HO3 | EO19: CW | EP19: 3 | EQ19: -1 | ER19: -1 | ES19: Annual | ET19: 1.42 | EV19: 12 | EW19: HO3 | EX19: AL | EY19: 5 | EZ19: 1995 | FA19: 2999 | FB19: Y | FC19: Annual | FD19: 10 | FF19: 12 | FG19: HO3 | FH19: AK | FI19: 1 | FJ19: 2500 | FK19: Annual | FL19: 0.3 | FN19: 12 | FO19: HO5 | FP19: CW | FQ19: 15000 | FR19: Annual | FS19: 50 | FU19: 12 | FV19: HO5 | FW19: CW | FX19: 25000 | FY19: Annual | FZ19: 100 | GH19: 12 | GI19: HO6 | GJ19: CW | GK19: 21000 | GL19: 80 | GT19: 12 | GU19: HO5 | GV19: SC | GW19: Yes | GX19: Reinforced Concrete | GY19: Annual | GZ19: 0.15 | HB19: 12 | HC19: HO5 | HD19: SC | HE19: Yes | HF19: 15 | HG19: Annual | HH19: 0.8 | HJ19: 12 | HK19: HO6 | HL19: SC | HM19: 5 | HN19: Yes | HO19: Masonry | HP19: 0.05 | HR19: 12 | HS19: Builders Risk DP3 | HT19: CW | HU19: 0 | HV19: Monthly | HW19: 0 | HY19: 12 | HZ19: VDP3 | IA19: CW | IB19: No | IC19: Monthly | ID19: 0 | IJ19: 12 | IK19: HO5 | IL19: CW | IM19: 1000000 | IN19: Annual | IO19: 200 | IQ19: 12 | IR19: HO5 | IS19: CW | IT19: 3000 | IU19: 10 | IW19: 12 | IX19: HO6 | IY19: ME | IZ19: 3 | JA19: 300 | JC19: 12 | JD19: Iowa | JE19: ALL | JF19: ALL | JG19: ALL | JH19: -0.05 | JJ19: 12 | JK19: Iowa | JL19: ALL | JM19: ALL | JN19: ALL | JO19: 0.025 | JP19: -0.025 | JQ19: 0.07 | JW19: 12 | JX19: Alabama | JY19: Choctaw | KA19: 12 | KB19: GA6 | KC19: 0.45 | KE19: 12 | KF19: ALL | KG19: TX | KH19: 100 | KJ19: 12 | KK19: HO5 | KL19: Bank Vault Jewelry | KM19: 0.01 | NG19: Coosa | NK19: Cross | NM19: Douglas | NS19: Gadsden | NU19: Calhoun | NW19: Custer | NY19: DeKalb | OA19: Dubois | OC19: Chickasaw | OE19: Crawford | OG19: East Feliciana | OK19: Saint Mary's | OO19: Clinton | OQ19: Dakota | OS19: Franklin | OU19: Cass | PA19: Sussex | PC19: Mora | PE19: Genesee | PG19: Chatham | PI19: Darke | PK19: Lake | PO19: Edgefield | PQ19: Davidson | PS19: Bowie | PU19: San Juan | PW19: Lynchburg (City) | PY19: Kittitas | QA19: Florence | QH19: Kentucky | QI19: KY | QJ19: 100 | QK19: 200 | QU19: DE2 | QV19: 2.5 | QW19: Michigan | QX19: Coosa | QZ19: Cross | RA19: Douglas | RD19: Franklin | RE19: Calhoun | RF19: Custer | RG19: De Witt | RH19: Dubois | RI19: Chickasaw | RJ19: Crawford | RK19: East Feliciana | RM19: Saint Mary's | RO19: Clinton | RP19: Dakota | RQ19: Franklin | RR19: Cass | RU19: Sussex | RV19: Mora | RW19: Genesee | RX19: Chatham | RY19: Darke | RZ19: Lake | SB19: Edgefield | SC19: Davidson | SD19: Bowie | SE19: San Juan | SF19: CHESAPEAKE CITY | SG19: Kittitas | SI19: Florence | SJ19: Washington_DC | SN19: GADSDEN | SP19: ST. TAMMANY | SX19: ONSLOW | TA19: LIVE OAK
A20: 13 | B20: VDP3 | C20: ALL | D20: ALL | E20: 1.58 | G20: 13 | H20: HO3 | I20: CT | J20: CT2 | K20: Annual | L20: 0.315 | N20: 13 | O20: HO6 | P20: CW | Q20: 110000 | R20: 119999 | S20: 110000 | T20: 1.19 | U20: 120000 | V20: 1.23 | X20: 13 | Y20: HO6 | Z20: FL | AA20: 2 | AB20: 0.2 | AD20: 13 | AE20: ALL | AF20: Darke | AG20: Ohio | AH20: OH1 | AJ20: 13 | AK20: HO8 | AL20: CW | AM20: Reinforced Concrete | AN20: Annual | AO20: 0.8 | AQ20: 13 | AR20: HO8 | AS20: CW | AT20: Primary | AU20: Annual | AV20: 1 | AX20: 13 | AY20: HO6 | AZ20: CW | BA20: 2 | BB20: 2 | BC20: Annual | BD20: 0.82 | BF20: 13 | BG20: HO8 | BH20: CW | BI20: 0 | BJ20: 10 | BK20: 0 | BL20: 10 | BM20: Annual | BN20: 1 | BP20: 13 | BQ20: HO6 | BR20: CW | BS20: NO | BT20: Reinforced Concrete | BU20: 15 | BV20: 100 | BW20: Annual | BX20: 0.75 | BZ20: 13 | CA20: HO8 | CB20: CW | CC20: 2 | CD20: Annual | CE20: 1.1 | CG20: 13 | CH20: Builders Risk DP3 | CI20: CW | CJ20: 500000 | CK20: 1000000 | CL20: Monthly | CM20: 0.9 | CS20: 13 | CT20: HO8 | CU20: CW | CV20: 3 | CW20: Annual | CX20: 1.3 | CZ20: 13 | DA20: HO8 | DB20: CW | DC20: 2 | DD20: Annual | DE20: 1 | DG20: 13 | DH20: HO8 | DI20: CW | DJ20: CentralStationFireAlarm | DK20: Annual | DL20: 0.95 | DN20: 13 | DO20: DP3 | DP20: NEW_BUSINESS | DQ20: FL | DR20: ALL | DS20: 33013 | DT20: 10000 | DU20: Annual | DV20: 1 | DX20: 13 | DY20: HO8 | DZ20: CW | EA20: 2500 | EB20: 0 | EC20: Annual | ED20: 0.925 | EM20: 13 | EN20: HO3 | EO20: CW | EP20: 4 | EQ20: -1 | ER20: -1 | ES20: Annual | ET20: 1.42 | EV20: 13 | EW20: HO3 | EX20: AL | EY20: 6 | EZ20: 0 | FA20: 1994 | FB20: N | FC20: Annual | FD20: 0 | FF20: 13 | FG20: HO3 | FH20: AK | FI20: 1 | FJ20: 1000 | FK20: Annual | FL20: 0.3 | FN20: 13 | FO20: HO8 | FP20: CW | FQ20: 15000 | FR20: Annual | FS20: 50 | FU20: 13 | FV20: HO8 | FW20: CW | FX20: 25000 | FY20: Annual | FZ20: 100 | GH20: 13 | GI20: HO6 | GJ20: CW | GK20: 22000 | GL20: 85 | GT20: 13 | GU20: HO8 | GV20: SC | GW20: Yes | GX20: Reinforced Concrete | GY20: Annual | GZ20: 0.15 | HB20: 13 | HC20: HO8 | HD20: SC | HE20: Yes | HF20: 15 | HG20: Annual | HH20: 0.8 | HJ20: 13 | HK20: HO6 | HL20: SC | HM20: 10 | HN20: Yes | HO20: Masonry | HP20: 0.04 | HR20: 13 | HS20: VDP1 | HT20: CW | HU20: 0 | HV20: Monthly | HW20: 0 | HY20: 13 | HZ20: VDP3 | IA20: CW | IB20: Yes | IC20: Monthly | ID20: 0 | IJ20: 13 | IK20: HO8 | IL20: CW | IM20: 1000000 | IN20: Annual | IO20: 200 | IQ20: 13 | IR20: HO5 | IS20: CW | IT20: 4000 | IU20: 15 | IW20: 13 | IX20: HO6 | IY20: ME | IZ20: 4 | JA20: 300 | JC20: 13 | JD20: Kansas | JE20: ALL | JF20: ALL | JG20: ALL | JH20: -0.05 | JJ20: 13 | JK20: Kansas | JL20: ALL | JM20: ALL | JN20: ALL | JO20: 0.03 | JP20: -0.02 | JQ20: 0.08 | JW20: 13 | JX20: Alabama | JY20: Clarke | KA20: 13 | KB20: GA14 | KC20: 0.45 | KE20: 13 | KF20: ALL | KG20: MS | KH20: 100 | KJ20: 13 | KK20: HO8 | KL20: Bank Vault Jewelry | KM20: 0.01 | NG20: Covington | NK20: Dallas | NM20: Eagle | NS20: Gilchrist | NU20: Camden | NW20: Elmore | NY20: De Witt | OA20: Elkhart | OC20: Clarke | OE20: Decatur | OG20: Evangeline | OK20: Somerset | OO20: Crawford | OQ20: Dodge | OS20: George | OU20: Cedar | PA20: Union | PC20: Otero | PE20: Greene | PG20: Cherokee | PI20: Defiance | PK20: Lane | PO20: Fairfield | PQ20: Decatur | PS20: Brazoria | PU20: Sanpete | PW20: Manassas (City) | PY20: Klickitat | QA20: Fond du Lac | QH20: Louisiana | QI20: LA | QJ20: 100 | QK20: 200 | QU20: DC1 | QV20: 2.5 | QW20: Minnesota | QX20: Covington | QZ20: Dallas | RA20: Eagle | RD20: Gadsden | RE20: Camden | RF20: Elmore | RG20: DeKalb | RH20: Elkhart | RI20: Clarke | RJ20: Decatur | RK20: Evangeline | RM20: Somerset | RO20: Crawford | RP20: Dodge | RQ20: George | RR20: Cedar | RU20: Union | RV20: Otero | RW20: Greene | RX20: Cherokee | RY20: Defiance | RZ20: Lane | SB20: Fairfield | SC20: DeKalb | SD20: Brazoria | SE20: Sanpete | SF20: Campbell | SG20: Klickitat | SI20: Fond du Lac | SN20: GILCHRIST | SP20: TANGIPAHOA | SX20: PAMLICO | TA20: MATAGORDA
G21: 14 | H21: HO3 | I21: DC | J21: DC1 | K21: Annual | L21: 0.42 | N21: 14 | O21: HO6 | P21: CW | Q21: 120000 | R21: 129999 | S21: 120000 | T21: 1.23 | U21: 130000 | V21: 1.27 | X21: 14 | Y21: HO6 | Z21: FL | AA21: 3 | AB21: 0.35 | AD21: 14 | AE21: ALL | AF21: Gallia | AG21: Ohio | AH21: OH1 | AJ21: 14 | AK21: DP1 | AL21: CW | AM21: Reinforced Concrete | AN21: Annual | AO21: 0.8 | AQ21: 14 | AR21: DP1 | AS21: CW | AT21: Primary | AU21: Annual | AV21: 1 | AX21: 14 | AY21: HO6 | AZ21: CW | BA21: 20 | BB21: 20 | BC21: Annual | BD21: 1.05 | BF21: 14 | BG21: DP1 | BH21: CW | BI21: 0 | BJ21: 10 | BK21: 0 | BL21: 10 | BM21: Annual | BN21: 1 | BP21: 14 | BQ21: HO6 | BR21: CW | BS21: NO | BT21: Superior | BU21: 1 | BV21: 3 | BW21: Annual | BX21: 1 | BZ21: 14 | CA21: HO8 | CB21: CW | CC21: 3 | CD21: Annual | CE21: 1.5 | CG21: 14 | CH21: Builders Risk DP3 | CI21: CW | CJ21: 1000001 | CK21: 9999999999 | CL21: Monthly | CM21: 0.85 | CS21: 14 | CT21: DP1 | CU21: CW | CV21: 3 | CW21: Annual | CX21: 1.3 | CZ21: 14 | DA21: DP1 | DB21: CW | DC21: 2 | DD21: Annual | DE21: 1 | DG21: 14 | DH21: DP1 | DI21: CW | DJ21: CentralStationFireAlarm | DK21: Annual | DL21: 0.95 | DN21: 14 | DO21: DP3 | DP21: NEW_BUSINESS | DQ21: FL | DR21: ALL | DS21: 33014 | DT21: 10000 | DU21: Annual | DV21: 1 | DX21: 14 | DY21: DP1 | DZ21: CW | EA21: 2500 | EB21: 0 | EC21: Annual | ED21: 0.925 | EM21: 14 | EN21: HO3 | EO21: CW | EP21: 5 | EQ21: -1 | ER21: -1 | ES21: Annual | ET21: 1.43 | EV21: 14 | EW21: HO3 | EX21: AL | EY21: 6 | EZ21: 1995 | FA21: 2999 | FB21: N | FC21: Annual | FD21: 0 | FF21: 14 | FG21: HO3 | FH21: AL | FI21: 1 | FJ21: 0 | FK21: Annual | FL21: 1.02 | FN21: 14 | FO21: DP1 | FP21: CW | FQ21: 15000 | FR21: Annual | FS21: 50 | FU21: 14 | FV21: DP1 | FW21: CW | FX21: 25000 | FY21: Annual | FZ21: 100 | GH21: 14 | GI21: HO6 | GJ21: CW | GK21: 23000 | GL21: 90 | GT21: 14 | GU21: DP1 | GV21: SC | GW21: Yes | GX21: Reinforced Concrete | GY21: Annual | GZ21: 0.15 | HB21: 14 | HC21: DP1 | HD21: SC | HE21: Yes | HF21: 15 | HG21: Annual | HH21: 0.8 | HJ21: 14 | HK21: HO6 | HL21: SC | HM21: 15 | HN21: Yes | HO21: Masonry | HP21: 0.03 | HR21: 14 | HS21: VDP3 | HT21: CW | HU21: 0 | HV21: Monthly | HW21: 0 | HY21: 14 | HZ21: Builders Risk | IA21: CW | IB21: No | IC21: Monthly | ID21: 1 | IJ21: 14 | IK21: DP1 | IL21: CW | IM21: 1000000 | IN21: Annual | IO21: 200 | IQ21: 14 | IR21: HO5 | IS21: CW | IT21: 5000 | IU21: 20 | IW21: 14 | IX21: HO6 | IY21: ME | IZ21: 5 | JA21: 300 | JC21: 14 | JD21: Louisiana | JE21: ALL | JF21: ALL | JG21: ALL | JH21: -0.05 | JJ21: 14 | JK21: Louisiana | JL21: ALL | JM21: ALL | JN21: ALL | JO21: 0.02 | JP21: -0.03 | JQ21: 0.06 | JW21: 14 | JX21: Alabama | JY21: Clay | KA21: 14 | KB21: ME8 | KC21: 0.3 | KE21: 14 | KF21: ALL | KG21: DE | KH21: 100 | KJ21: 14 | KK21: DP1 | KL21: Bank Vault Jewelry | KM21: 0.01 | NG21: Crenshaw | NK21: Desha | NM21: Elbert | NS21: Glades | NU21: Candler | NW21: Franklin | NY21: Douglas | OA21: Fayette | OC21: Clay | OE21: Dickinson | OG21: Franklin | OK21: Talbot | OO21: Delta | OQ21: Douglas | OS21: Greene | OU21: Chariton | PA21: Warren | PC21: Quay | PE21: Hamilton | PG21: Chowan | PI21: Delaware | PK21: Lincoln | PO21: Florence | PQ21: DeKalb | PS21: Brazos | PU21: Sevier | PW21: Manassas Park (City) | PY21: Lewis | QA21: Forest | QH21: Maine | QI21: ME | QJ21: 100 | QK21: 200 | QU21: FL1 | QV21: 4 | QW21: Mississippi | QX21: Crenshaw | QZ21: Desha | RA21: El Paso | RD21: Gilchrist | RE21: Candler | RF21: Franklin | RG21: Douglas | RH21: Fayette | RI21: Clay | RJ21: Dickinson | RK21: Franklin | RM21: Talbot | RO21: Delta | RP21: Douglas | RQ21: Greene | RR21: Chariton | RU21: Warren | RV21: Quay | RW21: Hamilton | RX21: Chowan | RY21: Delaware | RZ21: Lincoln | SB21: Florence | SC21: Decatur | SD21: Brazos | SE21: Sevier | SF21: Caroline | SG21: Lewis | SI21: Forest | SN21: GLADES | SP21: TERREBONNE | SX21: PASQUOTANK | TA21: NUECES
G22: 15 | H22: HO3 | I22: DE | J22: DE1 | K22: Annual | L22: 0.22 | N22: 15 | O22: HO6 | P22: CW | Q22: 130000 | R22: 139999 | S22: 130000 | T22: 1.27 | U22: 140000 | V22: 1.31 | X22: 15 | Y22: HO6 | Z22: FL | AA22: 4 | AB22: 0.25 | AD22: 15 | AE22: ALL | AF22: Henry | AG22: Ohio | AH22: OH1 | AJ22: 15 | AK22: DP3 | AL22: CW | AM22: Reinforced Concrete | AN22: Annual | AO22: 0.8 | AQ22: 15 | AR22: DP3 | AS22: CW | AT22: Primary | AU22: Annual | AV22: 1 | AX22: 15 | AY22: HO6 | AZ22: CW | BA22: 21 | BB22: 21 | BC22: Annual | BD22: 1.07 | BF22: 15 | BG22: DP3 | BH22: CW | BI22: 0 | BJ22: 10 | BK22: 0 | BL22: 10 | BM22: Annual | BN22: 1 | BP22: 15 | BQ22: HO6 | BR22: CW | BS22: NO | BT22: Superior | BU22: 4 | BV22: 7 | BW22: Annual | BX22: 1 | BZ22: 15 | CA22: HO8 | CB22: CW | CC22: 4 | CD22: Annual | CE22: 2 | CG22: 15 | CH22: DP1 | CI22: CW | CJ22: 0 | CK22: 99999 | CL22: Annual | CM22: 2 | CS22: 15 | CT22: DP3 | CU22: CW | CV22: 3 | CW22: Annual | CX22: 1.3 | CZ22: 15 | DA22: DP3 | DB22: CW | DC22: 2 | DD22: Annual | DE22: 1 | DG22: 15 | DH22: DP3 | DI22: CW | DJ22: CentralStationFireAlarm | DK22: Annual | DL22: 0.95 | DN22: 15 | DO22: DP3 | DP22: NEW_BUSINESS | DQ22: FL | DR22: ALL | DS22: 33015 | DT22: 10000 | DU22: Annual | DV22: 1 | DX22: 15 | DY22: DP3 | DZ22: CW | EA22: 2500 | EB22: 0 | EC22: Annual | ED22: 0.925 | EM22: 15 | EN22: HO3 | EO22: CW | EP22: 6 | EQ22: 835 | ER22: 997 | ES22: Annual | ET22: 0.75 | EV22: 15 | EW22: HO3 | EX22: AR | EY22: 1 | EZ22: 0 | FA22: 1994 | FB22: N | FC22: Annual | FD22: 0 | FF22: 15 | FG22: HO3 | FH22: AL | FI22: 1 | FJ22: 1000 | FK22: Annual | FL22: 1.02 | FN22: 15 | FO22: DP3 | FP22: CW | FQ22: 15000 | FR22: Annual | FS22: 50 | FU22: 15 | FV22: DP3 | FW22: CW | FX22: 25000 | FY22: Annual | FZ22: 100 | GH22: 15 | GI22: HO6 | GJ22: CW | GK22: 24000 | GL22: 95 | GT22: 15 | GU22: DP3 | GV22: SC | GW22: Yes | GX22: Reinforced Concrete | GY22: Annual | GZ22: 0.15 | HB22: 15 | HC22: DP3 | HD22: SC | HE22: Yes | HF22: 15 | HG22: Annual | HH22: 0.8 | HJ22: 15 | HK22: HO6 | HL22: SC | HM22: 25 | HN22: Yes | HO22: Masonry | HP22: 0.02 | HR22: 15 | HS22: Builders Risk | HT22: CW | HU22: 5000 | HV22: Monthly | HW22: 12.5 | HY22: 15 | HZ22: Builders Risk DP3 | IA22: CW | IB22: No | IC22: Monthly | ID22: 1 | IJ22: 15 | IK22: DP3 | IL22: CW | IM22: 1000000 | IN22: Annual | IO22: 200 | IQ22: 15 | IR22: HO8 | IS22: CW | IT22: 0 | IU22: 0 | IW22: 15 | IX22: HO6 | IY22: ME | IZ22: 6 | JA22: 300 | JC22: 15 | JD22: Maine | JE22: ALL | JF22: ALL | JG22: ALL | JH22: -0.05 | JJ22: 15 | JK22: Maine | JL22: ALL | JM22: ALL | JN22: ALL | JO22: 0.06 | JP22: 0.025 | JQ22: 0.125 | JW22: 15 | JX22: Alabama | JY22: Cleburne | KA22: 15 | KB22: MD1 | KC22: 0.4 | KE22: 15 | KF22: ALL | KG22: RI | KH22: 100 | KJ22: 15 | KK22: DP3 | KL22: Bank Vault Jewelry | KM22: 0.01 | NG22: Cullman | NK22: Drew | NM22: El Paso | NS22: Gulf | NU22: Carroll | NW22: Fremont | NY22: DuPage | OA22: Floyd | OC22: Clayton | OE22: Doniphan | OG22: Grant | OK22: Washington | OO22: Dickinson | OQ22: Faribault | OS22: Grenada | OU22: Christian | PC22: Rio Arriba | PE22: Herkimer | PG22: Clay | PI22: Erie | PK22: Linn | PO22: Georgetown | PQ22: Dickson | PS22: Brewster | PU22: Summit | PW22: Martinsville (City) | PY22: Lincoln | QA22: Grant | QH22: Maryland | QI22: MD | QJ22: 100 | QK22: 100 | QU22: FL2 | QV22: 4 | QW22: Missouri | QX22: Cullman | QZ22: Drew | RA22: Elbert | RD22: Glades | RE22: Carroll | RF22: Fremont | RG22: DuPage | RH22: Floyd | RI22: Clayton | RJ22: Doniphan | RK22: Grant | RM22: Washington | RO22: Dickinson | RP22: Faribault | RQ22: Grenada | RR22: Christian | RV22: Rio Arriba | RW22: Herkimer | RX22: Clay | RY22: Erie | RZ22: Linn | SB22: Georgetown | SC22: Dickson | SD22: Brewster | SE22: Summit | SF22: Carroll | SG22: Lincoln | SI22: Grant | SN22: GULF | SP22: VERMILLION | SX22: PENDER | TA22: ORANGE
G23: 16 | H23: HO3 | I23: DE | J23: DE2 | K23: Annual | L23: 0.31 | N23: 16 | O23: HO6 | P23: CW | Q23: 140000 | R23: 149999 | S23: 140000 | T23: 1.31 | U23: 150000 | V23: 1.35 | X23: 16 | Y23: HO6 | Z23: FL | AA23: 5 | AB23: 0.3 | AD23: 16 | AE23: ALL | AF23: Lake | AG23: Ohio | AH23: OH1 | AJ23: 16 | AK23: HO3 | AL23: CW | AM23: Steel | AN23: Annual | AO23: 0.9 | AQ23: 16 | AR23: HO3 | AS23: CW | AT23: Secondary/Seasonal | AU23: Annual | AV23: 1.05 | AX23: 16 | AY23: HO6 | AZ23: CW | BA23: 22 | BB23: 22 | BC23: Annual | BD23: 1.08 | BF23: 16 | BG23: HO3 | BH23: CW | BI23: 11 | BJ23: 999 | BK23: 0 | BL23: 5 | BM23: Annual | BN23: 0.95 | BP23: 16 | BQ23: HO6 | BR23: CW | BS23: NO | BT23: Superior | BU23: 8 | BV23: 14 | BW23: Annual | BX23: 0.85 | BZ23: 16 | CA23: DP1 | CB23: CW | CC23: 0 | CD23: Annual | CE23: 0.98 | CG23: 16 | CH23: DP1 | CI23: CW | CJ23: 100000 | CK23: 149999 | CL23: Annual | CM23: 1.35 | CS23: 16 | CT23: HO3 | CU23: CW | CV23: 4 | CW23: Annual | CX23: 1.3 | CZ23: 16 | DA23: HO3 | DB23: CW | DC23: 3 | DD23: Annual | DE23: 1 | DG23: 16 | DH23: HO3 | DI23: CW | DJ23: CentralStationBurglar&Firealarm | DK23: Annual | DL23: 0.9 | DN23: 16 | DO23: HO3 | DP23: NEW_BUSINESS | DQ23: FL | DR23: ALL | DS23: 33017 | DT23: 10000 | DU23: Annual | DV23: 1 | DX23: 16 | DY23: HO3 | DZ23: CW | EA23: 25000 | EC23: Annual | ED23: 0.85 | EM23: 16 | EN23: HO3 | EO23: CW | EP23: 6 | EQ23: 799 | ER23: 834 | ES23: Annual | ET23: 0.8 | EV23: 16 | EW23: HO3 | EX23: AR | EY23: 1 | EZ23: 1995 | FA23: 2999 | FB23: N | FC23: Annual | FD23: 0 | FF23: 16 | FG23: HO3 | FH23: AL | FI23: 1 | FJ23: 2500 | FK23: Annual | FL23: 0.95 | FN23: 16 | FO23: Builders Risk | FP23: CW | FQ23: 5000 | FR23: Monthly | FS23: 0 | FU23: 16 | FV23: HO3 | FW23: CW | FX23: 5000 | FY23: Annual | FZ23: 25 | GH23: 16 | GI23: HO6 | GJ23: CW | GK23: 25000 | GL23: 100 | GT23: 16 | GU23: HO3 | GV23: SC | GW23: Yes | GX23: Steel | GY23: Annual | GZ23: 0.15 | HB23: 16 | HC23: HO3 | HD23: SC | HE23: Yes | HF23: 25 | HG23: Annual | HH23: 0.75 | HR23: 16 | HS23: Builders Risk DP3 | HT23: CW | HU23: 5000 | HV23: Monthly | HW23: 12.5 | HY23: 16 | HZ23: VDP1 | IA23: CW | IB23: No | IC23: Monthly | ID23: 1 | IJ23: 16 | IK23: HO3 | IL23: CW | IM23: 300000 | IN23: Annual | IO23: 50 | IQ23: 16 | IR23: HO8 | IS23: CW | IT23: 1000 | IU23: 0 | IW23: 16 | IX23: HO6 | IY23: ME | IZ23: 7 | JA23: 300 | JC23: 16 | JD23: Maryland | JE23: ALL | JF23: ALL | JG23: ALL | JH23: -0.05 | JJ23: 16 | JK23: Maryland | JL23: ALL | JM23: ALL | JN23: ALL | JO23: 0.03 | JP23: -0.025 | JQ23: 0.08 | JW23: 16 | JX23: Alabama | JY23: Coffee | KA23: 16 | KB23: MA4 | KC23: 0.3 | KE23: 16 | KF23: ALL | KG23: ME | KH23: 100 | KJ23: 16 | KK23: HO3 | KL23: Furs | KM23: 0.015 | NG23: Dale | NK23: Faulkner | NM23: Fremont | NS23: Hamilton | NU23: Catoosa | NW23: Gem | NY23: Edgar | OA23: Fountain | OC23: Clinton | OE23: Douglas | OG23: Iberia | OK23: Wicomico | OO23: Eaton | OQ23: Fillmore | OS23: Hancock | OU23: Clark | PC23: Roosevelt | PE23: Jefferson | PG23: Cleveland | PI23: Fairfield | PK23: Malheur | PO23: Greenville | PQ23: Dyer | PS23: Briscoe | PU23: Tooele | PW23: Newport News (City) | PY23: Mason | QA23: Green | QH23: Massachusetts | QI23: MA | QJ23: 100 | QK23: 200 | QU23: FL3 | QV23: 4 | QW23: Nevada | QX23: Dale | QZ23: Faulkner | RA23: Fremont | RD23: Gulf | RE23: Catoosa | RF23: Gem | RG23: Edgar | RH23: Fountain | RI23: Clinton | RJ23: Douglas | RK23: Iberia | RM23: Wicomico | RO23: Eaton | RP23: Fillmore | RQ23: Hancock | RR23: Clark | RV23: Roosevelt | RW23: Jefferson | RX23: Cleveland | RY23: Fairfield | RZ23: Malheur | SB23: Greenville | SC23: Dyer | SD23: Briscoe | SE23: Tooele | SF23: Charles City | SG23: Mason | SI23: Green | SN23: HAMILTON | SP23: WASHINGTON | SX23: PERQUIMANS | TA23: REFUGIO
G24: 17 | H24: HO3 | I24: DE | J24: DE3 | K24: Annual | L24: 0.3675 | N24: 17 | O24: HO6 | P24: CW | Q24: 150000 | R24: 159999 | S24: 150000 | T24: 1.35 | U24: 160000 | V24: 1.38 | X24: 17 | Y24: HO6 | Z24: FL | AA24: 6 | AB24: 0.2 | AD24: 17 | AE24: ALL | AF24: Marion | AG24: Ohio | AH24: OH1 | AJ24: 17 | AK24: HO5 | AL24: CW | AM24: Steel | AN24: Annual | AO24: 0.9 | AQ24: 17 | AR24: HO5 | AS24: CW | AT24: Secondary/Seasonal | AU24: Annual | AV24: 1.05 | AX24: 17 | AY24: HO6 | AZ24: CW | BA24: 23 | BB24: 23 | BC24: Annual | BD24: 1.09 | BF24: 17 | BG24: HO5 | BH24: CW | BI24: 11 | BJ24: 999 | BK24: 0 | BL24: 5 | BM24: Annual | BN24: 0.95 | BP24: 17 | BQ24: HO6 | BR24: CW | BS24: NO | BT24: Superior | BU24: 15 | BV24: 100 | BW24: Annual | BX24: 0.75 | BZ24: 17 | CA24: DP1 | CB24: CW | CC24: 1 | CD24: Annual | CE24: 1 | CG24: 17 | CH24: DP1 | CI24: CW | CJ24: 150000 | CK24: 249999 | CL24: Annual | CM24: 1.2 | CS24: 17 | CT24: HO5 | CU24: CW | CV24: 4 | CW24: Annual | CX24: 1.3 | CZ24: 17 | DA24: HO5 | DB24: CW | DC24: 3 | DD24: Annual | DE24: 1 | DG24: 17 | DH24: HO5 | DI24: CW | DJ24: CentralStationBurglar&Firealarm | DK24: Annual | DL24: 0.9 | DN24: 17 | DO24: HO3 | DP24: NEW_BUSINESS | DQ24: FL | DR24: ALL | DS24: 33019 | DT24: 10000 | DU24: Annual | DV24: 1 | DX24: 17 | DY24: HO5 | DZ24: CW | EA24: 25000 | EC24: Annual | ED24: 0.85 | EM24: 17 | EN24: HO3 | EO24: CW | EP24: 6 | EQ24: 769 | ER24: 798 | ES24: Annual | ET24: 0.85 | EV24: 17 | EW24: HO3 | EX24: AZ | EY24: 1 | EZ24: 0 | FA24: 1994 | FB24: N | FC24: Annual | FD24: 0 | FF24: 17 | FG24: HO3 | FH24: AL | FI24: 1 | FJ24: 5000 | FK24: Annual | FL24: 0.84 | FN24: 17 | FO24: Builders Risk DP3 | FP24: CW | FQ24: 5000 | FR24: Monthly | FS24: 0 | FU24: 17 | FV24: HO5 | FW24: CW | FX24: 5000 | FY24: Annual | FZ24: 25 | GH24: 17 | GI24: HO6 | GJ24: CW | GK24: 26000 | GL24: 105 | GT24: 17 | GU24: HO5 | GV24: SC | GW24: Yes | GX24: Steel | GY24: Annual | GZ24: 0.15 | HB24: 17 | HC24: HO5 | HD24: SC | HE24: Yes | HF24: 25 | HG24: Annual | HH24: 0.75 | HR24: 17 | HS24: VDP1 | HT24: CW | HU24: 5000 | HV24: Monthly | HW24: 12.5 | HY24: 17 | HZ24: VDP3 | IA24: CW | IB24: Yes | IC24: Monthly | ID24: 1 | IJ24: 17 | IK24: HO5 | IL24: CW | IM24: 300000 | IN24: Annual | IO24: 50 | IQ24: 17 | IR24: HO8 | IS24: CW | IT24: 10000 | IU24: 40 | IW24: 17 | IX24: HO6 | IY24: ME | IZ24: 8 | JA24: 300 | JC24: 17 | JD24: Massachusetts | JE24: ALL | JF24: ALL | JG24: ALL | JH24: -0.05 | JJ24: 17 | JK24: Massachusetts | JL24: ALL | JM24: ALL | JN24: ALL | JO24: 0.035 | JP24: -0.02 | JQ24: 0.085 | JW24: 17 | JX24: Alabama | JY24: Colbert | KA24: 17 | KB24: NH2 | KC24: 0.3 | KE24: 17 | KF24: ALL | KG24: CO | KH24: 100 | KJ24: 17 | KK24: HO5 | KL24: Furs | KM24: 0.015 | NG24: Dallas | NK24: Franklin | NM24: Garfield | NS24: Hardee | NU24: Charlton | NW24: Gooding | NY24: Edwards | OA24: Franklin | OC24: Crawford | OE24: Edwards | OG24: Iberville | OK24: Worcester | OO24: Emmet | OQ24: Freeborn | OS24: Harrison | OU24: Clay | PC24: Sandoval | PE24: Kings | PG24: Columbus | PI24: Fayette | PK24: Marion | PO24: Greenwood | PQ24: Fayette | PS24: Brooks | PU24: Uintah | PW24: Norfolk (City) | PY24: Okanogan | QA24: Green Lake | QH24: Michigan | QI24: MI | QJ24: 59 | QK24: 59 | QU24: FL4 | QV24: 4 | QW24: New_Hampshire | QX24: Dallas | QZ24: Franklin | RA24: Garfield | RD24: Hamilton | RE24: Charlton | RF24: Gooding | RG24: Edwards | RH24: Franklin | RI24: Crawford | RJ24: Edwards | RK24: Iberville | RM24: Worcester | RO24: Emmet | RP24: Freeborn | RQ24: Harrison | RR24: Clay | RV24: San Juan | RW24: Kings | RX24: Columbus | RY24: Fayette | RZ24: Marion | SB24: Greenwood | SC24: Fayette | SD24: Brooks | SE24: Uintah | SF24: Charlotte | SG24: Okanogan | SI24: Green Lake | SN24: HARDEE | SX24: SAMPSON | TA24: SAN PATRICIO
G25: 18 | H25: HO3 | I25: FL | J25: FL1 | K25: Annual | L25: 0.25 | N25: 18 | O25: HO6 | P25: CW | Q25: 160000 | R25: 169999 | S25: 160000 | T25: 1.38 | U25: 170000 | V25: 1.41 | X25: 18 | Y25: HO6 | Z25: FL | AA25: 7 | AB25: 0.25 | AD25: 18 | AE25: ALL | AF25: Morrow | AG25: Ohio | AH25: OH1 | AJ25: 18 | AK25: HO8 | AL25: CW | AM25: Steel | AN25: Annual | AO25: 0.9 | AQ25: 18 | AR25: HO8 | AS25: CW | AT25: Secondary/Seasonal | AU25: Annual | AV25: 1.05 | AX25: 18 | AY25: HO6 | AZ25: CW | BA25: 24 | BB25: 24 | BC25: Annual | BD25: 1.1 | BF25: 18 | BG25: HO8 | BH25: CW | BI25: 11 | BJ25: 999 | BK25: 0 | BL25: 5 | BM25: Annual | BN25: 0.95 | BP25: 18 | BQ25: HO6 | BR25: CW | BS25: NO | BT25: Log Home | BU25: 0 | BV25: 1 | BW25: Annual | BX25: 1 | BZ25: 18 | CA25: DP1 | CB25: CW | CC25: 2 | CD25: Annual | CE25: 1.1 | CG25: 18 | CH25: DP1 | CI25: CW | CJ25: 250000 | CK25: 349999 | CL25: Annual | CM25: 1 | CS25: 18 | CT25: HO8 | CU25: CW | CV25: 4 | CW25: Annual | CX25: 1.3 | CZ25: 18 | DA25: HO8 | DB25: CW | DC25: 3 | DD25: Annual | DE25: 1 | DG25: 18 | DH25: HO8 | DI25: CW | DJ25: CentralStationBurglar&Firealarm | DK25: Annual | DL25: 0.9 | DN25: 18 | DO25: HO3 | DP25: NEW_BUSINESS | DQ25: FL | DR25: ALL | DS25: 33024 | DT25: 10000 | DU25: Annual | DV25: 1 | DX25: 18 | DY25: HO8 | DZ25: CW | EA25: 25000 | EC25: Annual | ED25: 0.85 | EM25: 18 | EN25: HO3 | EO25: CW | EP25: 6 | EQ25: 741 | ER25: 768 | ES25: Annual | ET25: 0.9 | EV25: 18 | EW25: HO3 | EX25: AZ | EY25: 1 | EZ25: 1995 | FA25: 2999 | FB25: N | FC25: Annual | FD25: 0 | FF25: 18 | FG25: HO3 | FH25: AL | FI25: 1 | FJ25: 10000 | FK25: Annual | FL25: 0.7 | FN25: 18 | FO25: VDP1 | FP25: CW | FQ25: 5000 | FR25: Monthly | FS25: 0 | FU25: 18 | FV25: HO8 | FW25: CW | FX25: 5000 | FY25: Annual | FZ25: 25 | GH25: 18 | GI25: HO6 | GJ25: CW | GK25: 27000 | GL25: 110 | GT25: 18 | GU25: HO8 | GV25: SC | GW25: Yes | GX25: Steel | GY25: Annual | GZ25: 0.15 | HB25: 18 | HC25: HO8 | HD25: SC | HE25: Yes | HF25: 25 | HG25: Annual | HH25: 0.75 | HR25: 18 | HS25: VDP3 | HT25: CW | HU25: 5000 | HV25: Monthly | HW25: 12.5 | HY25: 18 | HZ25: VDP3 | IA25: CW | IB25: No | IC25: Monthly | ID25: 1 | IJ25: 18 | IK25: HO8 | IL25: CW | IM25: 300000 | IN25: Annual | IO25: 50 | IQ25: 18 | IR25: HO8 | IS25: CW | IT25: 2000 | IU25: 5 | IW25: 18 | IX25: HO6 | IY25: ME | IZ25: 9 | JA25: 300 | JC25: 18 | JD25: Michigan | JE25: ALL | JF25: ALL | JG25: ALL | JH25: -0.05 | JJ25: 18 | JK25: Michigan | JL25: ALL | JM25: ALL | JN25: ALL | JO25: 0.02 | JP25: -0.03 | JQ25: 0.055 | JW25: 18 | JX25: Alabama | JY25: Conecuh | KA25: 18 | KB25: NJ4 | KC25: 0.45 | KE25: 18 | KF25: ALL | KG25: OH | KH25: 100 | KJ25: 18 | KK25: HO8 | KL25: Furs | KM25: 0.015 | NG25: DeKalb | NK25: Fulton | NM25: Gilpin | NS25: Hendry | NU25: Chatham | NW25: Idaho | NY25: Effingham | OA25: Fulton | OC25: Dallas | OE25: Elk | OG25: Jackson | OO25: Genesee | OQ25: Goodhue | OS25: Hinds | OU25: Clinton | PC25: San Juan | PE25: Lewis | PG25: Craven | PI25: Franklin | PK25: Morrow | PO25: Hampton | PQ25: Fentress | PS25: Brown | PU25: Utah | PW25: Norton (City) | PY25: Pacific | QA25: Iowa | QH25: Minnesota | QI25: MN | QJ25: 100 | QK25: 200 | QU25: FL5 | QV25: 4 | QW25: New_Jersey | QX25: DeKalb | QZ25: Fulton | RA25: Gilpin | RD25: Hardee | RE25: Chatham | RF25: Idaho | RG25: Effingham | RH25: Fulton | RI25: Dallas | RJ25: Elk | RK25: JEFFERSON PARISH | RO25: Genesee | RP25: Goodhue | RQ25: Hinds | RR25: Clinton | RV25: San Miguel | RW25: Lewis | RX25: Craven | RY25: Franklin | RZ25: Morrow | SB25: Hampton | SC25: Fentress | SD25: Brown | SE25: Utah | SF25: Charlottesville (City) | SG25: Pacific | SI25: Iowa | SN25: HENDRY | SX25: TYRRELL | TA25: VICTORIA
G26: 19 | H26: HO3 | I26: FL | J26: FL10 | K26: Annual | L26: 0.25 | N26: 19 | O26: HO6 | P26: CW | Q26: 170000 | R26: 179999 | S26: 170000 | T26: 1.41 | U26: 180000 | V26: 1.44 | X26: 19 | Y26: HO6 | Z26: FL | AA26: 8 | AB26: 0.25 | AD26: 19 | AE26: ALL | AF26: Portage | AG26: Ohio | AH26: OH1 | AJ26: 19 | AK26: DP1 | AL26: CW | AM26: Steel | AN26: Annual | AO26: 0.9 | AQ26: 19 | AR26: DP1 | AS26: CW | AT26: Secondary/Seasonal | AU26: Annual | AV26: 1.05 | AX26: 19 | AY26: HO6 | AZ26: CW | BA26: 25 | BB26: 25 | BC26: Annual | BD26: 1.11 | BF26: 19 | BG26: DP1 | BH26: CW | BI26: 11 | BJ26: 999 | BK26: 0 | BL26: 5 | BM26: Annual | BN26: 0.95 | BP26: 19 | BQ26: HO6 | BR26: CW | BS26: NO | BT26: Log Home | BU26: 2 | BV26: 100 | BW26: Annual | BX26: 1.05 | BZ26: 19 | CA26: DP1 | CB26: CW | CC26: 3 | CD26: Annual | CE26: 1.5 | CG26: 19 | CH26: DP1 | CI26: CW | CJ26: 350000 | CK26: 499999 | CL26: Annual | CM26: 0.95 | CS26: 19 | CT26: DP1 | CU26: CW | CV26: 4 | CW26: Annual | CX26: 1.3 | CZ26: 19 | DA26: DP1 | DB26: CW | DC26: 3 | DD26: Annual | DE26: 1 | DG26: 19 | DH26: DP1 | DI26: CW | DJ26: CentralStationBurglar&Firealarm | DK26: Annual | DL26: 0.9 | DN26: 19 | DO26: HO3 | DP26: NEW_BUSINESS | DQ26: FL | DR26: ALL | DS26: 33025 | DT26: 10000 | DU26: Annual | DV26: 1 | DX26: 19 | DY26: DP1 | DZ26: CW | EA26: 25000 | EC26: Annual | ED26: 0.85 | EM26: 19 | EN26: HO3 | EO26: CW | EP26: 6 | EQ26: 0 | ER26: 548 | ES26: Annual | ET26: 4 | EV26: 19 | EW26: HO3 | EX26: CA | EY26: 1 | EZ26: 0 | FA26: 1994 | FB26: N | FC26: Annual | FD26: 0 | FF26: 19 | FG26: HO3 | FH26: AL | FI26: 1 | FJ26: 25000 | FK26: Annual | FL26: 0.67 | FN26: 19 | FO26: VDP3 | FP26: CW | FQ26: 5000 | FR26: Monthly | FS26: 0 | FU26: 19 | FV26: DP1 | FW26: CW | FX26: 5000 | FY26: Annual | FZ26: 25 | GH26: 19 | GI26: HO6 | GJ26: CW | GK26: 28000 | GL26: 115 | GT26: 19 | GU26: DP1 | GV26: SC | GW26: Yes | GX26: Steel | GY26: Annual | GZ26: 0.15 | HB26: 19 | HC26: DP1 | HD26: SC | HE26: Yes | HF26: 25 | HG26: Annual | HH26: 0.75 | IJ26: 19 | IK26: DP1 | IL26: CW | IM26: 300000 | IN26: Annual | IO26: 50 | IQ26: 19 | IR26: HO8 | IS26: CW | IT26: 3000 | IU26: 10 | IW26: 19 | IX26: HO6 | IY26: ME | IZ26: 10 | JA26: 300 | JC26: 19 | JD26: Minnesota | JE26: ALL | JF26: ALL | JG26: ALL | JH26: -0.05 | JJ26: 19 | JK26: Minnesota | JL26: ALL | JM26: ALL | JN26: ALL | JO26: 0.035 | JP26: -0.02 | JQ26: 0.085 | JW26: 19 | JX26: Alabama | JY26: Coosa | KA26: 19 | KB26: NJ12 | KC26: 0.4 | KE26: 19 | KF26: ALL | KG26: LA | KH26: 100 | KJ26: 19 | KK26: DP1 | KL26: Furs | KM26: 0.015 | NG26: Elmore | NK26: Garland | NM26: Grand | NS26: Hernando | NU26: Chattahoochee | NW26: Jefferson | NY26: Fayette | OA26: Gibson | OC26: Davis | OE26: Ellis | OG26: Jefferson | OO26: Gladwin | OQ26: Grant | OS26: Holmes | OU26: Cole | PC26: San Miguel | PE26: Livingston | PG26: Cumberland | PI26: Fulton | PK26: Multnomah | PO26: Horry | PQ26: Franklin | PS26: Burleson | PU26: Wasatch | PW26: Petersburg (City) | PY26: Pend Oreille | QA26: Iron | QH26: Mississippi | QI26: MS | QJ26: 100 | QK26: 200 | QU26: FL6 | QV26: 4 | QW26: New_Mexico | QX26: Elmore | QZ26: Garland | RA26: Grand | RD26: Hendry | RE26: Chattahoochee | RF26: Jefferson | RG26: Fayette | RH26: Gibson | RI26: Davis | RJ26: Ellis | RK26: Jackson | RO26: Gladwin | RP26: Grant | RQ26: Holmes | RR26: Cole | RV26: Sandoval | RW26: Livingston | RX26: Cumberland | RY26: Fulton | RZ26: Multnomah | SB26: Horry | SC26: Franklin | SD26: Burleson | SE26: Wasatch | SF26: Chesapeake (City) | SG26: Pend Oreille | SI26: Iron | SN26: HERNANDO | SX26: WASHINGTON | TA26: WHARTON
G27: 20 | H27: HO3 | I27: FL | J27: FL11 | K27: Annual | L27: 0.25 | N27: 20 | O27: HO6 | P27: CW | Q27: 180000 | R27: 189999 | S27: 180000 | T27: 1.44 | U27: 190000 | V27: 1.47 | X27: 20 | Y27: HO6 | Z27: FL | AA27: 9 | AB27: 0.25 | AD27: 20 | AE27: ALL | AF27: Shelby | AG27: Ohio | AH27: OH1 | AJ27: 20 | AK27: DP3 | AL27: CW | AM27: Steel | AN27: Annual | AO27: 0.9 | AQ27: 20 | AR27: DP3 | AS27: CW | AT27: Secondary/Seasonal | AU27: Annual | AV27: 1.05 | AX27: 20 | AY27: HO6 | AZ27: CW | BA27: 26 | BB27: 26 | BC27: Annual | BD27: 1.12 | BF27: 20 | BG27: DP3 | BH27: CW | BI27: 11 | BJ27: 999 | BK27: 0 | BL27: 5 | BM27: Annual | BN27: 0.95 | BP27: 20 | BQ27: HO6 | BR27: CW | BS27: NO | BT27: Adobe | BU27: 0 | BV27: 1 | BW27: Annual | BX27: 1 | BZ27: 20 | CA27: DP1 | CB27: CW | CC27: 4 | CD27: Annual | CE27: 2 | CG27: 20 | CH27: DP1 | CI27: CW | CJ27: 500000 | CK27: 1000000 | CL27: Annual | CM27: 0.9 | CS27: 20 | CT27: DP3 | CU27: CW | CV27: 4 | CW27: Annual | CX27: 1.3 | CZ27: 20 | DA27: DP3 | DB27: CW | DC27: 3 | DD27: Annual | DE27: 1 | DG27: 20 | DH27: DP3 | DI27: CW | DJ27: CentralStationBurglar&Firealarm | DK27: Annual | DL27: 0.9 | DN27: 20 | DO27: HO3 | DP27: NEW_BUSINESS | DQ27: FL | DR27: ALL | DS27: 33026 | DT27: 10000 | DU27: Annual | DV27: 1 | DX27: 20 | DY27: DP3 | DZ27: CW | EA27: 25000 | EC27: Annual | ED27: 0.85 | EM27: 20 | EN27: HO3 | EO27: CW | EP27: 6 | EQ27: 713 | ER27: 740 | ES27: Annual | ET27: 1 | EV27: 20 | EW27: HO3 | EX27: CA | EY27: 1 | EZ27: 1995 | FA27: 2999 | FB27: N | FC27: Annual | FD27: 0 | FF27: 20 | FG27: HO3 | FH27: AL | FI27: 1 | FJ27: 50000 | FK27: Annual | FL27: 0.63 | FN27: 20 | FO27: Builders Risk | FP27: CW | FQ27: 10000 | FR27: Monthly | FS27: 25 | FU27: 20 | FV27: DP3 | FW27: CW | FX27: 5000 | FY27: Annual | FZ27: 25 | GH27: 20 | GI27: HO6 | GJ27: CW | GK27: 29000 | GL27: 120 | GT27: 20 | GU27: DP3 | GV27: SC | GW27: Yes | GX27: Steel | GY27: Annual | GZ27: 0.15 | HB27: 20 | HC27: DP3 | HD27: SC | HE27: Yes | HF27: 25 | HG27: Annual | HH27: 0.75 | IJ27: 20 | IK27: DP3 | IL27: CW | IM27: 300000 | IN27: Annual | IO27: 50 | IQ27: 20 | IR27: HO8 | IS27: CW | IT27: 4000 | IU27: 15 | IW27: 20 | IX27: HO6 | IY27: ME | IZ27: 11 | JA27: 300 | JC27: 20 | JD27: Mississippi | JE27: ALL | JF27: ALL | JG27: ALL | JH27: -0.05 | JJ27: 20 | JK27: Mississippi | JL27: ALL | JM27: ALL | JN27: ALL | JO27: 0.05 | JP27: 0.02 | JQ27: 0.115 | JW27: 20 | JX27: Alabama | JY27: Covington | KA27: 20 | KB27: NY8 | KC27: 0.5 | KE27: 20 | KF27: ALL | KG27: WI | KH27: 100 | KJ27: 20 | KK27: DP3 | KL27: Furs | KM27: 0.015 | NG27: Escambia | NK27: Grant | NM27: Gunnison | NS27: Highlands | NU27: Chattooga | NW27: Jerome | NY27: Ford | OA27: Grant | OC27: Decatur | OE27: Ellsworth | OG27: Jefferson Davis | OO27: Gogebic | OQ27: Hennepin | OS27: Humphreys | OU27: Cooper | PC27: Santa Fe | PE27: Madison | PG27: Currituck | PI27: Gallia | PK27: Polk | PO27: Jasper | PQ27: Gibson | PS27: Burnet | PU27: Washington | PW27: Poquoson (City) | PY27: Pierce | QA27: Jackson | QH27: Missouri | QI27: MO | QJ27: 100 | QK27: 200 | QU27: FL7 | QV27: 4 | QW27: New_York | QX27: Escambia | QZ27: Grant | RA27: Gunnison | RD27: Hernando | RE27: Chattooga | RF27: Jerome | RG27: Ford | RH27: Grant | RI27: Decatur | RJ27: Ellsworth | RK27: Jefferson | RO27: Gogebic | RP27: Hennepin | RQ27: Humphreys | RR27: Cooper | RV27: Santa Fe | RW27: Madison | RX27: Currituck | RY27: Gallia | RZ27: Polk | SB27: Jasper | SC27: Gibson | SD27: Burnet | SE27: Washington | SF27: Chesterfield | SG27: Pierce | SI27: Jackson | SN27: HIGHLANDS | TA27: WILLACY
G28: 21 | H28: HO3 | I28: FL | J28: FL12 | K28: Annual | L28: 0.25 | N28: 21 | O28: HO6 | P28: CW | Q28: 190000 | R28: 199999 | S28: 190000 | T28: 1.47 | U28: 200000 | V28: 1.5 | X28: 21 | Y28: HO6 | Z28: FL | AA28: 10 | AB28: 0.25 | AD28: 21 | AE28: ALL | AF28: Warren | AG28: Ohio | AH28: OH1 | AJ28: 21 | AK28: HO3 | AL28: CW | AM28: Superior | AN28: Annual | AO28: 0.8 | AQ28: 21 | AR28: HO3 | AS28: CW | AT28: Short-Term Rental | AU28: Annual | AV28: 1.05 | AX28: 21 | AY28: HO6 | AZ28: CW | BA28: 27 | BB28: 27 | BC28: Annual | BD28: 1.13 | BF28: 21 | BG28: HO3 | BH28: CW | BI28: 11 | BJ28: 999 | BK28: 11 | BL28: 999 | BM28: Annual | BN28: 1 | BP28: 21 | BQ28: HO6 | BR28: CW | BS28: NO | BT28: Adobe | BU28: 2 | BV28: 100 | BW28: Annual | BX28: 1.05 | BZ28: 21 | CA28: DP3 | CB28: CW | CC28: 0 | CD28: Annual | CE28: 0.98 | CG28: 21 | CH28: DP1 | CI28: CW | CJ28: 1000001 | CK28: 9999999999 | CL28: Annual | CM28: 0.85 | CS28: 21 | CT28: HO3 | CU28: CW | CV28: 5 | CW28: Annual | CX28: 1.3 | CZ28: 21 | DA28: HO3 | DB28: CW | DC28: 4 | DD28: Annual | DE28: 1 | DG28: 21 | DH28: HO6 | DI28: CW | DJ28: None | DK28: Annual | DL28: 1 | DN28: 21 | DO28: HO3 | DP28: NEW_BUSINESS | DQ28: FL | DR28: ALL | DS28: 33028 | DT28: 10000 | DU28: Annual | DV28: 1 | DX28: 21 | DY28: HO3 | DZ28: CW | EA28: 500 | EC28: Annual | ED28: 1.1 | EM28: 21 | EN28: HO3 | EO28: CW | EP28: 6 | EQ28: 686 | ER28: 712 | ES28: Annual | ET28: 1.05 | EV28: 21 | EW28: HO3 | EX28: CO | EY28: 1 | EZ28: 0 | FA28: 1994 | FB28: N | FC28: Annual | FD28: 0 | FF28: 21 | FG28: HO3 | FH28: AL | FI28: 1 | FJ28: 80000 | FK28: Annual | FL28: 0.57 | FN28: 21 | FO28: Builders Risk DP3 | FP28: CW | FQ28: 10000 | FR28: Monthly | FS28: 25 | FU28: 21 | FV28: HO6 | FW28: CW | FX28: 0 | FY28: Annual | FZ28: 0 | GH28: 21 | GI28: HO6 | GJ28: CW | GK28: 30000 | GL28: 125 | GT28: 21 | GU28: HO3 | GV28: SC | GW28: Yes | GX28: Superior | GY28: Annual | GZ28: 0.15 | HB28: 21 | HC28: HO3 | HD28: SC | HE28: Yes | HF28: 5 | HG28: Annual | HH28: 1 | IJ28: 21 | IK28: HO3 | IL28: CW | IM28: 500000 | IN28: Annual | IO28: 100 | IQ28: 21 | IR28: HO8 | IS28: CW | IT28: 5000 | IU28: 20 | IW28: 21 | IX28: HO6 | IY28: ME | IZ28: 12 | JA28: 300 | JC28: 21 | JD28: Missouri | JE28: ALL | JF28: ALL | JG28: ALL | JH28: -0.05 | JJ28: 21 | JK28: Missouri | JL28: ALL | JM28: ALL | JN28: ALL | JO28: 0.025 | JP28: -0.025 | JQ28: 0.065 | JW28: 21 | JX28: Alabama | JY28: Crenshaw | KA28: 21 | KB28: NC6 | KC28: 0.4 | KE28: 21 | KF28: ALL | KG28: NM | KH28: 100 | KJ28: 21 | KK28: HO3 | KL28: Cameras | KM28: 0.01 | NG28: Etowah | NK28: Greene | NM28: Hinsdale | NS28: Hillsborough | NU28: Cherokee | NW28: Kootenai | NY28: Franklin | OA28: Greene | OC28: Delaware | OE28: Finney | OG28: Lafayette | OO28: Grand Traverse | OQ28: Houston | OS28: Issaquena | OU28: Crawford | PC28: Sierra | PE28: Monroe | PG28: Dare | PI28: Geauga | PK28: Sherman | PO28: Kershaw | PQ28: Giles | PS28: Caldwell | PU28: Wayne | PW28: Portsmouth (City) | PY28: San Juan | QA28: Jefferson | QH28: Montana | QI28: MT | QJ28: 35 | QK28: 35 | QU28: FL8 | QV28: 4 | QW28: North_Carolina | QX28: Etowah | QZ28: Greene | RA28: Hinsdale | RD28: Highlands | RE28: Cherokee | RF28: Kootenai | RG28: Franklin | RH28: Greene | RI28: Delaware | RJ28: Finney | RK28: LAFAYETTE PARISH | RO28: Grand Traverse | RP28: Houston | RQ28: Issaquena | RR28: Crawford | RV28: Sierra | RW28: Monroe | RX28: Dare | RY28: Geauga | RZ28: Sherman | SB28: Kershaw | SC28: Giles | SD28: Caldwell | SE28: Wayne | SF28: Clarke | SG28: San Juan | SI28: Jefferson | SN28: HILLSBOROUGH
G29: 22 | H29: HO3 | I29: FL | J29: FL13 | K29: Annual | L29: 0.38 | N29: 22 | O29: HO6 | P29: CW | Q29: 200000 | R29: 10000000 | S29: 200000 | T29: 1.5 | U29: 10000000 | V29: 1.5 | X29: 22 | Y29: HO6 | Z29: FL | AA29: 11 | AB29: 0.25 | AD29: 22 | AE29: ALL | AF29: Benton | AG29: Oregon | AH29: OR1 | AJ29: 22 | AK29: HO5 | AL29: CW | AM29: Superior | AN29: Annual | AO29: 0.8 | AQ29: 22 | AR29: HO5 | AS29: CW | AT29: Short-Term Rental | AU29: Annual | AV29: 1.05 | AX29: 22 | AY29: HO6 | AZ29: CW | BA29: 28 | BB29: 28 | BC29: Annual | BD29: 1.14 | BF29: 22 | BG29: HO5 | BH29: CW | BI29: 11 | BJ29: 999 | BK29: 11 | BL29: 999 | BM29: Annual | BN29: 1 | BP29: 22 | BQ29: HO6 | BR29: CW | BS29: No | BT29: ALL | BU29: 101 | BV29: 9999 | BW29: Annual | BX29: 1 | BZ29: 22 | CA29: DP3 | CB29: CW | CC29: 1 | CD29: Annual | CE29: 1 | CG29: 22 | CH29: DP3 | CI29: CW | CJ29: 0 | CK29: 99999 | CL29: Annual | CM29: 2 | CS29: 22 | CT29: HO5 | CU29: CW | CV29: 5 | CW29: Annual | CX29: 1.3 | CZ29: 22 | DA29: HO5 | DB29: CW | DC29: 4 | DD29: Annual | DE29: 1 | DG29: 22 | DH29: HO6 | DI29: CW | DJ29: CentralStationBurglarAlarm | DK29: Annual | DL29: 0.95 | DN29: 22 | DO29: HO3 | DP29: NEW_BUSINESS | DQ29: FL | DR29: ALL | DS29: 33029 | DT29: 10000 | DU29: Annual | DV29: 1 | DX29: 22 | DY29: HO5 | DZ29: CW | EA29: 500 | EC29: Annual | ED29: 1.1 | EM29: 22 | EN29: HO3 | EO29: CW | EP29: 6 | EQ29: 653 | ER29: 685 | ES29: Annual | ET29: 1.2 | EV29: 22 | EW29: HO3 | EX29: CO | EY29: 1 | EZ29: 1995 | FA29: 2999 | FB29: N | FC29: Annual | FD29: 0 | FF29: 22 | FG29: HO3 | FH29: AL | FI29: 1 | FJ29: 130000 | FK29: Annual | FL29: 0.57 | FN29: 22 | FO29: VDP1 | FP29: CW | FQ29: 10000 | FR29: Monthly | FS29: 25 | FU29: 22 | FV29: HO6 | FW29: CW | FX29: 10000 | FY29: Annual | FZ29: 15 | GH29: 22 | GI29: HO6 | GJ29: CW | GK29: 31000 | GL29: 130 | GT29: 22 | GU29: HO5 | GV29: SC | GW29: Yes | GX29: Superior | GY29: Annual | GZ29: 0.15 | HB29: 22 | HC29: HO5 | HD29: SC | HE29: Yes | HF29: 5 | HG29: Annual | HH29: 1 | IJ29: 22 | IK29: HO5 | IL29: CW | IM29: 500000 | IN29: Annual | IO29: 100 | IQ29: 22 | IR29: DP1 | IS29: CW | IT29: 0 | IU29: 0 | IW29: 22 | IX29: HO6 | IY29: ME | IZ29: 13 | JA29: 300 | JC29: 22 | JD29: Nevada | JE29: ALL | JF29: ALL | JG29: ALL | JH29: -0.05 | JJ29: 22 | JK29: Nevada | JL29: ALL | JM29: ALL | JN29: ALL | JO29: 0.055 | JP29: 0.025 | JQ29: 0.12 | JW29: 22 | JX29: Alabama | JY29: Cullman | KA29: 22 | KB29: NC14 | KC29: 0.4 | KE29: 22 | KF29: ALL | KG29: IL | KH29: 100 | KJ29: 22 | KK29: HO5 | KL29: Cameras | KM29: 0.01 | NG29: Fayette | NK29: Hempstead | NM29: Huerfano | NS29: Holmes | NU29: Clarke | NW29: Latah | NY29: Fulton | OA29: Hamilton | OC29: Des Moines | OE29: Ford | OG29: Lafourche | OO29: Gratiot | OQ29: Hubbard | OS29: Itawamba | OU29: Dade | PC29: Socorro | PE29: Montgomery | PG29: Davidson | PI29: Greene | PK29: Tillamook | PO29: Lancaster | PQ29: Grainger | PS29: Calhoun | PU29: Weber | PW29: Radford (City) | PY29: Skagit | QA29: Juneau | QH29: Nebraska | QI29: NE | QJ29: 100 | QK29: 200 | QU29: FL9 | QV29: 4 | QW29: Ohio | QX29: Fayette | QZ29: Hempstead | RA29: Huerfano | RD29: Hillsborough | RE29: Clarke | RF29: Latah | RG29: Fulton | RH29: Hamilton | RI29: Des Moines | RJ29: Ford | RK29: La Salle | RO29: Gratiot | RP29: Hubbard | RQ29: Itawamba | RR29: Dade | RV29: Socorro | RW29: Montgomery | RX29: Davidson | RY29: Greene | RZ29: Tillamook | SB29: Lancaster | SC29: Grainger | SD29: Calhoun | SE29: Weber | SF29: Colonial Heights (City) | SG29: Skagit | SI29: Juneau | SN29: HOLMES
G30: 23 | H30: HO3 | I30: FL | J30: FL14 | K30: Annual | L30: 0.38 | X30: 23 | Y30: HO6 | Z30: FL | AA30: 12 | AB30: 0.25 | AD30: 23 | AE30: ALL | AF30: Gilliam | AG30: Oregon | AH30: OR1 | AJ30: 23 | AK30: HO8 | AL30: CW | AM30: Superior | AN30: Annual | AO30: 0.8 | AQ30: 23 | AR30: HO8 | AS30: CW | AT30: Short-Term Rental | AU30: Annual | AV30: 1.05 | AX30: 23 | AY30: HO6 | AZ30: CW | BA30: 29 | BB30: 29 | BC30: Annual | BD30: 1.15 | BF30: 23 | BG30: HO8 | BH30: CW | BI30: 11 | BJ30: 999 | BK30: 11 | BL30: 999 | BM30: Annual | BN30: 1 | BP30: 23 | BQ30: HO6 | BR30: CW | BS30: Yes | BT30: Frame | BU30: 101 | BV30: 9999 | BW30: Annual | BX30: 0 | BZ30: 23 | CA30: DP3 | CB30: CW | CC30: 2 | CD30: Annual | CE30: 1.1 | CG30: 23 | CH30: DP3 | CI30: CW | CJ30: 100000 | CK30: 149999 | CL30: Annual | CM30: 1.35 | CS30: 23 | CT30: HO8 | CU30: CW | CV30: 5 | CW30: Annual | CX30: 1.3 | CZ30: 23 | DA30: HO8 | DB30: CW | DC30: 4 | DD30: Annual | DE30: 1 | DG30: 23 | DH30: HO6 | DI30: CW | DJ30: CentralStationFireAlarm | DK30: Annual | DL30: 0.95 | DN30: 23 | DO30: HO3 | DP30: NEW_BUSINESS | DQ30: FL | DR30: ALL | DS30: 33031 | DT30: 10000 | DU30: Annual | DV30: 1 | DX30: 23 | DY30: HO8 | DZ30: CW | EA30: 500 | EC30: Annual | ED30: 1.1 | EM30: 23 | EN30: HO3 | EO30: CW | EP30: 6 | EQ30: 614 | ER30: 652 | ES30: Annual | ET30: 1.4 | EV30: 23 | EW30: HO3 | EX30: CT | EY30: 1 | EZ30: 0 | FA30: 1994 | FB30: Y | FC30: Annual | FD30: 2.63 | FF30: 23 | FG30: HO3 | FH30: AL | FI30: 1 | FJ30: 260000 | FK30: Annual | FL30: 0.57 | FN30: 23 | FO30: VDP3 | FP30: CW | FQ30: 10000 | FR30: Monthly | FS30: 25 | FU30: 23 | FV30: HO6 | FW30: CW | FX30: 25000 | FY30: Annual | FZ30: 40 | GH30: 23 | GI30: HO6 | GJ30: CW | GK30: 32000 | GL30: 135 | GT30: 23 | GU30: HO8 | GV30: SC | GW30: Yes | GX30: Superior | GY30: Annual | GZ30: 0.15 | HB30: 23 | HC30: HO8 | HD30: SC | HE30: Yes | HF30: 5 | HG30: Annual | HH30: 1 | IJ30: 23 | IK30: HO8 | IL30: CW | IM30: 500000 | IN30: Annual | IO30: 100 | IQ30: 23 | IR30: DP1 | IS30: CW | IT30: 1000 | IU30: 0 | IW30: 23 | IX30: HO6 | IY30: ME | IZ30: 14 | JA30: 300 | JC30: 23 | JD30: New_Hampshire | JE30: ALL | JF30: ALL | JG30: ALL | JH30: -0.05 | JJ30: 23 | JK30: New_Hampshire | JL30: ALL | JM30: ALL | JN30: ALL | JO30: 0.03 | JP30: -0.02 | JQ30: 0.08 | JW30: 23 | JX30: Alabama | JY30: Dale | KA30: 23 | KB30: NC22 | KC30: 0.4 | KE30: 23 | KF30: ALL | KG30: VA | KH30: 100 | KJ30: 23 | KK30: HO8 | KL30: Cameras | KM30: 0.01 | NG30: Franklin | NK30: Hot Spring | NM30: Jackson | NS30: Indian River | NU30: Clay | NW30: Lemhi | NY30: Gallatin | OA30: Hancock | OC30: Dickinson | OE30: Franklin | OG30: La Salle | OO30: Hillsdale | OQ30: Isanti | OS30: Jackson | OU30: Dallas | PC30: Taos | PE30: Nassau | PG30: Davie | PI30: Guernsey | PK30: Umatilla | PO30: Laurens | PQ30: Greene | PS30: Callahan | PW30: Richmond (City) | PY30: Skamania | QA30: Kenosha | QH30: Nevada | QI30: NV | QJ30: 100 | QK30: 200 | QU30: FL10 | QV30: 4 | QW30: Oregon | QX30: Franklin | QZ30: Hot Spring | RA30: Jackson | RD30: Holmes | RE30: Clay | RF30: Lemhi | RG30: Gallatin | RH30: Hancock | RI30: Dickinson | RJ30: Franklin | RK30: Lafayette | RO30: Hillsdale | RP30: Isanti | RQ30: Jackson | RR30: Dallas | RV30: Taos | RW30: Nassau | RX30: Davie | RY30: Guernsey | RZ30: Umatilla | SB30: Laurens | SC30: Greene | SD30: Callahan | SF30: Covington (City) | SG30: Skamania | SI30: Kenosha | SN30: INDIAN RIVER
G31: 24 | H31: HO3 | I31: FL | J31: FL2 | K31: Annual | L31: 0.45 | X31: 24 | Y31: HO6 | Z31: FL | AA31: 13 | AB31: 0.25 | AD31: 24 | AE31: ALL | AF31: Lake | AG31: Oregon | AH31: OR1 | AJ31: 24 | AK31: DP1 | AL31: CW | AM31: Superior | AN31: Annual | AO31: 0.8 | AQ31: 24 | AR31: DP1 | AS31: CW | AT31: Short-Term Rental | AU31: Annual | AV31: 1.05 | AX31: 24 | AY31: HO6 | AZ31: CW | BA31: 3 | BB31: 3 | BC31: Annual | BD31: 0.83 | BF31: 24 | BG31: DP1 | BH31: CW | BI31: 11 | BJ31: 999 | BK31: 11 | BL31: 999 | BM31: Annual | BN31: 1 | BP31: 24 | BQ31: HO6 | BR31: CW | BS31: Yes | BT31: Frame | BU31: 0 | BV31: 3 | BW31: Annual | BX31: 1.05 | BZ31: 24 | CA31: DP3 | CB31: CW | CC31: 3 | CD31: Annual | CE31: 1.5 | CG31: 24 | CH31: DP3 | CI31: CW | CJ31: 150000 | CK31: 249999 | CL31: Annual | CM31: 1.2 | CS31: 24 | CT31: DP1 | CU31: CW | CV31: 5 | CW31: Annual | CX31: 1.3 | CZ31: 24 | DA31: DP1 | DB31: CW | DC31: 4 | DD31: Annual | DE31: 1 | DG31: 24 | DH31: HO6 | DI31: CW | DJ31: CentralStationBurglar&Firealarm | DK31: Annual | DL31: 0.95 | DN31: 24 | DO31: HO3 | DP31: NEW_BUSINESS | DQ31: FL | DR31: ALL | DS31: 33032 | DT31: 10000 | DU31: Annual | DV31: 1 | DX31: 24 | DY31: DP1 | DZ31: CW | EA31: 500 | EC31: Annual | ED31: 1.1 | EM31: 24 | EN31: HO3 | EO31: CW | EP31: 6 | EQ31: 549 | ER31: 613 | ES31: Annual | ET31: 1.7 | EV31: 24 | EW31: HO3 | EX31: CT | EY31: 1 | EZ31: 1995 | FA31: 2999 | FB31: Y | FC31: Annual | FD31: 2.63 | FF31: 24 | FG31: HO3 | FH31: AL | FI31: 1 | FJ31: 400000 | FK31: Annual | FL31: 0.57 | FN31: 24 | FO31: Builders Risk | FP31: CW | FQ31: 15000 | FR31: Monthly | FS31: 50 | FU31: 24 | FV31: HO6 | FW31: CW | FX31: 5000 | FY31: Annual | FZ31: 10 | GH31: 24 | GI31: HO6 | GJ31: CW | GK31: 33000 | GL31: 140 | GT31: 24 | GU31: DP1 | GV31: SC | GW31: Yes | GX31: Superior | GY31: Annual | GZ31: 0.15 | HB31: 24 | HC31: DP1 | HD31: SC | HE31: Yes | HF31: 5 | HG31: Annual | HH31: 1 | IJ31: 24 | IK31: DP1 | IL31: CW | IM31: 500000 | IN31: Annual | IO31: 100 | IQ31: 24 | IR31: DP1 | IS31: CW | IT31: 10000 | IU31: 40 | IW31: 24 | IX31: HO6 | IY31: ME | IZ31: 15 | JA31: 300 | JC31: 24 | JD31: New_Jersey | JE31: ALL | JF31: ALL | JG31: ALL | JH31: -0.05 | JJ31: 24 | JK31: New_Jersey | JL31: ALL | JM31: ALL | JN31: ALL | JO31: 0.05 | JP31: 0.025 | JQ31: 0.11 | JW31: 24 | JX31: Alabama | JY31: Dallas | KA31: 24 | KB31: RI4 | KC31: 0.3 | KE31: 24 | KF31: ALL | KG31: NC | KH31: 100 | KJ31: 24 | KK31: DP1 | KL31: Cameras | KM31: 0.01 | NG31: Geneva | NK31: Howard | NM31: Jefferson | NS31: Jackson | NU31: Clayton | NW31: Lewis | NY31: Greene | OA31: Harrison | OC31: Dubuque | OE31: Geary | OG31: Lincoln | OO31: Houghton | OQ31: Itasca | OS31: Jasper | OU31: Daviess | PC31: Torrance | PE31: New York | PG31: Duplin | PI31: Hamilton | PK31: Union | PO31: Lee | PQ31: Grundy | PS31: Cameron | PW31: Roanoke (City) | PY31: Snohomish | QA31: Kewaunee | QH31: New_Hampshire | QI31: NH | QJ31: 100 | QK31: 200 | QU31: FL11 | QV31: 4 | QW31: Rhode_Island | QX31: Geneva | QZ31: Howard | RA31: Jefferson | RD31: Indian River | RE31: Clayton | RF31: Lewis | RG31: Greene | RH31: Harrison | RI31: Dubuque | RJ31: Geary | RK31: Lafourche | RO31: Houghton | RP31: Itasca | RQ31: Jasper | RR31: Daviess | RV31: Torrance | RW31: New York | RX31: Duplin | RY31: Hamilton | RZ31: Union | SB31: Lee | SC31: Grundy | SD31: Cameron | SF31: Craig | SG31: Snohomish | SI31: Kewaunee | SN31: JACKSON
G32: 25 | H32: HO3 | I32: FL | J32: FL3 | K32: Annual | L32: 0.25 | X32: 25 | Y32: HO6 | Z32: FL | AA32: 14 | AB32: 0.25 | AD32: 25 | AE32: ALL | AF32: Polk | AG32: Oregon | AH32: OR1 | AJ32: 25 | AK32: DP3 | AL32: CW | AM32: Superior | AN32: Annual | AO32: 0.8 | AQ32: 25 | AR32: DP3 | AS32: CW | AT32: Short-Term Rental | AU32: Annual | AV32: 1.05 | AX32: 25 | AY32: HO6 | AZ32: CW | BA32: 30 | BB32: 30 | BC32: Annual | BD32: 1.17 | BF32: 25 | BG32: DP3 | BH32: CW | BI32: 11 | BJ32: 999 | BK32: 11 | BL32: 999 | BM32: Annual | BN32: 1 | BP32: 25 | BQ32: HO6 | BR32: CW | BS32: Yes | BT32: Frame | BU32: 4 | BV32: 7 | BW32: Annual | BX32: 1 | BZ32: 25 | CA32: DP3 | CB32: CW | CC32: 4 | CD32: Annual | CE32: 2 | CG32: 25 | CH32: DP3 | CI32: CW | CJ32: 250000 | CK32: 349999 | CL32: Annual | CM32: 1 | CS32: 25 | CT32: DP3 | CU32: CW | CV32: 5 | CW32: Annual | CX32: 1.3 | CZ32: 25 | DA32: DP3 | DB32: CW | DC32: 4 | DD32: Annual | DE32: 1 | DG32: 25 | DH32: Builders Risk | DI32: CW | DJ32: None | DK32: Monthly | DL32: 1 | DN32: 25 | DO32: HO3 | DP32: NEW_BUSINESS | DQ32: FL | DR32: ALL | DS32: 33033 | DT32: 10000 | DU32: Annual | DV32: 1 | DX32: 25 | DY32: DP3 | DZ32: CW | EA32: 500 | EC32: Annual | ED32: 1.1 | EM32: 25 | EN32: HO3 | EO32: CW | EP32: A | EQ32: -1 | ER32: -1 | ES32: Annual | ET32: 1.42 | EV32: 25 | EW32: HO3 | EX32: CT | EY32: 2 | EZ32: 0 | FA32: 1994 | FB32: Y | FC32: Annual | FD32: 2.5 | FF32: 25 | FG32: HO3 | FH32: AL | FI32: 1 | FJ32: 530000 | FK32: Annual | FL32: 0.57 | FN32: 25 | FO32: Builders Risk DP3 | FP32: CW | FQ32: 15000 | FR32: Monthly | FS32: 50 | GH32: 25 | GI32: HO6 | GJ32: CW | GK32: 34000 | GL32: 145 | GT32: 25 | GU32: DP3 | GV32: SC | GW32: Yes | GX32: Superior | GY32: Annual | GZ32: 0.15 | HB32: 25 | HC32: DP3 | HD32: SC | HE32: Yes | HF32: 5 | HG32: Annual | HH32: 1 | IJ32: 25 | IK32: DP3 | IL32: CW | IM32: 500000 | IN32: Annual | IO32: 100 | IQ32: 25 | IR32: DP1 | IS32: CW | IT32: 2000 | IU32: 5 | IW32: 25 | IX32: HO6 | IY32: MA | IZ32: 1 | JA32: 300 | JC32: 25 | JD32: New_Mexico | JE32: ALL | JF32: ALL | JG32: ALL | JH32: -0.05 | JJ32: 25 | JK32: New_Mexico | JL32: ALL | JM32: ALL | JN32: ALL | JO32: 0.03 | JP32: -0.025 | JQ32: 0.08 | JW32: 25 | JX32: Alabama | JY32: DeKalb | KA32: 25 | KB32: SC7 | KC32: 0.45 | KE32: 25 | KF32: ALL | KG32: AL | KH32: 100 | KJ32: 25 | KK32: DP3 | KL32: Cameras | KM32: 0.01 | NG32: Greene | NK32: Independence | NM32: Kiowa | NS32: Jefferson | NU32: Clinch | NW32: Lincoln | NY32: Grundy | OA32: Hendricks | OC32: Emmet | OE32: Gove | OG32: Livingston | OO32: Huron | OQ32: Jackson | OS32: Jefferson | OU32: DeKalb | PC32: Union | PE32: Niagara | PG32: Durham | PI32: Hancock | PK32: Wallowa | PO32: Lexington | PQ32: Hamblen | PS32: Camp | PW32: Salem (City) | PY32: Spokane | QA32: La Crosse | QH32: New_Jersey | QI32: NJ | QJ32: 50 | QK32: 50 | QU32: FL12 | QV32: 4 | QW32: South_Carolina | QX32: Greene | QZ32: Independence | RA32: Kiowa | RD32: Jackson | RE32: Clinch | RF32: Lincoln | RG32: Grundy | RH32: Hendricks | RI32: Emmet | RJ32: Gove | RK32: Lincoln | RO32: Huron | RP32: Jackson | RQ32: Jefferson | RR32: DeKalb | RV32: Union | RW32: Niagara | RX32: Durham | RY32: Hancock | RZ32: Wallowa | SB32: Lexington | SC32: Hamblen | SD32: Camp | SF32: Culpeper | SG32: Spokane | SI32: La Crosse | SN32: JEFFERSON
G33: 26 | H33: HO3 | I33: FL | J33: FL4 | K33: Annual | L33: 0.25 | X33: 26 | Y33: HO6 | Z33: FL | AA33: 15 | AB33: 0.25 | AD33: 26 | AE33: ALL | AF33: Wheeler | AG33: Oregon | AH33: OR1 | AJ33: 26 | AK33: Builders Risk | AL33: CW | AM33: Frame | AN33: Monthly | AO33: 1 | AQ33: 26 | AR33: HO3 | AS33: CW | AT33: Vacant | AU33: Annual | AV33: 1 | AX33: 26 | AY33: HO6 | AZ33: CW | BA33: 31 | BB33: 31 | BC33: Annual | BD33: 1.18 | BF33: 26 | BG33: HO3 | BH33: CW | BI33: 11 | BJ33: 999 | BK33: 6 | BL33: 10 | BM33: Annual | BN33: 0.975 | BP33: 26 | BQ33: HO6 | BR33: CW | BS33: Yes | BT33: Frame | BU33: 8 | BV33: 9999 | BW33: Annual | BX33: 0.95 | BZ33: 26 | CA33: HO6 | CB33: CW | CC33: 0 | CD33: Annual | CE33: 0.98 | CG33: 26 | CH33: DP3 | CI33: CW | CJ33: 350000 | CK33: 499999 | CL33: Annual | CM33: 0.95 | CS33: 26 | CT33: Builders Risk | CU33: CW | CV33: 1 | CW33: Monthly | CX33: 1 | CZ33: 26 | DA33: HO3 | DB33: CW | DC33: 5 | DD33: Annual | DE33: 1 | DG33: 26 | DH33: Builders Risk DP3 | DI33: CW | DJ33: None | DK33: Monthly | DL33: 1 | DN33: 26 | DO33: HO3 | DP33: NEW_BUSINESS | DQ33: FL | DR33: ALL | DS33: 33034 | DT33: 10000 | DU33: Annual | DV33: 1 | DX33: 26 | DY33: HO3 | DZ33: CW | EA33: 5000 | EC33: Annual | ED33: 0.9 | EM33: 26 | EN33: HO3 | EO33: CW | EP33: Did Not Order | EQ33: -1 | ER33: -1 | ES33: Annual | ET33: 1.42 | EV33: 26 | EW33: HO3 | EX33: CT | EY33: 2 | EZ33: 1995 | FA33: 2999 | FB33: Y | FC33: Annual | FD33: 2.5 | FF33: 26 | FG33: HO3 | FH33: AL | FI33: 1 | FJ33: 540000 | FK33: Annual | FL33: 0.57 | FN33: 26 | FO33: VDP1 | FP33: CW | FQ33: 15000 | FR33: Monthly | FS33: 50 | GH33: 26 | GI33: HO6 | GJ33: CW | GK33: 35000 | GL33: 150 | GT33: 26 | GU33: DP1_Builders_Risk | GV33: SC | GW33: Yes | GX33: Frame | GY33: Monthly | GZ33: 0.0083 | HB33: 26 | HC33: Builders Risk | HD33: SC | HE33: Yes | HF33: 0 | HG33: Monthly | HH33: 0 | IJ33: 26 | IK33: DP3_Builders_Risk | IL33: CW | IM33: 0 | IN33: Monthly | IO33: 0 | IQ33: 26 | IR33: DP1 | IS33: CW | IT33: 3000 | IU33: 10 | IW33: 26 | IX33: HO6 | IY33: MA | IZ33: 2 | JA33: 300 | JJ33: 26 | JK33: New_York | JL33: ALL | JM33: ALL | JN33: ALL | JO33: 1 | JP33: 1 | JQ33: 1 | JW33: 26 | JX33: Alabama | JY33: Elmore | KA33: 26 | KB33: TX2 | KC33: 0.45 | KE33: 26 | KF33: ALL | KG33: TN | KH33: 100 | KJ33: 26 | KK33: HO3 | KL33: Musical Instruments | KM33: 0.01 | NG33: Hale | NK33: Izard | NM33: Kit Carson | NS33: Lafayette | NU33: Cobb | NW33: Madison | NY33: Hamilton | OA33: Henry | OC33: Fayette | OE33: Graham | OG33: Madison | OO33: Ingham | OQ33: Kanabec | OS33: Jefferson Davis | OU33: Dent | PC33: Valencia | PE33: Oneida | PG33: Edgecombe | PI33: Hardin | PK33: Wasco | PO33: Marion | PQ33: Hamilton | PS33: Carson | PW33: Staunton (City) | PY33: Stevens | QA33: Lafayette | QH33: New_Mexico | QI33: NM | QJ33: 100 | QK33: 200 | QU33: FL13 | QV33: 4 | QW33: Tennessee | QX33: Hale | QZ33: Izard | RA33: Kit Carson | RD33: Jefferson | RE33: Cobb | RF33: Madison | RG33: Hamilton | RH33: Henry | RI33: Fayette | RJ33: Graham | RK33: Livingston | RO33: Ingham | RP33: Kanabec | RQ33: Jefferson Davis | RR33: Dent | RV33: Valencia | RW33: Oneida | RX33: Edgecombe | RY33: Hardin | RZ33: Wasco | SB33: Marion | SC33: Hamilton | SD33: Carson | SF33: Cumberland | SG33: Stevens | SI33: Lafayette | SN33: LAFAYETTE
G34: 27 | H34: HO3 | I34: FL | J34: FL5 | K34: Annual | L34: 0.25 | X34: 27 | Y34: HO6 | Z34: FL | AA34: 16 | AB34: 0.25 | AD34: 27 | AE34: 29905 | AF34: Beaufort | AG34: South Carolina | AH34: SC1 | AJ34: 27 | AK34: Builders Risk DP3 | AL34: CW | AM34: Frame | AN34: Monthly | AO34: 1 | AQ34: 27 | AR34: HO5 | AS34: CW | AT34: Vacant | AU34: Annual | AV34: 1 | AX34: 27 | AY34: HO6 | AZ34: CW | BA34: 32 | BB34: 32 | BC34: Annual | BD34: 1.19 | BF34: 27 | BG34: HO5 | BH34: CW | BI34: 11 | BJ34: 999 | BK34: 6 | BL34: 10 | BM34: Annual | BN34: 0.975 | BP34: 27 | BQ34: HO6 | BR34: CW | BS34: Yes | BT34: Masonry | BU34: 101 | BV34: 9999 | BW34: Annual | BX34: 0 | BZ34: 27 | CA34: HO6 | CB34: CW | CC34: 1 | CD34: Annual | CE34: 1 | CG34: 27 | CH34: DP3 | CI34: CW | CJ34: 500000 | CK34: 1000000 | CL34: Annual | CM34: 0.9 | CS34: 27 | CT34: Builders Risk DP3 | CU34: CW | CV34: 1 | CW34: Monthly | CX34: 1 | CZ34: 27 | DA34: HO5 | DB34: CW | DC34: 5 | DD34: Annual | DE34: 1 | DG34: 27 | DH34: VDP1 | DI34: CW | DJ34: None | DK34: Monthly | DL34: 1 | DN34: 27 | DO34: HO3 | DP34: NEW_BUSINESS | DQ34: FL | DR34: ALL | DS34: 33056 | DT34: 10000 | DU34: Annual | DV34: 1 | DX34: 27 | DY34: HO5 | DZ34: CW | EA34: 5000 | EC34: Annual | ED34: 0.9 | EM34: 27 | EN34: HO3 | EO34: CW | EP34: Error | EQ34: -1 | ER34: -1 | ES34: Annual | ET34: 1.42 | EV34: 27 | EW34: HO3 | EX34: DC | EY34: 1 | EZ34: 0 | FA34: 1994 | FB34: N | FC34: Annual | FD34: 0 | FF34: 27 | FG34: HO3 | FH34: AL | FI34: 2 | FJ34: 0 | FK34: Annual | FL34: 1.02 | FN34: 27 | FO34: VDP3 | FP34: CW | FQ34: 15000 | FR34: Monthly | FS34: 50 | GH34: 27 | GI34: HO6 | GJ34: CW | GK34: 36000 | GL34: 155 | GT34: 27 | GU34: DP3_Builders_Risk | GV34: SC | GW34: Yes | GX34: Frame | GY34: Monthly | GZ34: 0.0083 | HB34: 27 | HC34: Builders Risk DP3 | HD34: SC | HE34: Yes | HF34: 0 | HG34: Monthly | HH34: 0 | IJ34: 27 | IK34: DP1_Vacant | IL34: CW | IM34: 0 | IN34: Monthly | IO34: 0 | IQ34: 27 | IR34: DP1 | IS34: CW | IT34: 4000 | IU34: 15 | IW34: 27 | IX34: HO6 | IY34: MA | IZ34: 3 | JA34: 300 | JJ34: 27 | JK34: North_Carolina | JL34: ALL | JM34: ALL | JN34: ALL | JO34: 1 | JP34: 1 | JQ34: 1 | JW34: 27 | JX34: Alabama | JY34: Escambia | KA34: 27 | KB34: TX10 | KC34: 0.45 | KE34: 27 | KF34: ALL | KG34: MN | KH34: 100 | KJ34: 27 | KK34: HO5 | KL34: Musical Instruments | KM34: 0.01 | NG34: Henry | NK34: Jackson | NM34: La Plata | NS34: Lake | NU34: Coffee | NW34: Minidoka | NY34: Hancock | OA34: Howard | OC34: Floyd | OE34: Grant | OG34: Morehouse | OO34: Ionia | OQ34: Kandiyohi | OS34: Jones | OU34: Douglas | PE34: Onondaga | PG34: Forsyth | PI34: Harrison | PK34: Washington | PO34: Marlboro | PQ34: Hancock | PS34: Cass | PW34: Suffolk (City) | PY34: Thurston | QA34: Langlade | QH34: New_York | QI34: NY | QJ34: 100 | QK34: 200 | QU34: FL14 | QV34: 4 | QW34: Texas | QX34: Henry | QZ34: Jackson | RA34: La Plata | RD34: Lafayette | RE34: Coffee | RF34: Minidoka | RG34: Hancock | RH34: Howard | RI34: Floyd | RJ34: Grant | RK34: Madison | RO34: Ionia | RP34: Kandiyohi | RQ34: Jones | RR34: Douglas | RW34: Onondaga | RX34: Forsyth | RY34: Harrison | RZ34: Washington | SB34: Marlboro | SC34: Hancock | SD34: Cass | SF34: Danville (City) | SG34: Thurston | SI34: Langlade | SN34: LAKE
G35: 28 | H35: HO3 | I35: FL | J35: FL6 | K35: Annual | L35: 0.25 | X35: 28 | Y35: HO6 | Z35: FL | AA35: 17 | AB35: 0.25 | AD35: 28 | AE35: 29928 | AF35: Beaufort | AG35: South Carolina | AH35: SC1 | AJ35: 28 | AK35: VDP1 | AL35: CW | AM35: Frame | AN35: Monthly | AO35: 1 | AQ35: 28 | AR35: HO8 | AS35: CW | AT35: Vacant | AU35: Annual | AV35: 1 | AX35: 28 | AY35: HO6 | AZ35: CW | BA35: 33 | BB35: 33 | BC35: Annual | BD35: 1.2 | BF35: 28 | BG35: HO8 | BH35: CW | BI35: 11 | BJ35: 999 | BK35: 6 | BL35: 10 | BM35: Annual | BN35: 0.975 | BP35: 28 | BQ35: HO6 | BR35: CW | BS35: Yes | BT35: Steel | BU35: 101 | BV35: 9999 | BW35: Annual | BX35: 0 | BZ35: 28 | CA35: HO6 | CB35: CW | CC35: 2 | CD35: Annual | CE35: 1.1 | CG35: 28 | CH35: DP3 | CI35: CW | CJ35: 1000001 | CK35: 9999999999 | CL35: Annual | CM35: 0.85 | CS35: 28 | CT35: VDP1 | CU35: CW | CV35: 1 | CW35: Monthly | CX35: 1 | CZ35: 28 | DA35: HO8 | DB35: CW | DC35: 5 | DD35: Annual | DE35: 1 | DG35: 28 | DH35: VDP3 | DI35: CW | DJ35: None | DK35: Monthly | DL35: 1 | DN35: 28 | DO35: HO3 | DP35: NEW_BUSINESS | DQ35: FL | DR35: ALL | DS35: 33063 | DT35: 10000 | DU35: Annual | DV35: 1 | DX35: 28 | DY35: HO8 | DZ35: CW | EA35: 5000 | EC35: Annual | ED35: 0.9 | EM35: 28 | EN35: HO3 | EO35: CW | EP35: I | EQ35: -1 | ER35: -1 | ES35: Annual | ET35: 1.42 | EV35: 28 | EW35: HO3 | EX35: DC | EY35: 1 | EZ35: 1995 | FA35: 2999 | FB35: N | FC35: Annual | FD35: 0 | FF35: 28 | FG35: HO3 | FH35: AL | FI35: 2 | FJ35: 1000 | FK35: Annual | FL35: 1.02 | GH35: 28 | GI35: HO6 | GJ35: CW | GK35: 37000 | GL35: 160 | GT35: 28 | GU35: DP1_Vacant | GV35: SC | GW35: Yes | GX35: Frame | GY35: Monthly | GZ35: 0.0083 | HB35: 28 | HC35: VDP1 | HD35: SC | HE35: Yes | HF35: 0 | HG35: Monthly | HH35: 0 | IJ35: 28 | IK35: DP3_Vacant | IL35: CW | IM35: 0 | IN35: Monthly | IO35: 0 | IQ35: 28 | IR35: DP1 | IS35: CW | IT35: 5000 | IU35: 20 | IW35: 28 | IX35: HO6 | IY35: MA | IZ35: 4 | JA35: 300 | JJ35: 28 | JK35: Ohio | JL35: ALL | JM35: ALL | JN35: ALL | JO35: 1 | JP35: 1 | JQ35: 1 | JW35: 28 | JX35: Alabama | JY35: Etowah | KA35: 28 | KB35: TX18 | KC35: 0.45 | KE35: 28 | KF35: ALL | KG35: DC | KH35: 100 | KJ35: 28 | KK35: HO8 | KL35: Musical Instruments | KM35: 0.01 | NG35: Houston | NK35: Jefferson | NM35: Lake | NS35: Lee | NU35: Colquitt | NW35: Nez Perce | NY35: Hardin | OA35: Huntington | OC35: Franklin | OE35: Gray | OG35: Natchitoches | OO35: Iosco | OQ35: Kittson | OS35: Kemper | OU35: Dunklin | PE35: Ontario | PG35: Franklin | PI35: Henry | PK35: Wheeler | PO35: McCormick | PQ35: Hardeman | PS35: Castro | PW35: Virginia Beach (City) | PY35: Wahkiakum | QA35: Lincoln | QH35: North_Carolina | QI35: NC | QJ35: 100 | QK35: 200 | QU35: FL15 | QV35: 4 | QW35: Utah | QX35: Houston | QZ35: Jefferson | RA35: Lake | RD35: Lake | RE35: Colquitt | RF35: Nez Perce | RG35: Hardin | RH35: Huntington | RI35: Franklin | RJ35: Gray | RK35: Morehouse | RO35: Iosco | RP35: Kittson | RQ35: Kemper | RR35: Dunklin | RW35: Ontario | RX35: Franklin | RY35: Henry | RZ35: Wheeler | SB35: McCormick | SC35: Hardeman | SD35: Castro | SF35: Dickenson | SG35: Wahkiakum | SI35: Lincoln | SN35: LEE
G36: 29 | H36: HO3 | I36: FL | J36: FL7 | K36: Annual | L36: 0.25 | X36: 29 | Y36: HO6 | Z36: FL | AA36: 18 | AB36: 0.25 | AD36: 29 | AE36: 29404 | AF36: Charleston | AG36: South Carolina | AH36: SC2 | AJ36: 29 | AK36: VDP3 | AL36: CW | AM36: Frame | AN36: Monthly | AO36: 1 | AQ36: 29 | AR36: DP1 | AS36: CW | AT36: Vacant | AU36: Annual | AV36: 1 | AX36: 29 | AY36: HO6 | AZ36: CW | BA36: 34 | BB36: 34 | BC36: Annual | BD36: 1.21 | BF36: 29 | BG36: DP1 | BH36: CW | BI36: 11 | BJ36: 999 | BK36: 6 | BL36: 10 | BM36: Annual | BN36: 0.975 | BP36: 29 | BQ36: HO6 | BR36: CW | BS36: Yes | BT36: Reinforced Concrete | BU36: 101 | BV36: 9999 | BW36: Annual | BX36: 0 | BZ36: 29 | CA36: HO6 | CB36: CW | CC36: 3 | CD36: Annual | CE36: 1.5 | CG36: 29 | CH36: HO3 | CI36: CW | CJ36: 0 | CK36: 99999 | CL36: Annual | CM36: 2 | CS36: 29 | CT36: VDP3 | CU36: CW | CV36: 1 | CW36: Monthly | CX36: 1 | CZ36: 29 | DA36: DP1 | DB36: CW | DC36: 5 | DD36: Annual | DE36: 1 | DG36: 29 | DH36: Builders Risk | DI36: CW | DJ36: CentralStationBurglarAlarm | DK36: Monthly | DL36: 0.95 | DN36: 29 | DO36: HO3 | DP36: NEW_BUSINESS | DQ36: FL | DR36: ALL | DS36: 33068 | DT36: 10000 | DU36: Annual | DV36: 1 | DX36: 29 | DY36: DP1 | DZ36: CW | EA36: 5000 | EC36: Annual | ED36: 0.9 | EM36: 29 | EN36: HO3 | EO36: CW | EP36: L | EQ36: -1 | ER36: -1 | ES36: Annual | ET36: 1.42 | EV36: 29 | EW36: HO3 | EX36: DE | EY36: 1 | EZ36: 0 | FA36: 1994 | FB36: Y | FC36: Annual | FD36: 2.25 | FF36: 29 | FG36: HO3 | FH36: AL | FI36: 2 | FJ36: 2500 | FK36: Annual | FL36: 0.95 | GH36: 29 | GI36: HO6 | GJ36: CW | GK36: 38000 | GL36: 165 | GT36: 29 | GU36: DP3_Vacant | GV36: SC | GW36: Yes | GX36: Frame | GY36: Monthly | GZ36: 0.0083 | HB36: 29 | HC36: VDP3 | HD36: SC | HE36: Yes | HF36: 0 | HG36: Monthly | HH36: 0 | IJ36: 29 | IK36: DP1_Builders_Risk | IL36: CW | IM36: 0 | IN36: Monthly | IO36: 0 | IQ36: 29 | IR36: DP3 | IS36: CW | IT36: 0 | IU36: 0 | IW36: 29 | IX36: HO6 | IY36: MA | IZ36: 5 | JA36: 300 | JJ36: 29 | JK36: Oregon | JL36: ALL | JM36: ALL | JN36: ALL | JO36: 1 | JP36: 1 | JQ36: 1 | JW36: 29 | JX36: Alabama | JY36: Fayette | KA36: 29 | KB36: TX26 | KC36: 0.45 | KE36: 29 | KF36: ALL | KG36: PA | KH36: 100 | KJ36: 29 | KK36: DP1 | KL36: Musical Instruments | KM36: 0.01 | NG36: Jackson | NK36: Johnson | NM36: Larimer | NS36: Leon | NU36: Columbia | NW36: Oneida | NY36: Henderson | OA36: Jackson | OC36: Fremont | OE36: Greeley | OG36: Orleans | OO36: Iron | OQ36: Koochiching | OS36: Lafayette | OU36: Franklin | PE36: Orange | PG36: Gaston | PI36: Highland | PK36: Yamhill | PO36: Newberry | PQ36: Hardin | PS36: Chambers | PW36: Waynesboro (City) | PY36: Walla Walla | QA36: Manitowoc | QH36: North_Dakota | QI36: ND | QJ36: 100 | QK36: 200 | QU36: FL16 | QV36: 4 | QW36: Virginia | QX36: Jackson | QZ36: Johnson | RA36: Larimer | RD36: Lee | RE36: Columbia | RF36: Oneida | RG36: Henderson | RH36: Jackson | RI36: Fremont | RJ36: Greeley | RK36: Natchitoches | RO36: Iron | RP36: Koochiching | RQ36: Lafayette | RR36: Franklin | RW36: Orange | RX36: Gaston | RY36: Highland | RZ36: Yamhill | SB36: Newberry | SC36: Hardin | SD36: Chambers | SF36: Dinwiddie | SG36: Walla Walla | SI36: Manitowoc | SN36: LEON
G37: 30 | H37: HO3 | I37: FL | J37: FL8 | K37: Annual | L37: 0.25 | X37: 30 | Y37: HO6 | Z37: FL | AA37: 19 | AB37: 0.25 | AD37: 30 | AE37: 29429 | AF37: Charleston | AG37: South Carolina | AH37: SC2 | AJ37: 30 | AK37: HO6 | AL37: CW | AM37: Frame | AN37: Annual | AO37: 1 | AQ37: 30 | AR37: DP3 | AS37: CW | AT37: Vacant | AU37: Annual | AV37: 1 | AX37: 30 | AY37: HO6 | AZ37: CW | BA37: 35 | BB37: 35 | BC37: Annual | BD37: 1.22 | BF37: 30 | BG37: DP3 | BH37: CW | BI37: 11 | BJ37: 999 | BK37: 6 | BL37: 10 | BM37: Annual | BN37: 0.975 | BP37: 30 | BQ37: HO6 | BR37: CW | BS37: Yes | BT37: Superior | BU37: 101 | BV37: 9999 | BW37: Annual | BX37: 0 | BZ37: 30 | CA37: HO6 | CB37: CW | CC37: 4 | CD37: Annual | CE37: 2 | CG37: 30 | CH37: HO3 | CI37: CW | CJ37: 100000 | CK37: 149999 | CL37: Annual | CM37: 1.35 | CS37: 30 | CT37: Builders Risk | CU37: CW | CV37: 2 | CW37: Monthly | CX37: 1.1 | CZ37: 30 | DA37: DP3 | DB37: CW | DC37: 5 | DD37: Annual | DE37: 1 | DG37: 30 | DH37: Builders Risk DP3 | DI37: CW | DJ37: CentralStationBurglarAlarm | DK37: Monthly | DL37: 0.95 | DN37: 30 | DO37: HO3 | DP37: NEW_BUSINESS | DQ37: FL | DR37: ALL | DS37: 33076 | DT37: 10000 | DU37: Annual | DV37: 1 | DX37: 30 | DY37: DP3 | DZ37: CW | EA37: 5000 | EC37: Annual | ED37: 0.9 | EM37: 30 | EN37: HO3 | EO37: CW | EP37: Reject | EQ37: -1 | ER37: -1 | ES37: Annual | ET37: 1.41 | EV37: 30 | EW37: HO3 | EX37: DE | EY37: 1 | EZ37: 1995 | FA37: 2999 | FB37: Y | FC37: Annual | FD37: 2.5 | FF37: 30 | FG37: HO3 | FH37: AL | FI37: 2 | FJ37: 5000 | FK37: Annual | FL37: 0.84 | GH37: 30 | GI37: HO6 | GJ37: CW | GK37: 39000 | GL37: 170 | GT37: 30 | GU37: DP1_Builders_Risk | GV37: SC | GW37: Yes | GX37: Masonry | GY37: Monthly | GZ37: 0.0125 | HB37: 30 | HC37: Builders Risk | HD37: SC | HE37: Yes | HF37: 10 | HG37: Monthly | HH37: 0.9 | IJ37: 30 | IK37: HO6 | IL37: CW | IM37: 0 | IN37: Annual | IO37: 0 | IQ37: 30 | IR37: DP3 | IS37: CW | IT37: 1000 | IU37: 0 | IW37: 30 | IX37: HO6 | IY37: MA | IZ37: 6 | JA37: 300 | JJ37: 30 | JK37: Rhode_Island | JL37: ALL | JM37: ALL | JN37: ALL | JO37: 1 | JP37: 1 | JQ37: 1 | JW37: 30 | JX37: Alabama | JY37: Franklin | KA37: 30 | KB37: VA7 | KC37: 0.4 | KE37: 30 | KF37: ALL | KG37: GA | KH37: 100 | KJ37: 30 | KK37: DP3 | KL37: Musical Instruments | KM37: 0.01 | NG37: Jefferson | NK37: Lafayette | NM37: Las Animas | NS37: Levy | NU37: Cook | NW37: Owyhee | NY37: Henry | OA37: Jasper | OC37: Greene | OE37: Greenwood | OG37: Ouachita | OO37: Isabella | OQ37: Lac qui Parle | OS37: Lamar | OU37: Gasconade | PE37: Orleans | PG37: Gates | PI37: Hocking | PO37: Oconee | PQ37: Hawkins | PS37: Cherokee | PW37: Williamsburg (City) | PY37: Whatcom | QA37: Marathon | QH37: Ohio | QI37: OH | QJ37: 100 | QK37: 200 | QU37: FL17 | QV37: 4 | QW37: Washington | QX37: Jefferson | QZ37: Lafayette | RA37: Las Animas | RD37: Leon | RE37: Cook | RF37: Owyhee | RG37: Henry | RH37: Jasper | RI37: Greene | RJ37: Greenwood | RK37: ORLEANS PARISH | RO37: Isabella | RP37: Lac qui Parle | RQ37: Lamar | RR37: Gasconade | RW37: Orleans | RX37: Gates | RY37: Hocking | SB37: Oconee | SC37: Hawkins | SD37: Cherokee | SF37: Emporia (City) | SG37: Whatcom | SI37: Marathon | SN37: LEVY
G38: 31 | H38: HO3 | I38: FL | J38: FL9 | K38: Annual | L38: 0.25 | X38: 31 | Y38: HO6 | Z38: FL | AA38: 20 | AB38: 0.25 | AD38: 31 | AE38: 29470 | AF38: Charleston | AG38: South Carolina | AH38: SC2 | AJ38: 31 | AK38: Builders Risk | AL38: CW | AM38: Adobe | AN38: Monthly | AO38: 1 | AQ38: 31 | AR38: Builders Risk | AS38: CW | AT38: Builders Risk | AU38: Monthly | AV38: 1 | AX38: 31 | AY38: HO6 | AZ38: CW | BA38: 36 | BB38: 36 | BC38: Annual | BD38: 1.23 | BF38: 31 | BG38: Builders Risk | BH38: CW | BI38: -1 | BJ38: 10 | BK38: -1 | BL38: 10 | BM38: Monthly | BN38: 1 | BP38: 31 | BQ38: HO6 | BR38: CW | BS38: Yes | BT38: Log Home | BU38: 101 | BV38: 9999 | BW38: Annual | BX38: 0 | BZ38: 31 | CA38: Builders Risk | CB38: CW | CC38: 0 | CD38: Monthly | CE38: 0.98 | CG38: 31 | CH38: HO3 | CI38: CW | CJ38: 150000 | CK38: 249999 | CL38: Annual | CM38: 1.2 | CS38: 31 | CT38: Builders Risk DP3 | CU38: CW | CV38: 2 | CW38: Monthly | CX38: 1.1 | CZ38: 31 | DA38: HO3 | DB38: CW | DC38: 6 | DD38: Annual | DE38: 1 | DG38: 31 | DH38: VDP1 | DI38: CW | DJ38: CentralStationBurglarAlarm | DK38: Monthly | DL38: 0.95 | DN38: 31 | DO38: HO3 | DP38: NEW_BUSINESS | DQ38: FL | DR38: ALL | DS38: 33101 | DT38: 10000 | DU38: Annual | DV38: 1 | DX38: 31 | DY38: HO3 | DZ38: CW | EA38: 50000 | EC38: Annual | ED38: 0.8 | EM38: 31 | EN38: HO3 | EO38: CW | EP38: Thin File | EQ38: -1 | ER38: -1 | ES38: Annual | ET38: 1.42 | EV38: 31 | EW38: HO3 | EX38: DE | EY38: 2 | EZ38: 0 | FA38: 1994 | FB38: Y | FC38: Annual | FD38: 2.25 | FF38: 31 | FG38: HO3 | FH38: AL | FI38: 2 | FJ38: 10000 | FK38: Annual | FL38: 0.7 | GH38: 31 | GI38: HO6 | GJ38: CW | GK38: 40000 | GL38: 175 | GT38: 31 | GU38: DP3_Builders_Risk | GV38: SC | GW38: Yes | GX38: Masonry | GY38: Monthly | GZ38: 0.0125 | HB38: 31 | HC38: Builders Risk DP3 | HD38: SC | HE38: Yes | HF38: 10 | HG38: Monthly | HH38: 0.9 | IJ38: 31 | IK38: HO6 | IL38: CW | IM38: 100000 | IN38: Annual | IO38: 15 | IQ38: 31 | IR38: DP3 | IS38: CW | IT38: 10000 | IU38: 40 | IW38: 31 | IX38: HO6 | IY38: MA | IZ38: 7 | JA38: 300 | JJ38: 31 | JK38: South_Carolina | JL38: ALL | JM38: ALL | JN38: ALL | JO38: 1 | JP38: 1 | JQ38: 1 | JW38: 31 | JX38: Alabama | JY38: Geneva | KA38: 31 | KB38: LA1 | KC38: 0.8 | KE38: 31 | KF38: ALL | KG38: CA | KH38: 100 | KJ38: 31 | KK38: HO3 | KL38: Silverware | KM38: 0.007 | NG38: Lamar | NK38: Lawrence | NM38: Lincoln | NS38: Liberty | NU38: Coweta | NW38: Payette | NY38: Iroquois | OA38: Jay | OC38: Grundy | OE38: Hamilton | OG38: Plaquemines | OO38: Jackson | OQ38: Lake | OS38: Lauderdale | OU38: Gentry | PE38: Oswego | PG38: Graham | PI38: Holmes | PO38: Orangeburg | PQ38: Haywood | PS38: Childress | PW38: Winchester (City) | PY38: Whitman | QA38: Marinette | QH38: Oklahoma | QI38: OK | QJ38: 100 | QK38: 200 | QU38: FL18 | QV38: 4 | QW38: Washington_DC | QX38: Lamar | QZ38: Lawrence | RA38: Lincoln | RD38: Levy | RE38: Coweta | RF38: Payette | RG38: Iroquois | RH38: Jay | RI38: Grundy | RJ38: Hamilton | RK38: Orleans | RO38: Jackson | RP38: Lake | RQ38: Lauderdale | RR38: Gentry | RW38: Oswego | RX38: Graham | RY38: Holmes | SB38: Orangeburg | SC38: Haywood | SD38: Childress | SF38: Essex | SG38: Whitman | SI38: Marinette | SN38: LIBERTY
G39: 32 | H39: HO3 | I39: GA | J39: GA1 | K39: Annual | L39: 0.23 | X39: 32 | Y39: HO6 | Z39: FL | AA39: 21 | AB39: 0.25 | AD39: 32 | AE39: 29483 | AF39: Dorchester | AG39: South Carolina | AH39: SC2 | AJ39: 32 | AK39: Builders Risk DP3 | AL39: CW | AM39: Adobe | AN39: Monthly | AO39: 1 | AQ39: 32 | AR39: Builders Risk DP3 | AS39: CW | AT39: Builders Risk | AU39: Monthly | AV39: 1 | AX39: 32 | AY39: HO6 | AZ39: CW | BA39: 37 | BB39: 37 | BC39: Annual | BD39: 1.24 | BF39: 32 | BG39: Builders Risk DP3 | BH39: CW | BI39: -1 | BJ39: 10 | BK39: -1 | BL39: 10 | BM39: Monthly | BN39: 1 | BP39: 32 | BQ39: HO6 | BR39: CW | BS39: Yes | BT39: Adobe | BU39: 101 | BV39: 9999 | BW39: Annual | BX39: 0 | BZ39: 32 | CA39: Builders Risk | CB39: CW | CC39: 1 | CD39: Monthly | CE39: 1 | CG39: 32 | CH39: HO3 | CI39: CW | CJ39: 250000 | CK39: 349999 | CL39: Annual | CM39: 1 | CS39: 32 | CT39: VDP1 | CU39: CW | CV39: 2 | CW39: Monthly | CX39: 1.1 | CZ39: 32 | DA39: HO5 | DB39: CW | DC39: 6 | DD39: Annual | DE39: 1 | DG39: 32 | DH39: VDP3 | DI39: CW | DJ39: CentralStationBurglarAlarm | DK39: Monthly | DL39: 0.95 | DN39: 32 | DO39: HO3 | DP39: NEW_BUSINESS | DQ39: FL | DR39: ALL | DS39: 33124 | DT39: 10000 | DU39: Annual | DV39: 1 | DX39: 32 | DY39: HO5 | DZ39: CW | EA39: 50000 | EC39: Annual | ED39: 0.8 | EM39: 32 | EN39: HO3 | EO39: HI | EP39: Not Applicable | EQ39: -1 | ER39: -1 | ES39: Annual | ET39: 0 | EV39: 32 | EW39: HO3 | EX39: DE | EY39: 2 | EZ39: 1995 | FA39: 2999 | FB39: Y | FC39: Annual | FD39: 2.5 | FF39: 32 | FG39: HO3 | FH39: AL | FI39: 2 | FJ39: 25000 | FK39: Annual | FL39: 0.67 | GH39: 32 | GI39: HO6 | GJ39: CW | GK39: 41000 | GL39: 180 | GT39: 32 | GU39: DP1_Vacant | GV39: SC | GW39: Yes | GX39: Masonry | GY39: Monthly | GZ39: 0.0125 | HB39: 32 | HC39: VDP1 | HD39: SC | HE39: Yes | HF39: 10 | HG39: Monthly | HH39: 0.9 | IJ39: 32 | IK39: HO6 | IL39: CW | IM39: 1000000 | IN39: Annual | IO39: 150 | IQ39: 32 | IR39: DP3 | IS39: CW | IT39: 2000 | IU39: 5 | IW39: 32 | IX39: HO6 | IY39: MA | IZ39: 8 | JA39: 300 | JJ39: 32 | JK39: Tennessee | JL39: ALL | JM39: ALL | JN39: ALL | JO39: 1 | JP39: 1 | JQ39: 1 | JW39: 32 | JX39: Alabama | JY39: Greene | KA39: 32 | KB39: LA9 | KC39: 0.8 | KE39: 32 | KF39: ALL | KG39: NV | KH39: 100 | KJ39: 32 | KK39: HO5 | KL39: Silverware | KM39: 0.007 | NG39: Lauderdale | NK39: Lee | NM39: Logan | NS39: Madison | NU39: Crawford | NW39: Power | NY39: Jackson | OA39: Jefferson | OC39: Guthrie | OE39: Harper | OG39: Pointe Coupee | OO39: Kalamazoo | OQ39: Lake of the Woods | OS39: Lawrence | OU39: Greene | PE39: Otsego | PG39: Granville | PI39: Huron | PO39: Pickens | PQ39: Henderson | PS39: Clay | PW39: Accomack | PY39: Yakima | QA39: Marquette | QH39: Oregon | QI39: OR | QJ39: 100 | QK39: 200 | QU39: FL19 | QV39: 4 | QW39: Wisconsin | QX39: Lauderdale | QZ39: Lee | RA39: Logan | RD39: Liberty | RE39: Crawford | RF39: Power | RG39: Jackson | RH39: Jefferson | RI39: Guthrie | RJ39: Harper | RK39: Ouachita | RO39: Kalamazoo | RP39: Lake of the Woods | RQ39: Lawrence | RR39: Greene | RW39: Otsego | RX39: Granville | RY39: Huron | SB39: Pickens | SC39: Henderson | SD39: Clay | SF39: Fairfax | SG39: Yakima | SI39: Marquette | SN39: MADISON
G40: 33 | H40: HO3 | I40: GA | J40: GA10 | K40: Annual | L40: 0.23 | X40: 33 | Y40: HO6 | Z40: FL | AA40: 22 | AB40: 0.25 | AD40: 33 | AE40: 29568 | AF40: Horry | AG40: South Carolina | AH40: SC3 | AJ40: 33 | AK40: VDP1 | AL40: CW | AM40: Adobe | AN40: Monthly | AO40: 1 | AQ40: 33 | AR40: VDP1 | AS40: CW | AT40: Builders Risk | AU40: Monthly | AV40: 1 | AX40: 33 | AY40: HO6 | AZ40: CW | BA40: 38 | BB40: 38 | BC40: Annual | BD40: 1.25 | BF40: 33 | BG40: VDP1 | BH40: CW | BI40: -1 | BJ40: 10 | BK40: -1 | BL40: 10 | BM40: Monthly | BN40: 1 | BP40: 33 | BQ40: HO6 | BR40: CW | BS40: Yes | BT40: Masonry | BU40: 0 | BV40: 3 | BW40: Annual | BX40: 1.05 | BZ40: 33 | CA40: Builders Risk | CB40: CW | CC40: 2 | CD40: Monthly | CE40: 1.1 | CG40: 33 | CH40: HO3 | CI40: CW | CJ40: 350000 | CK40: 499999 | CL40: Annual | CM40: 0.95 | CS40: 33 | CT40: VDP3 | CU40: CW | CV40: 2 | CW40: Monthly | CX40: 1.1 | CZ40: 33 | DA40: HO8 | DB40: CW | DC40: 6 | DD40: Annual | DE40: 1 | DG40: 33 | DH40: Builders Risk | DI40: CW | DJ40: CentralStationFireAlarm | DK40: Monthly | DL40: 0.95 | DN40: 33 | DO40: HO3 | DP40: NEW_BUSINESS | DQ40: FL | DR40: ALL | DS40: 33125 | DT40: 10000 | DU40: Annual | DV40: 1 | DX40: 33 | DY40: HO8 | DZ40: CW | EA40: 50000 | EC40: Annual | ED40: 0.8 | EM40: 33 | EN40: HO3 | EO40: KY | EP40: Not Applicable | EQ40: -1 | ER40: -1 | ES40: Annual | ET40: 0 | EV40: 33 | EW40: HO3 | EX40: DE | EY40: 3 | EZ40: 0 | FA40: 1994 | FB40: N | FC40: Annual | FD40: 0 | FF40: 33 | FG40: HO3 | FH40: AL | FI40: 2 | FJ40: 50000 | FK40: Annual | FL40: 0.63 | GH40: 33 | GI40: HO6 | GJ40: CW | GK40: 42000 | GL40: 185 | GT40: 33 | GU40: DP3_Vacant | GV40: SC | GW40: Yes | GX40: Masonry | GY40: Monthly | GZ40: 0.0125 | HB40: 33 | HC40: VDP3 | HD40: SC | HE40: Yes | HF40: 10 | HG40: Monthly | HH40: 0.9 | IJ40: 33 | IK40: HO6 | IL40: CW | IM40: 300000 | IN40: Annual | IO40: 25 | IQ40: 33 | IR40: DP3 | IS40: CW | IT40: 3000 | IU40: 10 | IW40: 33 | IX40: HO6 | IY40: MA | IZ40: 9 | JA40: 300 | JJ40: 33 | JK40: Texas | JL40: ALL | JM40: ALL | JN40: ALL | JO40: 1 | JP40: 1 | JQ40: 1 | JW40: 33 | JX40: Alabama | JY40: Hale | KA40: 33 | KB40: LA17 | KC40: 0.8 | KE40: 33 | KF40: ALL | KG40: KY | KH40: 100 | KJ40: 33 | KK40: HO8 | KL40: Silverware | KM40: 0.007 | NG40: Lawrence | NK40: Lincoln | NM40: Mesa | NS40: Manatee | NU40: Crisp | NW40: Shoshone | NY40: Jasper | OA40: Jennings | OC40: Hamilton | OE40: Harvey | OG40: Rapides | OO40: Kalkaska | OQ40: Le Sueur | OS40: Leake | OU40: Grundy | PE40: Putnam | PG40: Greene | PI40: Jackson | PO40: Richland | PQ40: Henry | PS40: Cochran | PW40: Albemarle | QA40: Menominee | QH40: Pennsylvania | QI40: PA | QJ40: 100 | QK40: 200 | QU40: FL20 | QV40: 4 | QX40: Lawrence | QZ40: Lincoln | RA40: Mesa | RD40: Madison | RE40: Crisp | RF40: Shoshone | RG40: Jasper | RH40: Jennings | RI40: Hamilton | RJ40: Harvey | RK40: Plaquemines | RO40: Kalkaska | RP40: Le Sueur | RQ40: Leake | RR40: Grundy | RW40: Putnam | RX40: Greene | RY40: Jackson | SB40: Richland | SC40: Henry | SD40: Cochran | SF40: Fairfax (City) | SI40: Menominee | SN40: MANATEE
G41: 34 | H41: HO3 | I41: GA | J41: GA11 | K41: Annual | L41: 0.23 | X41: 34 | Y41: HO6 | Z41: FL | AA41: 23 | AB41: 0.25 | AD41: 34 | AE41: 29585 | AF41: Georgetown | AG41: South Carolina | AH41: SC3 | AJ41: 34 | AK41: VDP3 | AL41: CW | AM41: Adobe | AN41: Monthly | AO41: 1 | AQ41: 34 | AR41: VDP3 | AS41: CW | AT41: Builders Risk | AU41: Monthly | AV41: 1 | AX41: 34 | AY41: HO6 | AZ41: CW | BA41: 39 | BB41: 39 | BC41: Annual | BD41: 1.27 | BF41: 34 | BG41: VDP3 | BH41: CW | BI41: -1 | BJ41: 10 | BK41: -1 | BL41: 10 | BM41: Monthly | BN41: 1 | BP41: 34 | BQ41: HO6 | BR41: CW | BS41: Yes | BT41: Steel | BU41: 0 | BV41: 3 | BW41: Annual | BX41: 1.05 | BZ41: 34 | CA41: Builders Risk | CB41: CW | CC41: 3 | CD41: Monthly | CE41: 1.5 | CG41: 34 | CH41: HO3 | CI41: CW | CJ41: 500000 | CK41: 1000000 | CL41: Annual | CM41: 0.9 | CS41: 34 | CT41: Builders Risk | CU41: CW | CV41: 3 | CW41: Monthly | CX41: 1.3 | CZ41: 34 | DA41: DP1 | DB41: CW | DC41: 6 | DD41: Annual | DE41: 1 | DG41: 34 | DH41: Builders Risk DP3 | DI41: CW | DJ41: CentralStationFireAlarm | DK41: Monthly | DL41: 0.95 | DN41: 34 | DO41: HO3 | DP41: NEW_BUSINESS | DQ41: FL | DR41: ALL | DS41: 33126 | DT41: 10000 | DU41: Annual | DV41: 1 | DX41: 34 | DY41: DP1 | DZ41: CW | EA41: 50000 | EC41: Annual | ED41: 0.8 | EM41: 34 | EN41: HO3 | EO41: MA | EP41: Not Applicable | EQ41: -1 | ER41: -1 | ES41: Annual | ET41: 0 | EV41: 34 | EW41: HO3 | EX41: DE | EY41: 3 | EZ41: 1995 | FA41: 2999 | FB41: N | FC41: Annual | FD41: 0 | FF41: 34 | FG41: HO3 | FH41: AL | FI41: 2 | FJ41: 80000 | FK41: Annual | FL41: 0.57 | GH41: 34 | GI41: HO6 | GJ41: CW | GK41: 43000 | GL41: 190 | GT41: 34 | GU41: DP1_Builders_Risk | GV41: SC | GW41: Yes | GX41: Reinforced Concrete | GY41: Monthly | GZ41: 0.0125 | HB41: 34 | HC41: Builders Risk | HD41: SC | HE41: Yes | HF41: 15 | HG41: Monthly | HH41: 0.8 | IJ41: 34 | IK41: HO6 | IL41: CW | IM41: 500000 | IN41: Annual | IO41: 50 | IQ41: 34 | IR41: DP3 | IS41: CW | IT41: 4000 | IU41: 15 | IW41: 34 | IX41: HO6 | IY41: MA | IZ41: 10 | JA41: 300 | JJ41: 34 | JK41: Utah | JL41: ALL | JM41: ALL | JN41: ALL | JO41: 1 | JP41: 1 | JQ41: 1 | JW41: 34 | JX41: Alabama | JY41: Henry | KA41: 34 | KB41: MS2 | KC41: 0.8 | KE41: 34 | KF41: ALL | KG41: WA | KH41: 100 | KJ41: 34 | KK41: DP1 | KL41: Silverware | KM41: 0.007 | NG41: Lee | NK41: Little River | NM41: Mineral | NS41: Marion | NU41: Dade | NW41: Teton | NY41: Jefferson | OA41: Johnson | OC41: Hancock | OE41: Haskell | OG41: Red River | OO41: Kent | OQ41: Lincoln | OS41: Lee | OU41: Harrison | PE41: Queens | PG41: Guilford | PI41: Jefferson | PO41: Saluda | PQ41: Hickman | PS41: Coke | PW41: Alleghany | QA41: Milwaukee | QH41: Rhode_Island | QI41: RI | QJ41: 100 | QK41: 200 | QU41: FL21 | QV41: 4 | QX41: Lee | QZ41: Little River | RA41: Mineral | RD41: Manatee | RE41: Dade | RF41: Teton | RG41: Jefferson | RH41: Johnson | RI41: Hancock | RJ41: Haskell | RK41: Pointe Coupee | RO41: Kent | RP41: Lincoln | RQ41: Lee | RR41: Harrison | RW41: Queens | RX41: Guilford | RY41: Jefferson | SB41: Saluda | SC41: Hickman | SD41: Coke | SF41: Falls Church (City) | SI41: Milwaukee | SN41: MARION
G42: 35 | H42: HO3 | I42: GA | J42: GA2 | K42: Annual | L42: 0.2 | X42: 35 | Y42: HO6 | Z42: FL | AA42: 24 | AB42: 0.25 | AD42: 35 | AE42: ALL | AF42: Georgetown | AG42: South Carolina | AH42: SC6 | AJ42: 35 | AK42: HO6 | AL42: CW | AM42: Adobe | AN42: Annual | AO42: 1 | AQ42: 35 | AR42: Builders Risk | AS42: CW | AT42: Long-Term Rental | AU42: Monthly | AV42: 1 | AX42: 35 | AY42: HO6 | AZ42: CW | BA42: 4 | BB42: 4 | BC42: Annual | BD42: 0.84 | BF42: 35 | BG42: Builders Risk | BH42: CW | BI42: 11 | BJ42: 999 | BK42: -1 | BL42: 5 | BM42: Monthly | BN42: 0.95 | BP42: 35 | BQ42: HO6 | BR42: CW | BS42: Yes | BT42: Reinforced Concrete | BU42: 0 | BV42: 3 | BW42: Annual | BX42: 1.05 | BZ42: 35 | CA42: Builders Risk | CB42: CW | CC42: 4 | CD42: Monthly | CE42: 2 | CG42: 35 | CH42: HO3 | CI42: CW | CJ42: 1000001 | CK42: 9999999999 | CL42: Annual | CM42: 0.85 | CS42: 35 | CT42: Builders Risk DP3 | CU42: CW | CV42: 3 | CW42: Monthly | CX42: 1.3 | CZ42: 35 | DA42: DP3 | DB42: CW | DC42: 6 | DD42: Annual | DE42: 1 | DG42: 35 | DH42: VDP1 | DI42: CW | DJ42: CentralStationFireAlarm | DK42: Monthly | DL42: 0.95 | DN42: 35 | DO42: HO3 | DP42: NEW_BUSINESS | DQ42: FL | DR42: ALL | DS42: 33127 | DT42: 10000 | DU42: Annual | DV42: 1 | DX42: 35 | DY42: DP3 | DZ42: CW | EA42: 50000 | EC42: Annual | ED42: 0.8 | EM42: 35 | EN42: HO3 | EO42: MD | EP42: Not Applicable | EQ42: -1 | ER42: -1 | ES42: Annual | ET42: 0 | EV42: 35 | EW42: HO3 | EX42: FL | EY42: 1 | EZ42: 0 | FA42: 1994 | FB42: Y | FC42: Annual | FD42: 0 | FF42: 35 | FG42: HO3 | FH42: AL | FI42: 2 | FJ42: 130000 | FK42: Annual | FL42: 0.57 | GH42: 35 | GI42: HO6 | GJ42: CW | GK42: 44000 | GL42: 195 | GT42: 35 | GU42: DP3_Builders_Risk | GV42: SC | GW42: Yes | GX42: Reinforced Concrete | GY42: Monthly | GZ42: 0.0125 | HB42: 35 | HC42: Builders Risk DP3 | HD42: SC | HE42: Yes | HF42: 15 | HG42: Monthly | HH42: 0.8 | IJ42: 35 | IK42: DP3_Builders_Risk | IL42: CW | IM42: 100000 | IN42: Monthly | IO42: 15 | IQ42: 35 | IR42: DP3 | IS42: CW | IT42: 5000 | IU42: 20 | IW42: 35 | IX42: HO6 | IY42: NH | IZ42: 1 | JA42: 300 | JJ42: 35 | JK42: Virginia | JL42: ALL | JM42: ALL | JN42: ALL | JO42: 1 | JP42: 1 | JQ42: 1 | JW42: 35 | JX42: Alabama | JY42: Houston | KA42: 35 | KB42: AL1 | KC42: 0.8 | KE42: 35 | KF42: ALL | KG42: MD | KH42: 100 | KJ42: 35 | KK42: DP3 | KL42: Silverware | KM42: 0.007 | NG42: Limestone | NK42: Logan | NM42: Moffat | NS42: Martin | NU42: Dawson | NW42: Twin Falls | NY42: Jersey | OA42: Knox | OC42: Hardin | OE42: Hodgeman | OG42: Richland | OO42: Keweenaw | OQ42: Lyon | OS42: Leflore | OU42: Henry | PE42: Rensselaer | PG42: Halifax | PI42: Knox | PO42: Spartanburg | PQ42: Houston | PS42: Coleman | PW42: Amelia | QA42: Monroe | QH42: South_Carolina | QI42: SC | QJ42: 100 | QK42: 200 | QU42: FL22 | QV42: 4 | QX42: Limestone | QZ42: Logan | RA42: Moffat | RD42: Marion | RE42: Dawson | RF42: Twin Falls | RG42: Jersey | RH42: Knox | RI42: Hardin | RJ42: Hodgeman | RK42: Rapides | RO42: Keweenaw | RP42: Lyon | RQ42: Leflore | RR42: Henry | RW42: Rensselaer | RX42: Halifax | RY42: Knox | SB42: Spartanburg | SC42: Houston | SD42: Coleman | SF42: Fauquier | SI42: Monroe | SN42: MARTIN
